Workbook

Sheet Instructions
B2: NDPA 2023 / GAID 2025 Compliance Audit Work Plan
B3: Typical Nigerian University — prepared to support the annual Compliance Audit Returns (CAR) under GAID Article 10
B5: Purpose | C5: Risk-based audit work plan covering every faculty, school, directorate and central department so the University can evidence compliance and file its CAR (Schedule 2 template) through a licensed DPCO.
B6: Audit period | C6: 1 January – 31 December 2026 (audit year). Fieldwork Nov 2026 – Feb 2027. CAR filing deadline: 31 March 2027 (GAID Art. 10(7)).
B7: Assumption | C7: The University is a Data Controller of Major Importance (likely EHL as a public institution). Confirm the actual level against Schedule 7 — only UHL/EHL file CAR; OHL renews registration instead (Art. 9(2)-(3)).
B8: Structure | C8: Dashboard = audit universe + live scores. CAR Framework = base controls applied to every unit. Timeline = audit phases. One tab per unit, prefixed CEN / DIR / DEPT / FAC / SCH.
B9: Academic departments | C9: Academic departments (e.g., Dept. of Economics) sit inside their faculty tab — the faculty audit samples records at department level. Add a tab per academic department by copying a faculty tab if needed.
B10: Cells to edit | C10: Yellow cells only: unit header details (Head of Unit, Lead Auditor, planned dates), Risk, Auditor, Status, Compliance Rating, Findings, Recommendation, Management Response, Target Date. Blue-header columns are reference content. Grey cells are formulas — do not overwrite.
B11: Scoring | C11: Compliant = 100%, Partially Compliant = 50%, Non-Compliant = 0%, Not Applicable = excluded. Unit score = average of rated controls; it flows to the Dashboard automatically.
B12: Planned dates | C12: Each control row inherits the unit's planned start/end from the header. Change the header dates and all rows update; overwrite a row date only if that control is scheduled separately.
B13: Source | C13: Nigeria Data Protection Commission, NDP Act General Application and Implementation Directive (GAID) 2025, NDPC/NDP ACT-GAID/01/2025, issued 20 March 2025, effective 19 September 2025 — ndpc.gov.ng. Unit profiles are typical assumptions; adjust to the actual institution.
B15: Legend
C16: Input cell — fill in during the audit
C17: Formula cell — calculated automatically
C18: Reference / plan content
B20: Example of a completed control row
B21: Ref | C21: DEPT-ADM-04
B22: CAR Area | C22: Consent (CAR disclosure)
B23: Risk | C23: High
B24: Auditor | C24: A. Bello
B25: Status | C25: Completed
B26: Compliance Rating | C26: Partially Compliant
B27: Findings | C27: Admissions portal captures DOB but has no parental consent step for applicants under 18; 212 applicants aged 16–17 in 2026 cycle.
B28: Recommendation | C28: Add guardian consent screen for under-18 applicants; retro-notify guardians of current minors.
B29: Management Response | C29: Agreed. Owner: Admissions Officer with DICT. Target: 30 April 2027.

Sheet Dashboard
A1: Audit Universe & Compliance Dashboard
A2: Typical Nigerian University — NDPA 2023 / GAID 2025 Art. 10 CAR audit (2026 audit year, filing by 31 March 2027). Scores update from each unit tab.
A4: Summary by Unit Type
A5: Unit Type | B5: No. of Units | C5: Controls | D5: Completed | E5: Non-Compliant | F5: Avg. Score
A6: Central Governance | B6: =COUNTIF($C$14:$C$51,A6) -> 1 | C6: =SUMIF($C$14:$C$51,A6,$H$14:$H$51) -> 39 | D6: =SUMIF($C$14:$C$51,A6,$I$14:$I$51) -> 0 | E6: =SUMIF($C$14:$C$51,A6,$L$14:$L$51) -> 0 | F6: =_xlfn.IFERROR(_xlfn.AVERAGEIF($C$14:$C$51,A6,$M$14:$M$51),"")
A7: Directorate | B7: =COUNTIF($C$14:$C$51,A7) -> 10 | C7: =SUMIF($C$14:$C$51,A7,$H$14:$H$51) -> 248 | D7: =SUMIF($C$14:$C$51,A7,$I$14:$I$51) -> 0 | E7: =SUMIF($C$14:$C$51,A7,$L$14:$L$51) -> 0 | F7: =_xlfn.IFERROR(_xlfn.AVERAGEIF($C$14:$C$51,A7,$M$14:$M$51),"")
A8: Department | B8: =COUNTIF($C$14:$C$51,A8) -> 9 | C8: =SUMIF($C$14:$C$51,A8,$H$14:$H$51) -> 218 | D8: =SUMIF($C$14:$C$51,A8,$I$14:$I$51) -> 0 | E8: =SUMIF($C$14:$C$51,A8,$L$14:$L$51) -> 0 | F8: =_xlfn.IFERROR(_xlfn.AVERAGEIF($C$14:$C$51,A8,$M$14:$M$51),"")
A9: Faculty | B9: =COUNTIF($C$14:$C$51,A9) -> 13 | C9: =SUMIF($C$14:$C$51,A9,$H$14:$H$51) -> 306 | D9: =SUMIF($C$14:$C$51,A9,$I$14:$I$51) -> 0 | E9: =SUMIF($C$14:$C$51,A9,$L$14:$L$51) -> 0 | F9: =_xlfn.IFERROR(_xlfn.AVERAGEIF($C$14:$C$51,A9,$M$14:$M$51),"")
A10: School | B10: =COUNTIF($C$14:$C$51,A10) -> 5 | C10: =SUMIF($C$14:$C$51,A10,$H$14:$H$51) -> 122 | D10: =SUMIF($C$14:$C$51,A10,$I$14:$I$51) -> 0 | E10: =SUMIF($C$14:$C$51,A10,$L$14:$L$51) -> 0 | F10: =_xlfn.IFERROR(_xlfn.AVERAGEIF($C$14:$C$51,A10,$M$14:$M$51),"")
A11: University Total | B11: =SUM(B6:B10) -> 38 | C11: =SUM(C6:C10) -> 933 | D11: =SUM(D6:D10) -> 0 | E11: =SUM(E6:E10) -> 0 | F11: =_xlfn.IFERROR(AVERAGE($M$14:$M$51),"")
A12: Audit Universe
A13: # | B13: Unit | C13: Unit Type | D13: Reports To | E13: Head of Unit | F13: Inherent Risk | G13: Planned Start | H13: Controls | I13: Completed | J13: Compliant | K13: Partial | L13: Non-Compliant | M13: Score | N13: Open Tab
A14: 1 | B14: Data Protection Office (DPO) & Central Governance | C14: Central Governance | D14: Vice-Chancellor / University Management | E14: ='CEN-DPO Office'!C7 -> [Enter name] | F14: ='CEN-DPO Office'!C11 -> High | G14: ='CEN-DPO Office'!K5 -> 46328 | H14: ='CEN-DPO Office'!K7 -> 39 | I14: ='CEN-DPO Office'!K8 -> 0 | J14: ='CEN-DPO Office'!K9 -> 0 | K14: ='CEN-DPO Office'!K10 -> 0 | L14: ='CEN-DPO Office'!K11 -> 0 | M14: ='CEN-DPO Office'!K13 | N14: Open →
A15: 2 | B15: Directorate of Information & Communication Technology (DICT) | C15: Directorate | D15: Vice-Chancellor | E15: ='DIR-ICT'!C7 -> [Enter name] | F15: ='DIR-ICT'!C11 -> High | G15: ='DIR-ICT'!K5 -> 46342 | H15: ='DIR-ICT'!K7 -> 28 | I15: ='DIR-ICT'!K8 -> 0 | J15: ='DIR-ICT'!K9 -> 0 | K15: ='DIR-ICT'!K10 -> 0 | L15: ='DIR-ICT'!K11 -> 0 | M15: ='DIR-ICT'!K13 | N15: Open →
A16: 3 | B16: Directorate of Academic Planning | C16: Directorate | D16: Vice-Chancellor | E16: ='DIR-Academic Planning'!C7 -> [Enter name] | F16: ='DIR-Academic Planning'!C11 -> Medium | G16: ='DIR-Academic Planning'!K5 -> 46342 | H16: ='DIR-Academic Planning'!K7 -> 24 | I16: ='DIR-Academic Planning'!K8 -> 0 | J16: ='DIR-Academic Planning'!K9 -> 0 | K16: ='DIR-Academic Planning'!K10 -> 0 | L16: ='DIR-Academic Planning'!K11 -> 0 | M16: ='DIR-Academic Planning'!K13 | N16: Open →
A17: 4 | B17: Directorate of Quality Assurance | C17: Directorate | D17: Vice-Chancellor | E17: ='DIR-Quality Assurance'!C7 -> [Enter name] | F17: ='DIR-Quality Assurance'!C11 -> Medium | G17: ='DIR-Quality Assurance'!K5 -> 46342 | H17: ='DIR-Quality Assurance'!K7 -> 24 | I17: ='DIR-Quality Assurance'!K8 -> 0 | J17: ='DIR-Quality Assurance'!K9 -> 0 | K17: ='DIR-Quality Assurance'!K10 -> 0 | L17: ='DIR-Quality Assurance'!K11 -> 0 | M17: ='DIR-Quality Assurance'!K13 | N17: Open →
A18: 5 | B18: Directorate of Physical Planning & Works | C18: Directorate | D18: Vice-Chancellor | E18: ='DIR-Physical Planning'!C7 -> [Enter name] | F18: ='DIR-Physical Planning'!C11 -> Low | G18: ='DIR-Physical Planning'!K5 -> 46342 | H18: ='DIR-Physical Planning'!K7 -> 23 | I18: ='DIR-Physical Planning'!K8 -> 0 | J18: ='DIR-Physical Planning'!K9 -> 0 | K18: ='DIR-Physical Planning'!K10 -> 0 | L18: ='DIR-Physical Planning'!K11 -> 0 | M18: ='DIR-Physical Planning'!K13 | N18: Open →
A19: 6 | B19: Directorate of Health Services (University Health Centre) | C19: Directorate | D19: Vice-Chancellor | E19: ='DIR-Health Services'!C7 -> [Enter name] | F19: ='DIR-Health Services'!C11 -> High | G19: ='DIR-Health Services'!K5 -> 46342 | H19: ='DIR-Health Services'!K7 -> 26 | I19: ='DIR-Health Services'!K8 -> 0 | J19: ='DIR-Health Services'!K9 -> 0 | K19: ='DIR-Health Services'!K10 -> 0 | L19: ='DIR-Health Services'!K11 -> 0 | M19: ='DIR-Health Services'!K13 | N19: Open →
A20: 7 | B20: Directorate of Security Services | C20: Directorate | D20: Vice-Chancellor | E20: ='DIR-Security Services'!C7 -> [Enter name] | F20: ='DIR-Security Services'!C11 -> High | G20: ='DIR-Security Services'!K5 -> 46342 | H20: ='DIR-Security Services'!K7 -> 26 | I20: ='DIR-Security Services'!K8 -> 0 | J20: ='DIR-Security Services'!K9 -> 0 | K20: ='DIR-Security Services'!K10 -> 0 | L20: ='DIR-Security Services'!K11 -> 0 | M20: ='DIR-Security Services'!K13 | N20: Open →
A21: 8 | B21: Directorate of Research, Innovation & Development | C21: Directorate | D21: DVC (Research) | E21: ='DIR-Research & Dev'!C7 -> [Enter name] | F21: ='DIR-Research & Dev'!C11 -> Medium | G21: ='DIR-Research & Dev'!K5 -> 46342 | H21: ='DIR-Research & Dev'!K7 -> 24 | I21: ='DIR-Research & Dev'!K8 -> 0 | J21: ='DIR-Research & Dev'!K9 -> 0 | K21: ='DIR-Research & Dev'!K10 -> 0 | L21: ='DIR-Research & Dev'!K11 -> 0 | M21: ='DIR-Research & Dev'!K13 | N21: Open →
A22: 9 | B22: Directorate of Linkages & International Collaborations | C22: Directorate | D22: Vice-Chancellor | E22: ='DIR-Linkages'!C7 -> [Enter name] | F22: ='DIR-Linkages'!C11 -> High | G22: ='DIR-Linkages'!K5 -> 46342 | H22: ='DIR-Linkages'!K7 -> 24 | I22: ='DIR-Linkages'!K8 -> 0 | J22: ='DIR-Linkages'!K9 -> 0 | K22: ='DIR-Linkages'!K10 -> 0 | L22: ='DIR-Linkages'!K11 -> 0 | M22: ='DIR-Linkages'!K13 | N22: Open →
A23: 10 | B23: Directorate of Student Affairs | C23: Directorate | D23: DVC (Academic) | E23: ='DIR-Student Affairs'!C7 -> [Enter name] | F23: ='DIR-Student Affairs'!C11 -> High | G23: ='DIR-Student Affairs'!K5 -> 46342 | H23: ='DIR-Student Affairs'!K7 -> 25 | I23: ='DIR-Student Affairs'!K8 -> 0 | J23: ='DIR-Student Affairs'!K9 -> 0 | K23: ='DIR-Student Affairs'!K10 -> 0 | L23: ='DIR-Student Affairs'!K11 -> 0 | M23: ='DIR-Student Affairs'!K13 | N23: Open →
A24: 11 | B24: Directorate of Advancement, Alumni & Endowment | C24: Directorate | D24: Vice-Chancellor | E24: ='DIR-Advancement'!C7 -> [Enter name] | F24: ='DIR-Advancement'!C11 -> Medium | G24: ='DIR-Advancement'!K5 -> 46342 | H24: ='DIR-Advancement'!K7 -> 24 | I24: ='DIR-Advancement'!K8 -> 0 | J24: ='DIR-Advancement'!K9 -> 0 | K24: ='DIR-Advancement'!K10 -> 0 | L24: ='DIR-Advancement'!K11 -> 0 | M24: ='DIR-Advancement'!K13 | N24: Open →
A25: 12 | B25: Registry – Establishments / Human Resources | C25: Department | D25: Registrar | E25: ='DEPT-HR Establishments'!C7 -> [Enter name] | F25: ='DEPT-HR Establishments'!C11 -> High | G25: ='DEPT-HR Establishments'!K5 -> 46391 | H25: ='DEPT-HR Establishments'!K7 -> 25 | I25: ='DEPT-HR Establishments'!K8 -> 0 | J25: ='DEPT-HR Establishments'!K9 -> 0 | K25: ='DEPT-HR Establishments'!K10 -> 0 | L25: ='DEPT-HR Establishments'!K11 -> 0 | M25: ='DEPT-HR Establishments'!K13 | N25: Open →
A26: 13 | B26: Registry – Admissions Office | C26: Department | D26: Registrar | E26: ='DEPT-Admissions'!C7 -> [Enter name] | F26: ='DEPT-Admissions'!C11 -> High | G26: ='DEPT-Admissions'!K5 -> 46391 | H26: ='DEPT-Admissions'!K7 -> 26 | I26: ='DEPT-Admissions'!K8 -> 0 | J26: ='DEPT-Admissions'!K9 -> 0 | K26: ='DEPT-Admissions'!K10 -> 0 | L26: ='DEPT-Admissions'!K11 -> 0 | M26: ='DEPT-Admissions'!K13 | N26: Open →
A27: 14 | B27: Registry – Examinations & Records | C27: Department | D27: Registrar | E27: ='DEPT-Exams & Records'!C7 -> [Enter name] | F27: ='DEPT-Exams & Records'!C11 -> High | G27: ='DEPT-Exams & Records'!K5 -> 46391 | H27: ='DEPT-Exams & Records'!K7 -> 24 | I27: ='DEPT-Exams & Records'!K8 -> 0 | J27: ='DEPT-Exams & Records'!K9 -> 0 | K27: ='DEPT-Exams & Records'!K10 -> 0 | L27: ='DEPT-Exams & Records'!K11 -> 0 | M27: ='DEPT-Exams & Records'!K13 | N27: Open →
A28: 15 | B28: Registry – Council & Senate Affairs | C28: Department | D28: Registrar | E28: ='DEPT-Council & Senate'!C7 -> [Enter name] | F28: ='DEPT-Council & Senate'!C11 -> Medium | G28: ='DEPT-Council & Senate'!K5 -> 46391 | H28: ='DEPT-Council & Senate'!K7 -> 23 | I28: ='DEPT-Council & Senate'!K8 -> 0 | J28: ='DEPT-Council & Senate'!K9 -> 0 | K28: ='DEPT-Council & Senate'!K10 -> 0 | L28: ='DEPT-Council & Senate'!K11 -> 0 | M28: ='DEPT-Council & Senate'!K13 | N28: Open →
A29: 16 | B29: Bursary Department | C29: Department | D29: Vice-Chancellor | E29: ='DEPT-Bursary'!C7 -> [Enter name] | F29: ='DEPT-Bursary'!C11 -> High | G29: ='DEPT-Bursary'!K5 -> 46391 | H29: ='DEPT-Bursary'!K7 -> 24 | I29: ='DEPT-Bursary'!K8 -> 0 | J29: ='DEPT-Bursary'!K9 -> 0 | K29: ='DEPT-Bursary'!K10 -> 0 | L29: ='DEPT-Bursary'!K11 -> 0 | M29: ='DEPT-Bursary'!K13 | N29: Open →
A30: 17 | B30: University Library | C30: Department | D30: Vice-Chancellor | E30: ='DEPT-Library'!C7 -> [Enter name] | F30: ='DEPT-Library'!C11 -> Medium | G30: ='DEPT-Library'!K5 -> 46391 | H30: ='DEPT-Library'!K7 -> 24 | I30: ='DEPT-Library'!K8 -> 0 | J30: ='DEPT-Library'!K9 -> 0 | K30: ='DEPT-Library'!K10 -> 0 | L30: ='DEPT-Library'!K11 -> 0 | M30: ='DEPT-Library'!K13 | N30: Open →
A31: 18 | B31: Legal Unit | C31: Department | D31: Registrar | E31: ='DEPT-Legal Unit'!C7 -> [Enter name] | F31: ='DEPT-Legal Unit'!C11 -> Medium | G31: ='DEPT-Legal Unit'!K5 -> 46391 | H31: ='DEPT-Legal Unit'!K7 -> 25 | I31: ='DEPT-Legal Unit'!K8 -> 0 | J31: ='DEPT-Legal Unit'!K9 -> 0 | K31: ='DEPT-Legal Unit'!K10 -> 0 | L31: ='DEPT-Legal Unit'!K11 -> 0 | M31: ='DEPT-Legal Unit'!K13 | N31: Open →
A32: 19 | B32: Information, Public Relations & Protocol | C32: Department | D32: Vice-Chancellor | E32: ='DEPT-Info & PR'!C7 -> [Enter name] | F32: ='DEPT-Info & PR'!C11 -> Medium | G32: ='DEPT-Info & PR'!K5 -> 46391 | H32: ='DEPT-Info & PR'!K7 -> 24 | I32: ='DEPT-Info & PR'!K8 -> 0 | J32: ='DEPT-Info & PR'!K9 -> 0 | K32: ='DEPT-Info & PR'!K10 -> 0 | L32: ='DEPT-Info & PR'!K11 -> 0 | M32: ='DEPT-Info & PR'!K13 | N32: Open →
A33: 20 | B33: Procurement Department | C33: Department | D33: Vice-Chancellor | E33: ='DEPT-Procurement'!C7 -> [Enter name] | F33: ='DEPT-Procurement'!C11 -> Medium | G33: ='DEPT-Procurement'!K5 -> 46391 | H33: ='DEPT-Procurement'!K7 -> 23 | I33: ='DEPT-Procurement'!K8 -> 0 | J33: ='DEPT-Procurement'!K9 -> 0 | K33: ='DEPT-Procurement'!K10 -> 0 | L33: ='DEPT-Procurement'!K11 -> 0 | M33: ='DEPT-Procurement'!K13 | N33: Open →
A34: 21 | B34: Faculty of Arts | C34: Faculty | D34: DVC (Academic) | E34: ='FAC-Arts'!C7 -> [Enter name] | F34: ='FAC-Arts'!C11 -> Medium | G34: ='FAC-Arts'!K5 -> 46412 | H34: ='FAC-Arts'!K7 -> 23 | I34: ='FAC-Arts'!K8 -> 0 | J34: ='FAC-Arts'!K9 -> 0 | K34: ='FAC-Arts'!K10 -> 0 | L34: ='FAC-Arts'!K11 -> 0 | M34: ='FAC-Arts'!K13 | N34: Open →
A35: 22 | B35: Faculty of Education | C35: Faculty | D35: DVC (Academic) | E35: ='FAC-Education'!C7 -> [Enter name] | F35: ='FAC-Education'!C11 -> High | G35: ='FAC-Education'!K5 -> 46412 | H35: ='FAC-Education'!K7 -> 24 | I35: ='FAC-Education'!K8 -> 0 | J35: ='FAC-Education'!K9 -> 0 | K35: ='FAC-Education'!K10 -> 0 | L35: ='FAC-Education'!K11 -> 0 | M35: ='FAC-Education'!K13 | N35: Open →
A36: 23 | B36: Faculty of Engineering | C36: Faculty | D36: DVC (Academic) | E36: ='FAC-Engineering'!C7 -> [Enter name] | F36: ='FAC-Engineering'!C11 -> Medium | G36: ='FAC-Engineering'!K5 -> 46412 | H36: ='FAC-Engineering'!K7 -> 23 | I36: ='FAC-Engineering'!K8 -> 0 | J36: ='FAC-Engineering'!K9 -> 0 | K36: ='FAC-Engineering'!K10 -> 0 | L36: ='FAC-Engineering'!K11 -> 0 | M36: ='FAC-Engineering'!K13 | N36: Open →
A37: 24 | B37: Faculty of Law | C37: Faculty | D37: DVC (Academic) | E37: ='FAC-Law'!C7 -> [Enter name] | F37: ='FAC-Law'!C11 -> High | G37: ='FAC-Law'!K5 -> 46412 | H37: ='FAC-Law'!K7 -> 24 | I37: ='FAC-Law'!K8 -> 0 | J37: ='FAC-Law'!K9 -> 0 | K37: ='FAC-Law'!K10 -> 0 | L37: ='FAC-Law'!K11 -> 0 | M37: ='FAC-Law'!K13 | N37: Open →
A38: 25 | B38: Faculty of Management Sciences | C38: Faculty | D38: DVC (Academic) | E38: ='FAC-Management Sciences'!C7 -> [Enter name] | F38: ='FAC-Management Sciences'!C11 -> Medium | G38: ='FAC-Management Sciences'!K5 -> 46412 | H38: ='FAC-Management Sciences'!K7 -> 23 | I38: ='FAC-Management Sciences'!K8 -> 0 | J38: ='FAC-Management Sciences'!K9 -> 0 | K38: ='FAC-Management Sciences'!K10 -> 0 | L38: ='FAC-Management Sciences'!K11 -> 0 | M38: ='FAC-Management Sciences'!K13 | N38: Open →
A39: 26 | B39: Faculty of Science | C39: Faculty | D39: DVC (Academic) | E39: ='FAC-Science'!C7 -> [Enter name] | F39: ='FAC-Science'!C11 -> Medium | G39: ='FAC-Science'!K5 -> 46412 | H39: ='FAC-Science'!K7 -> 23 | I39: ='FAC-Science'!K8 -> 0 | J39: ='FAC-Science'!K9 -> 0 | K39: ='FAC-Science'!K10 -> 0 | L39: ='FAC-Science'!K11 -> 0 | M39: ='FAC-Science'!K13 | N39: Open →
A40: 27 | B40: Faculty of Social Sciences | C40: Faculty | D40: DVC (Academic) | E40: ='FAC-Social Sciences'!C7 -> [Enter name] | F40: ='FAC-Social Sciences'!C11 -> High | G40: ='FAC-Social Sciences'!K5 -> 46412 | H40: ='FAC-Social Sciences'!K7 -> 24 | I40: ='FAC-Social Sciences'!K8 -> 0 | J40: ='FAC-Social Sciences'!K9 -> 0 | K40: ='FAC-Social Sciences'!K10 -> 0 | L40: ='FAC-Social Sciences'!K11 -> 0 | M40: ='FAC-Social Sciences'!K13 | N40: Open →
A41: 28 | B41: Faculty of Agriculture | C41: Faculty | D41: DVC (Academic) | E41: ='FAC-Agriculture'!C7 -> [Enter name] | F41: ='FAC-Agriculture'!C11 -> Low | G41: ='FAC-Agriculture'!K5 -> 46412 | H41: ='FAC-Agriculture'!K7 -> 23 | I41: ='FAC-Agriculture'!K8 -> 0 | J41: ='FAC-Agriculture'!K9 -> 0 | K41: ='FAC-Agriculture'!K10 -> 0 | L41: ='FAC-Agriculture'!K11 -> 0 | M41: ='FAC-Agriculture'!K13 | N41: Open →
A42: 29 | B42: Faculty of Environmental Sciences | C42: Faculty | D42: DVC (Academic) | E42: ='FAC-Environmental Sci'!C7 -> [Enter name] | F42: ='FAC-Environmental Sci'!C11 -> Medium | G42: ='FAC-Environmental Sci'!K5 -> 46412 | H42: ='FAC-Environmental Sci'!K7 -> 23 | I42: ='FAC-Environmental Sci'!K8 -> 0 | J42: ='FAC-Environmental Sci'!K9 -> 0 | K42: ='FAC-Environmental Sci'!K10 -> 0 | L42: ='FAC-Environmental Sci'!K11 -> 0 | M42: ='FAC-Environmental Sci'!K13 | N42: Open →
A43: 30 | B43: Faculty of Pharmaceutical Sciences | C43: Faculty | D43: DVC (Academic) | E43: ='FAC-Pharmaceutical Sci'!C7 -> [Enter name] | F43: ='FAC-Pharmaceutical Sci'!C11 -> High | G43: ='FAC-Pharmaceutical Sci'!K5 -> 46412 | H43: ='FAC-Pharmaceutical Sci'!K7 -> 23 | I43: ='FAC-Pharmaceutical Sci'!K8 -> 0 | J43: ='FAC-Pharmaceutical Sci'!K9 -> 0 | K43: ='FAC-Pharmaceutical Sci'!K10 -> 0 | L43: ='FAC-Pharmaceutical Sci'!K11 -> 0 | M43: ='FAC-Pharmaceutical Sci'!K13 | N43: Open →
A44: 31 | B44: Faculty of Basic Medical Sciences | C44: Faculty | D44: Provost, College of Health Sciences | E44: ='FAC-Basic Medical Sci'!C7 -> [Enter name] | F44: ='FAC-Basic Medical Sci'!C11 -> High | G44: ='FAC-Basic Medical Sci'!K5 -> 46412 | H44: ='FAC-Basic Medical Sci'!K7 -> 24 | I44: ='FAC-Basic Medical Sci'!K8 -> 0 | J44: ='FAC-Basic Medical Sci'!K9 -> 0 | K44: ='FAC-Basic Medical Sci'!K10 -> 0 | L44: ='FAC-Basic Medical Sci'!K11 -> 0 | M44: ='FAC-Basic Medical Sci'!K13 | N44: Open →
A45: 32 | B45: Faculty of Clinical Sciences | C45: Faculty | D45: Provost, College of Health Sciences | E45: ='FAC-Clinical Sci'!C7 -> [Enter name] | F45: ='FAC-Clinical Sci'!C11 -> High | G45: ='FAC-Clinical Sci'!K5 -> 46412 | H45: ='FAC-Clinical Sci'!K7 -> 25 | I45: ='FAC-Clinical Sci'!K8 -> 0 | J45: ='FAC-Clinical Sci'!K9 -> 0 | K45: ='FAC-Clinical Sci'!K10 -> 0 | L45: ='FAC-Clinical Sci'!K11 -> 0 | M45: ='FAC-Clinical Sci'!K13 | N45: Open →
A46: 33 | B46: Faculty of Computing | C46: Faculty | D46: DVC (Academic) | E46: ='FAC-Computing'!C7 -> [Enter name] | F46: ='FAC-Computing'!C11 -> Medium | G46: ='FAC-Computing'!K5 -> 46412 | H46: ='FAC-Computing'!K7 -> 24 | I46: ='FAC-Computing'!K8 -> 0 | J46: ='FAC-Computing'!K9 -> 0 | K46: ='FAC-Computing'!K10 -> 0 | L46: ='FAC-Computing'!K11 -> 0 | M46: ='FAC-Computing'!K13 | N46: Open →
A47: 34 | B47: School of Postgraduate Studies | C47: School | D47: DVC (Academic) | E47: ='SCH-Postgraduate'!C7 -> [Enter name] | F47: ='SCH-Postgraduate'!C11 -> High | G47: ='SCH-Postgraduate'!K5 -> 46433 | H47: ='SCH-Postgraduate'!K7 -> 25 | I47: ='SCH-Postgraduate'!K8 -> 0 | J47: ='SCH-Postgraduate'!K9 -> 0 | K47: ='SCH-Postgraduate'!K10 -> 0 | L47: ='SCH-Postgraduate'!K11 -> 0 | M47: ='SCH-Postgraduate'!K13 | N47: Open →
A48: 35 | B48: School of General Studies | C48: School | D48: DVC (Academic) | E48: ='SCH-General Studies'!C7 -> [Enter name] | F48: ='SCH-General Studies'!C11 -> Medium | G48: ='SCH-General Studies'!K5 -> 46433 | H48: ='SCH-General Studies'!K7 -> 23 | I48: ='SCH-General Studies'!K8 -> 0 | J48: ='SCH-General Studies'!K9 -> 0 | K48: ='SCH-General Studies'!K10 -> 0 | L48: ='SCH-General Studies'!K11 -> 0 | M48: ='SCH-General Studies'!K13 | N48: Open →
A49: 36 | B49: Centre/School of Distance Learning & Continuing Education | C49: School | D49: DVC (Academic) | E49: ='SCH-Distance Learning'!C7 -> [Enter name] | F49: ='SCH-Distance Learning'!C11 -> High | G49: ='SCH-Distance Learning'!K5 -> 46433 | H49: ='SCH-Distance Learning'!K7 -> 25 | I49: ='SCH-Distance Learning'!K8 -> 0 | J49: ='SCH-Distance Learning'!K9 -> 0 | K49: ='SCH-Distance Learning'!K10 -> 0 | L49: ='SCH-Distance Learning'!K11 -> 0 | M49: ='SCH-Distance Learning'!K13 | N49: Open →
A50: 37 | B50: School of Basic / Pre-Degree Studies (JUPEB/IJMB) | C50: School | D50: DVC (Academic) | E50: ='SCH-Basic Studies'!C7 -> [Enter name] | F50: ='SCH-Basic Studies'!C11 -> High | G50: ='SCH-Basic Studies'!K5 -> 46433 | H50: ='SCH-Basic Studies'!K7 -> 24 | I50: ='SCH-Basic Studies'!K8 -> 0 | J50: ='SCH-Basic Studies'!K9 -> 0 | K50: ='SCH-Basic Studies'!K10 -> 0 | L50: ='SCH-Basic Studies'!K11 -> 0 | M50: ='SCH-Basic Studies'!K13 | N50: Open →
A51: 38 | B51: University Staff School (Nursery/Primary/Secondary) | C51: School | D51: Registrar | E51: ='SCH-Staff School'!C7 -> [Enter name] | F51: ='SCH-Staff School'!C11 -> High | G51: ='SCH-Staff School'!K5 -> 46433 | H51: ='SCH-Staff School'!K7 -> 25 | I51: ='SCH-Staff School'!K8 -> 0 | J51: ='SCH-Staff School'!K9 -> 0 | K51: ='SCH-Staff School'!K10 -> 0 | L51: ='SCH-Staff School'!K11 -> 0 | M51: ='SCH-Staff School'!K13 | N51: Open →
A53: Score bands: red < 50%, amber 50–79%, green ≥ 80%. Green text = linked from unit tabs.

Sheet CAR Framework
A1: CAR Base Control Framework (applied to every unit)
A2: Derived from GAID 2025 Art. 10 (Filing of CAR) and the obligations that feed the CAR (Arts. 7, 13, 15-19, 27-36, 45-49). Unit tabs add unit-specific controls after these.
A4: No. | B4: CAR Area | C4: GAID / NDPA Reference | D4: Control Objective | E4: Standard Audit Procedure | F4: Evidence | G4: Default Risk
A5: 1 | B5: ROPA | C5: GAID Art. 13(2)-(3), Art. 52; NDPA s.24(3) | D5: All processing activities of the unit are captured in the Record of Processing Activities (ROPA) submitted to the DPO. | E5: Walk through the unit's key processing (its key processes) and confirm each activity is captured in the ROPA with purpose, data categories, recipients and retention. | F5: Unit ROPA extract; process walkthrough notes | G5: High
A6: 2 | B6: Data inventory & sensitive data | C6: NDPA s.30; GAID Art. 28(3)(d) | D6: Personal and sensitive personal data held by the unit is identified and classified. | E6: Inventory data held (its data); flag sensitive categories and confirm they are recorded as such. | F6: Data inventory; classification register | G6: High
A7: 3 | B7: Lawful basis | C7: GAID Art. 16, 23; NDPA s.25 | D7: A documented lawful basis exists for each processing activity; legitimate interest supported by LIA. | E7: For each ROPA activity, confirm lawful basis is recorded and appropriate; where legitimate interest is used, inspect Schedule 8 LIA. | F7: Lawful basis register; LIAs | G7: High
A8: 4 | B8: Consent (CAR disclosure) | C8: GAID Art. 17, 18(1)-(2); NDPA s.26 | D8: Consent is obtained and recorded where required (marketing, sensitive data, children, incompatible further processing, transfers, automated decisions) — CAR must state reliance. | E8: Identify Art. 18(1) activities in the unit; test consent capture, records and ease of withdrawal for a sample of 5. | F8: Consent forms/records; withdrawal mechanism | G8: High
A9: 5 | B9: Privacy notice at collection | C9: GAID Art. 27; Art. 7(j)-(m); NDPA s.27 | D9: Data subjects receive clear privacy information at every collection point (forms, portals, surveys). | E9: Collect all forms/portals used by the unit; check each notice against Art. 27(3)(a)-(j). | F9: Forms; screenshots; notice checklist | G9: Medium
A10: 6 | B10: Minimisation & purpose limitation | C10: GAID Art. 15 & Sch. 1; NDPA s.24(1)(b),(c) | D10: Only data necessary for the stated purpose is collected and used. | E10: Review fields on the unit forms and systems (its systems); identify excessive fields (e.g., religion, NIN, BVN) not justified by purpose. | F10: Form review worksheet | G10: Medium
A11: 7 | B11: Retention & disposal | C11: GAID Art. 49(3)-(4); NDPA s.24(1)(d) | D11: Retention periods defined; data disposed of securely (default not later than 6 months after purpose ends unless justified). | E11: Obtain retention schedule; inspect archives/systems for data past retention; review disposal records (shredding/wiping). | F11: Retention schedule; disposal certificates | G11: Medium
A12: 8 | B12: Accuracy & rectification | C12: GAID Art. 36; NDPA s.24(1)(e) | D12: Data subjects can verify and correct data; input errors by the unit corrected free of charge. | E12: Review rectification procedure (e.g., name/DOB corrections); sample 5 requests for timeliness and absence of fees for unit errors. | F12: Correction requests; procedure | G12: Medium
A13: 9 | B13: Data subject rights | C13: GAID Art. 36-38, 40; NDPA s.34-38 | D13: Access, erasure, portability, objection requests and SNAGs are logged, escalated to the DPO and resolved on time. | E13: Enquire about requests received by the unit; test log and escalation to DPO. | F13: Rights request log; SNAG responses | G13: Medium
A14: 10 | B14: Physical & access security | C14: NDPA s.39; GAID Art. 29 | D14: Physical records and system access are restricted on a need-to-know basis. | E14: Inspect records rooms/cabinets; review user access list for its systems and confirm leavers are removed. | F14: Access lists; site inspection photos | G14: High
A15: 11 | B15: Technical security & devices | C15: GAID Art. 10(5), 29(2); NDPA s.39 | D15: Unit devices and online systems use authentication, encryption, updated software and are audited frequently. | E15: Sample 5 unit laptops/desktops: password, screen lock, encryption, antivirus, OS updates; check use of personal email/USB for personal data. | F15: Device checklist; screenshots | G15: High
A16: 12 | B16: Third-party processors & DPAs | C16: GAID Art. 34; NDPA s.29 | D16: Vendors/partners processing personal data for {u} have Data Processing Agreements and were vetted. | E16: List third parties receiving data from the unit; inspect DPAs against Art. 34(2). | F16: Vendor list; DPAs | G16: High
... A26: 22 | B26: Prior findings follow-up | C26: GAID Art. 10(1), (11) | D26: Previous audit/CAR findings for the unit are remediated. | E26: Obtain prior-year findings for the unit; verify implementation of each agreed action. | F26: Prior report; action tracker | G26: Medium

Sheet Timeline
A1: Audit & CAR Filing Timeline — 2026 Audit Year
A3: Phase | B3: Activity | C3: Start | D3: End | E3: Days | F3: Owner | G3: GAID Reference | H3: Status
A4: 1. Planning | B4: Confirm DCMI level, engage licensed DPCO, approve audit plan & universe | C4: 46296 | D4: 46325 | E4: =NETWORKDAYS(C4,D4) -> 22 | F4: DPO / Internal Audit | G4: Art. 8, 9, 10(14) | H4: Not Started
A5: 1. Planning | B5: Issue ROPA & data inventory requests to all units | C5: 46307 | D5: 46325 | E5: =NETWORKDAYS(C5,D5) -> 15 | F5: DPO | G5: Art. 13 | H5: Not Started
A6: 2. Fieldwork | B6: Central governance (DPO office) | C6: 46328 | D6: 46339 | E6: =NETWORKDAYS(C6,D6) -> 10 | F6: Audit team | G6: Art. 10-14 | H6: Not Started
A7: 2. Fieldwork | B7: Directorates | C7: 46342 | D7: 46367 | E7: =NETWORKDAYS(C7,D7) -> 20 | F7: Audit team | G7: Art. 10(2)-(5) | H7: Not Started
A8: 2. Fieldwork | B8: Central administrative departments | C8: 46391 | D8: 46409 | E8: =NETWORKDAYS(C8,D8) -> 15 | F8: Audit team | G8: Art. 10(2)-(5) | H8: Not Started
A9: 2. Fieldwork | B9: Faculties | C9: 46412 | D9: 46430 | E9: =NETWORKDAYS(C9,D9) -> 15 | F9: Audit team | G9: Art. 10(2)-(5) | H9: Not Started
A10: 2. Fieldwork | B10: Schools | C10: 46433 | D10: 46444 | E10: =NETWORKDAYS(C10,D10) -> 10 | F10: Audit team | G10: Art. 10(2)-(5) | H10: Not Started
A11: 3. Reporting | B11: Draft unit reports & management responses | C11: 46447 | D11: 46456 | E11: =NETWORKDAYS(C11,D11) -> 8 | F11: Audit team / Unit heads | G11: Art. 10(1) | H11: Not Started
A12: 3. Reporting | B12: Consolidate findings into Schedule 2 CAR template; DPCO verification of SADPR & DPIAs | C12: 46457 | D12: 46465 | E12: =NETWORKDAYS(C12,D12) -> 7 | F12: DPCO / DPO | G12: Art. 10(6), 13(4), 28(5) | H12: Not Started
A13: 4. Filing | B13: Management approval & payment of CAR filing fee | C13: 46468 | D13: 46471 | E13: =NETWORKDAYS(C13,D13) -> 4 | F13: VC / Bursary | G13: Art. 10(10) & Sch. 10 | H13: Not Started
A14: 4. Filing | B14: File CAR on NDPC portal via DPCO (deadline 31 March) | C14: 46472 | D14: 46477 | E14: =NETWORKDAYS(C14,D14) -> 4 | F14: DPCO | G14: Art. 10(7), 10(12) | H14: Not Started
A15: 5. Follow-up | B15: Respond to NDPC requests; track remediation of findings | C15: 46478 | D15: 46568 | E15: =NETWORKDAYS(C15,D15) -> 65 | F15: DPO | G15: Art. 10(11), 10(13) | H15: Not Started
A17: Note: weekend days excluded via NETWORKDAYS; public holidays (Christmas, New Year, Easter) not deducted — adjust dates if needed.

Sheet CEN-DPO Office
A1: Compliance Audit Work Plan — Data Protection Office (DPO) & Central Governance | N1: ← Back to Dashboard
A2: NDPA 2023 / GAID 2025 — Article 10 Compliance Audit Returns (CAR) | Audit year 2026 | CAR due 31 March 2027
A4: Unit | C4: Data Protection Office (DPO) & Central Governance | H4: Lead Auditor | K4: [Enter name]
A5: Unit type | C5: Central Governance | H5: Planned Start | K5: 46328
A6: Reports to | C6: Vice-Chancellor / University Management | H6: Planned End | K6: 46339
A7: Head of Unit | C7: [Enter name] | H7: Controls in plan | K7: =COUNTA(A15:A53) -> 39
A8: Data subjects | C8: All data subjects of the University | H8: Completed | K8: =COUNTIF(K15:K53,"Completed") -> 0
A9: Key personal data | C9: Consolidated ROPA, DPIAs, breach register, complaints, CAR records | H9: Compliant | K9: =COUNTIF(L15:L53,"Compliant") -> 0
A10: Key systems / records | C10: CAR portal, ROPA register, breach log | H10: Partially Compliant | K10: =COUNTIF(L15:L53,"Partially Compliant") -> 0
A11: Inherent data risk | C11: High | H11: Non-Compliant | K11: =COUNTIF(L15:L53,"Non-Compliant") -> 0
H12: Not Applicable | K12: =COUNTIF(L15:L53,"Not Applicable") -> 0
H13: Compliance Score | K13: =_xlfn.IFERROR(AVERAGE(M15:M53),"")
A14: Ref | B14: CAR Area | C14: GAID / NDPA Reference | D14: Control Objective | E14: Audit Procedure | F14: Evidence to Obtain | G14: Risk | H14: Planned Start | I14: Planned End | J14: Auditor | K14: Status | L14: Compliance Rating | M14: Score | N14: Findings | O14: Recommendation | P14: Management Response / Owner | Q14: Target Date
A15: CEN-DO-01 | B15: Registration as DCMI | C15: GAID Art. 8, 9 & Sch. 7; NDPA s.44 | D15: University is registered with NDPC as a Data Controller of Major Importance at the correct level (UHL/EHL/OHL). | E15: Confirm NDPC registration certificate, check classification against Schedule 7 criteria (student + staff population, sensitivity) and confirm level is still accurate. | F15: NDPC registration certificate; classification working paper | G15: High | H15: =$K$5 -> 46328 | I15: =$K$6 -> 46339 | K15: Not Started | M15: =IF(L15="Compliant",1,IF(L15="Partially Compliant",0.5,IF(L15="Non-Compliant",0,"")))
A16: CEN-DO-02 | B16: Registration changes | C16: GAID Art. 9(4) | D16: Significant changes to registration details notified to NDPC within 60 days. | E16: Identify changes in the year (new VC/DPO, new campuses, new systems) and trace notification to NDPC within 60 days. | F16: Change log; NDPC correspondence | G16: Medium | H16: =$K$5 -> 46328 | I16: =$K$6 -> 46339 | K16: Not Started | M16: =IF(L16="Compliant",1,IF(L16="Partially Compliant",0.5,IF(L16="Non-Compliant",0,"")))
A17: CEN-DO-03 | B17: CAR filing | C17: GAID Art. 10(6),(7),(12),(14) | D17: Annual CAR prepared on the Schedule 2 template and filed through a licensed DPCO via the NDPC portal by 31 March. | E17: Confirm engagement of an NDPC-licensed DPCO, review prior-year CAR filing date and portal acknowledgement, confirm current CAR timetable meets 31 March deadline. | F17: DPCO licence; DPCO engagement letter; prior CAR acknowledgement / certificate | G17: High | H17: =$K$5 -> 46328 | I17: =$K$6 -> 46339 | K17: Not Started | M17: =IF(L17="Compliant",1,IF(L17="Partially Compliant",0.5,IF(L17="Non-Compliant",0,"")))
A18: CEN-DO-04 | B18: CAR fees & penalties | C18: GAID Art. 10(9),(10) & Sch. 10 | D18: Filing fee paid at the correct rate; no 50% late-filing penalty incurred. | E18: Recompute filing fee per Schedule 10, trace payment in Bursary records, check for late-filing penalty. | F18: Payment receipt; Schedule 10 computation | G18: Medium | H18: =$K$5 -> 46328 | I18: =$K$6 -> 46339 | K18: Not Started | M18: =IF(L18="Compliant",1,IF(L18="Partially Compliant",0.5,IF(L18="Non-Compliant",0,"")))
A19: CEN-DO-05 | B19: NDPC information requests | C19: GAID Art. 10(11) & (13) | D19: Additional information requested by NDPC after CAR filing was provided promptly; CAR certificate obtained. | E19: Review NDPC correspondence after last filing and confirm timely responses and receipt of CAR certificate. | F19: NDPC letters; response log; CAR certificate | G19: Medium | H19: =$K$5 -> 46328 | I19: =$K$6 -> 46339 | K19: Not Started | M19: =IF(L19="Compliant",1,IF(L19="Partially Compliant",0.5,IF(L19="Non-Compliant",0,"")))
A20: CEN-DO-06 | B20: DPO designation | C20: GAID Art. 11, 12; NDPA s.32 | D20: DPO formally designated, reports directly to management, is resourced and free from conflict of interest. | E20: Review appointment letter, organogram, DPO budget and other roles held; confirm DPO contact details published and communicated to NDPC. | F20: Appointment letter; organogram; website DPO contact page | G20: High | H20: =$K$5 -> 46328 | I20: =$K$6 -> 46339 | K20: Not Started | M20: =IF(L20="Compliant",1,IF(L20="Partially Compliant",0.5,IF(L20="Non-Compliant",0,"")))
A21: CEN-DO-07 | B21: DPO credentials | C21: GAID Art. 14 & Sch. 3 | D21: DPO is certified and maintains CPD for Annual Credential Assessment. | E21: Inspect DPO certification and CPD evidence against Schedule 3 metrics. | F21: Certificates; CPD log | G21: Medium | H21: =$K$5 -> 46328 | I21: =$K$6 -> 46339 | K21: Not Started | M21: =IF(L21="Compliant",1,IF(L21="Partially Compliant",0.5,IF(L21="Non-Compliant",0,"")))
A22: CEN-DO-08 | B22: Semi-Annual DP Report | C22: GAID Art. 13 | D22: SADPR compiled twice in the year, acknowledged by management and filed with ROPA. | E22: Obtain both SADPRs, confirm coverage of Art. 13(5)(a)-(m) items and management acknowledgement. | F22: SADPR (H1 & H2); acknowledgement | G22: High | H22: =$K$5 -> 46328 | I22: =$K$6 -> 46339 | K22: Not Started | M22: =IF(L22="Compliant",1,IF(L22="Partially Compliant",0.5,IF(L22="Non-Compliant",0,"")))
A23: CEN-DO-09 | B23: Consolidated ROPA | C23: GAID Art. 13(3); Art. 52 | D23: University-wide ROPA is complete and covers every faculty, school, directorate and department. | E23: Reconcile consolidated ROPA against the audit universe on the Dashboard; list units without ROPA entries. | F23: Consolidated ROPA; reconciliation | G23: High | H23: =$K$5 -> 46328 | I23: =$K$6 -> 46339 | K23: Not Started | M23: =IF(L23="Compliant",1,IF(L23="Partially Compliant",0.5,IF(L23="Non-Compliant",0,"")))
A24: CEN-DO-10 | B24: Compliance schedules | C24: GAID Art. 7(d),(h) | D24: Schedule of NDPA obligations and compliance timelines exists and is tracked. | E24: Review compliance schedule and test status of five obligations to evidence. | F24: Compliance schedule / tracker | G24: Medium | H24: =$K$5 -> 46328 | I24: =$K$6 -> 46339 | K24: Not Started | M24: =IF(L24="Compliant",1,IF(L24="Partially Compliant",0.5,IF(L24="Non-Compliant",0,"")))
A25: CEN-DO-11 | B25: MEM schedule | C25: GAID Art. 29(1)-(4) | D25: Monitoring, Evaluation & Maintenance schedule for data security exists and is vetted by a certified information security officer. | E25: Inspect MEM schedule; confirm people/process/technology coverage and certification sign-off. | F25: MEM schedule; InfoSec officer certificate | G25: High | H25: =$K$5 -> 46328 | I25: =$K$6 -> 46339 | K25: Not Started | M25: =IF(L25="Compliant",1,IF(L25="Partially Compliant",0.5,IF(L25="Non-Compliant",0,"")))
A26: CEN-DO-12 | B26: SToP schedule | C26: GAID Art. 30(1)-(5); Art. 46 | D26: University-wide Sensitisation & Training on Privacy schedule is approved and published to staff. | E26: Inspect SToP schedule, publication medium, and evaluation of stop/start/continue practices. | F26: SToP schedule; intranet/notice board evidence | G26: Medium | H26: =$K$5 -> 46328 | I26: =$K$6 -> 46339 | K26: Not Started | M26: =IF(L26="Compliant",1,IF(L26="Partially Compliant",0.5,IF(L26="Non-Compliant",0,"")))
... A53: CEN-DO-39 | B53: Prior findings follow-up | C53: GAID Art. 10(1), (11) | D53: Previous audit/CAR findings for the unit are remediated. | E53: Obtain prior-year findings for Data Protection Office (DPO) & Central Governance; verify implementation of each agreed action. | F53: Prior report; action tracker | G53: High | H53: =$K$5 -> 46328 | I53: =$K$6 -> 46339 | K53: Not Started | M53: =IF(L53="Compliant",1,IF(L53="Partially Compliant",0.5,IF(L53="Non-Compliant",0,"")))
A55: Bold teal CAR Areas = controls specific to this unit. Base controls are listed on the 'CAR Framework' tab.

Sheet DIR-ICT
A1: Compliance Audit Work Plan — Directorate of Information & Communication Technology (DICT) | N1: ← Back to Dashboard
A2: NDPA 2023 / GAID 2025 — Article 10 Compliance Audit Returns (CAR) | Audit year 2026 | CAR due 31 March 2027
A4: Unit | C4: Directorate of Information & Communication Technology (DICT) | H4: Lead Auditor | K4: [Enter name]
A5: Unit type | C5: Directorate | H5: Planned Start | K5: 46342
A6: Reports to | C6: Vice-Chancellor | H6: Planned End | K6: 46367
A7: Head of Unit | C7: [Enter name] | H7: Controls in plan | K7: =COUNTA(A15:A42) -> 28
A8: Data subjects | C8: Students, applicants, staff, alumni, website visitors | H8: Completed | K8: =COUNTIF(K15:K42,"Completed") -> 0
A9: Key personal data | C9: Portal credentials, biodata, results, email, logs, biometrics | H9: Compliant | K9: =COUNTIF(L15:L42,"Compliant") -> 0
A10: Key systems / records | C10: Student portal, ERP/SIS, email, LMS hosting, data centre, cloud services | H10: Partially Compliant | K10: =COUNTIF(L15:L42,"Partially Compliant") -> 0
A11: Inherent data risk | C11: High | H11: Non-Compliant | K11: =COUNTIF(L15:L42,"Non-Compliant") -> 0
H12: Not Applicable | K12: =COUNTIF(L15:L42,"Not Applicable") -> 0
H13: Compliance Score | K13: =_xlfn.IFERROR(AVERAGE(M15:M42),"")
A14: Ref | B14: CAR Area | C14: GAID / NDPA Reference | D14: Control Objective | E14: Audit Procedure | F14: Evidence to Obtain | G14: Risk | H14: Planned Start | I14: Planned End | J14: Auditor | K14: Status | L14: Compliance Rating | M14: Score | N14: Findings | O14: Recommendation | P14: Management Response / Owner | Q14: Target Date
A15: DIR-ICT-01 | B15: ROPA | C15: GAID Art. 13(2)-(3), Art. 52; NDPA s.24(3) | D15: All processing activities of the unit are captured in the Record of Processing Activities (ROPA) submitted to the DPO. | E15: Walk through Directorate of Information & Communication Technology (DICT)'s key processing (portal administration, account management, hosting and backups) and confirm each activity is captured in the ROPA with purpose, data categories, recipients and retention. | F15: Unit ROPA extract; process walkthrough notes | G15: High | H15: =$K$5 -> 46342 | I15: =$K$6 -> 46367 | K15: Not Started | M15: =IF(L15="Compliant",1,IF(L15="Partially Compliant",0.5,IF(L15="Non-Compliant",0,"")))
A16: DIR-ICT-02 | B16: Data inventory & sensitive data | C16: NDPA s.30; GAID Art. 28(3)(d) | D16: Personal and sensitive personal data held by the unit is identified and classified. | E16: Inventory data held (Portal credentials, biodata, results, email, logs, biometrics); flag sensitive categories and confirm they are recorded as such. | F16: Data inventory; classification register | G16: High | H16: =$K$5 -> 46342 | I16: =$K$6 -> 46367 | K16: Not Started | M16: =IF(L16="Compliant",1,IF(L16="Partially Compliant",0.5,IF(L16="Non-Compliant",0,"")))
A17: DIR-ICT-03 | B17: Lawful basis | C17: GAID Art. 16, 23; NDPA s.25 | D17: A documented lawful basis exists for each processing activity; legitimate interest supported by LIA. | E17: For each ROPA activity, confirm lawful basis is recorded and appropriate; where legitimate interest is used, inspect Schedule 8 LIA. | F17: Lawful basis register; LIAs | G17: High | H17: =$K$5 -> 46342 | I17: =$K$6 -> 46367 | K17: Not Started | M17: =IF(L17="Compliant",1,IF(L17="Partially Compliant",0.5,IF(L17="Non-Compliant",0,"")))
A18: DIR-ICT-04 | B18: Consent (CAR disclosure) | C18: GAID Art. 17, 18(1)-(2); NDPA s.26 | D18: Consent is obtained and recorded where required (marketing, sensitive data, children, incompatible further processing, transfers, automated decisions) — CAR must state reliance. | E18: Identify Art. 18(1) activities in Directorate of Information & Communication Technology (DICT); test consent capture, records and ease of withdrawal for a sample of 5. | F18: Consent forms/records; withdrawal mechanism | G18: High | H18: =$K$5 -> 46342 | I18: =$K$6 -> 46367 | K18: Not Started | M18: =IF(L18="Compliant",1,IF(L18="Partially Compliant",0.5,IF(L18="Non-Compliant",0,"")))
A19: DIR-ICT-05 | B19: Privacy notice at collection | C19: GAID Art. 27; Art. 7(j)-(m); NDPA s.27 | D19: Data subjects receive clear privacy information at every collection point (forms, portals, surveys). | E19: Collect all forms/portals used by Directorate of Information & Communication Technology (DICT); check each notice against Art. 27(3)(a)-(j). | F19: Forms; screenshots; notice checklist | G19: High | H19: =$K$5 -> 46342 | I19: =$K$6 -> 46367 | K19: Not Started | M19: =IF(L19="Compliant",1,IF(L19="Partially Compliant",0.5,IF(L19="Non-Compliant",0,"")))
A20: DIR-ICT-06 | B20: Minimisation & purpose limitation | C20: GAID Art. 15 & Sch. 1; NDPA s.24(1)(b),(c) | D20: Only data necessary for the stated purpose is collected and used. | E20: Review fields on Directorate of Information & Communication Technology (DICT) forms and systems (Student portal, ERP/SIS, email, LMS hosting, data centre, cloud services); identify excessive fields (e.g., religion, NIN, BVN) not justified by purpose. | F20: Form review worksheet | G20: High | H20: =$K$5 -> 46342 | I20: =$K$6 -> 46367 | K20: Not Started | M20: =IF(L20="Compliant",1,IF(L20="Partially Compliant",0.5,IF(L20="Non-Compliant",0,"")))
A21: DIR-ICT-07 | B21: Retention & disposal | C21: GAID Art. 49(3)-(4); NDPA s.24(1)(d) | D21: Retention periods defined; data disposed of securely (default not later than 6 months after purpose ends unless justified). | E21: Obtain retention schedule; inspect archives/systems for data past retention; review disposal records (shredding/wiping). | F21: Retention schedule; disposal certificates | G21: High | H21: =$K$5 -> 46342 | I21: =$K$6 -> 46367 | K21: Not Started | M21: =IF(L21="Compliant",1,IF(L21="Partially Compliant",0.5,IF(L21="Non-Compliant",0,"")))
A22: DIR-ICT-08 | B22: Accuracy & rectification | C22: GAID Art. 36; NDPA s.24(1)(e) | D22: Data subjects can verify and correct data; input errors by the unit corrected free of charge. | E22: Review rectification procedure (e.g., name/DOB corrections); sample 5 requests for timeliness and absence of fees for unit errors. | F22: Correction requests; procedure | G22: High | H22: =$K$5 -> 46342 | I22: =$K$6 -> 46367 | K22: Not Started | M22: =IF(L22="Compliant",1,IF(L22="Partially Compliant",0.5,IF(L22="Non-Compliant",0,"")))
A23: DIR-ICT-09 | B23: Data subject rights | C23: GAID Art. 36-38, 40; NDPA s.34-38 | D23: Access, erasure, portability, objection requests and SNAGs are logged, escalated to the DPO and resolved on time. | E23: Enquire about requests received by Directorate of Information & Communication Technology (DICT); test log and escalation to DPO. | F23: Rights request log; SNAG responses | G23: High | H23: =$K$5 -> 46342 | I23: =$K$6 -> 46367 | K23: Not Started | M23: =IF(L23="Compliant",1,IF(L23="Partially Compliant",0.5,IF(L23="Non-Compliant",0,"")))
A24: DIR-ICT-10 | B24: Physical & access security | C24: NDPA s.39; GAID Art. 29 | D24: Physical records and system access are restricted on a need-to-know basis. | E24: Inspect records rooms/cabinets; review user access list for Student portal, ERP/SIS, email, LMS hosting, data centre, cloud services and confirm leavers are removed. | F24: Access lists; site inspection photos | G24: High | H24: =$K$5 -> 46342 | I24: =$K$6 -> 46367 | K24: Not Started | M24: =IF(L24="Compliant",1,IF(L24="Partially Compliant",0.5,IF(L24="Non-Compliant",0,"")))
A25: DIR-ICT-11 | B25: Technical security & devices | C25: GAID Art. 10(5), 29(2); NDPA s.39 | D25: Unit devices and online systems use authentication, encryption, updated software and are audited frequently. | E25: Sample 5 unit laptops/desktops: password, screen lock, encryption, antivirus, OS updates; check use of personal email/USB for personal data. | F25: Device checklist; screenshots | G25: High | H25: =$K$5 -> 46342 | I25: =$K$6 -> 46367 | K25: Not Started | M25: =IF(L25="Compliant",1,IF(L25="Partially Compliant",0.5,IF(L25="Non-Compliant",0,"")))
A26: DIR-ICT-12 | B26: Third-party processors & DPAs | C26: GAID Art. 34; NDPA s.29 | D26: Vendors/partners processing personal data for Directorate of Information & Communication Technology (DICT) have Data Processing Agreements and were vetted. | E26: List third parties receiving data from Directorate of Information & Communication Technology (DICT); inspect DPAs against Art. 34(2). | F26: Vendor list; DPAs | G26: High | H26: =$K$5 -> 46342 | I26: =$K$6 -> 46367 | K26: Not Started | M26: =IF(L26="Compliant",1,IF(L26="Partially Compliant",0.5,IF(L26="Non-Compliant",0,"")))
... A42: DIR-ICT-28 | B42: Software deployment | C42: GAID Art. 31 | D42: University apps/portals interacting with data subjects had DPIA, privacy by design and in-app privacy statement. | E42: For each app launched/updated in the year, inspect DPIA and pre-installation privacy statement per Art. 31(2)(e). | F42: App DPIAs; screenshots | G42: High | H42: =$K$5 -> 46342 | I42: =$K$6 -> 46367 | K42: Not Started | M42: =IF(L42="Compliant",1,IF(L42="Partially Compliant",0.5,IF(L42="Non-Compliant",0,"")))
A44: Bold teal CAR Areas = controls specific to this unit. Base controls are listed on the 'CAR Framework' tab.

Sheet DIR-Academic Planning
A1: Compliance Audit Work Plan — Directorate of Academic Planning | N1: ← Back to Dashboard
A2: NDPA 2023 / GAID 2025 — Article 10 Compliance Audit Returns (CAR) | Audit year 2026 | CAR due 31 March 2027
A4: Unit | C4: Directorate of Academic Planning | H4: Lead Auditor | K4: [Enter name]
A5: Unit type | C5: Directorate | H5: Planned Start | K5: 46342
A6: Reports to | C6: Vice-Chancellor | H6: Planned End | K6: 46367
A7: Head of Unit | C7: [Enter name] | H7: Controls in plan | K7: =COUNTA(A15:A38) -> 24
A8: Data subjects | C8: Students, staff | H8: Completed | K8: =COUNTIF(K15:K38,"Completed") -> 0
A9: Key personal data | C9: Enrolment statistics, staff nominal roll, NUC returns | H9: Compliant | K9: =COUNTIF(L15:L38,"Compliant") -> 0
A10: Key systems / records | C10: NUC portal, planning databases, spreadsheets | H10: Partially Compliant | K10: =COUNTIF(L15:L38,"Partially Compliant") -> 0
A11: Inherent data risk | C11: Medium | H11: Non-Compliant | K11: =COUNTIF(L15:L38,"Non-Compliant") -> 0
H12: Not Applicable | K12: =COUNTIF(L15:L38,"Not Applicable") -> 0
H13: Compliance Score | K13: =_xlfn.IFERROR(AVERAGE(M15:M38),"")
A14: Ref | B14: CAR Area | C14: GAID / NDPA Reference | D14: Control Objective | E14: Audit Procedure | F14: Evidence to Obtain | G14: Risk | H14: Planned Start | I14: Planned End | J14: Auditor | K14: Status | L14: Compliance Rating | M14: Score | N14: Findings | O14: Recommendation | P14: Management Response / Owner | Q14: Target Date
A15: DIR-AP-01 | B15: ROPA | C15: GAID Art. 13(2)-(3), Art. 52; NDPA s.24(3) | D15: All processing activities of the unit are captured in the Record of Processing Activities (ROPA) submitted to the DPO. | E15: Walk through Directorate of Academic Planning's key processing (NUC/TETFund statistical returns, programme planning) and confirm each activity is captured in the ROPA with purpose, data categories, recipients and retention. | F15: Unit ROPA extract; process walkthrough notes | G15: High | H15: =$K$5 -> 46342 | I15: =$K$6 -> 46367 | K15: Not Started | M15: =IF(L15="Compliant",1,IF(L15="Partially Compliant",0.5,IF(L15="Non-Compliant",0,"")))
A16: DIR-AP-02 | B16: Data inventory & sensitive data | C16: NDPA s.30; GAID Art. 28(3)(d) | D16: Personal and sensitive personal data held by the unit is identified and classified. | E16: Inventory data held (Enrolment statistics, staff nominal roll, NUC returns); flag sensitive categories and confirm they are recorded as such. | F16: Data inventory; classification register | G16: High | H16: =$K$5 -> 46342 | I16: =$K$6 -> 46367 | K16: Not Started | M16: =IF(L16="Compliant",1,IF(L16="Partially Compliant",0.5,IF(L16="Non-Compliant",0,"")))
A17: DIR-AP-03 | B17: Lawful basis | C17: GAID Art. 16, 23; NDPA s.25 | D17: A documented lawful basis exists for each processing activity; legitimate interest supported by LIA. | E17: For each ROPA activity, confirm lawful basis is recorded and appropriate; where legitimate interest is used, inspect Schedule 8 LIA. | F17: Lawful basis register; LIAs | G17: High | H17: =$K$5 -> 46342 | I17: =$K$6 -> 46367 | K17: Not Started | M17: =IF(L17="Compliant",1,IF(L17="Partially Compliant",0.5,IF(L17="Non-Compliant",0,"")))
A18: DIR-AP-04 | B18: Consent (CAR disclosure) | C18: GAID Art. 17, 18(1)-(2); NDPA s.26 | D18: Consent is obtained and recorded where required (marketing, sensitive data, children, incompatible further processing, transfers, automated decisions) — CAR must state reliance. | E18: Identify Art. 18(1) activities in Directorate of Academic Planning; test consent capture, records and ease of withdrawal for a sample of 5. | F18: Consent forms/records; withdrawal mechanism | G18: High | H18: =$K$5 -> 46342 | I18: =$K$6 -> 46367 | K18: Not Started | M18: =IF(L18="Compliant",1,IF(L18="Partially Compliant",0.5,IF(L18="Non-Compliant",0,"")))
A19: DIR-AP-05 | B19: Privacy notice at collection | C19: GAID Art. 27; Art. 7(j)-(m); NDPA s.27 | D19: Data subjects receive clear privacy information at every collection point (forms, portals, surveys). | E19: Collect all forms/portals used by Directorate of Academic Planning; check each notice against Art. 27(3)(a)-(j). | F19: Forms; screenshots; notice checklist | G19: Medium | H19: =$K$5 -> 46342 | I19: =$K$6 -> 46367 | K19: Not Started | M19: =IF(L19="Compliant",1,IF(L19="Partially Compliant",0.5,IF(L19="Non-Compliant",0,"")))
A20: DIR-AP-06 | B20: Minimisation & purpose limitation | C20: GAID Art. 15 & Sch. 1; NDPA s.24(1)(b),(c) | D20: Only data necessary for the stated purpose is collected and used. | E20: Review fields on Directorate of Academic Planning forms and systems (NUC portal, planning databases, spreadsheets); identify excessive fields (e.g., religion, NIN, BVN) not justified by purpose. | F20: Form review worksheet | G20: Medium | H20: =$K$5 -> 46342 | I20: =$K$6 -> 46367 | K20: Not Started | M20: =IF(L20="Compliant",1,IF(L20="Partially Compliant",0.5,IF(L20="Non-Compliant",0,"")))
A21: DIR-AP-07 | B21: Retention & disposal | C21: GAID Art. 49(3)-(4); NDPA s.24(1)(d) | D21: Retention periods defined; data disposed of securely (default not later than 6 months after purpose ends unless justified). | E21: Obtain retention schedule; inspect archives/systems for data past retention; review disposal records (shredding/wiping). | F21: Retention schedule; disposal certificates | G21: Medium | H21: =$K$5 -> 46342 | I21: =$K$6 -> 46367 | K21: Not Started | M21: =IF(L21="Compliant",1,IF(L21="Partially Compliant",0.5,IF(L21="Non-Compliant",0,"")))
A22: DIR-AP-08 | B22: Accuracy & rectification | C22: GAID Art. 36; NDPA s.24(1)(e) | D22: Data subjects can verify and correct data; input errors by the unit corrected free of charge. | E22: Review rectification procedure (e.g., name/DOB corrections); sample 5 requests for timeliness and absence of fees for unit errors. | F22: Correction requests; procedure | G22: Medium | H22: =$K$5 -> 46342 | I22: =$K$6 -> 46367 | K22: Not Started | M22: =IF(L22="Compliant",1,IF(L22="Partially Compliant",0.5,IF(L22="Non-Compliant",0,"")))
A23: DIR-AP-09 | B23: Data subject rights | C23: GAID Art. 36-38, 40; NDPA s.34-38 | D23: Access, erasure, portability, objection requests and SNAGs are logged, escalated to the DPO and resolved on time. | E23: Enquire about requests received by Directorate of Academic Planning; test log and escalation to DPO. | F23: Rights request log; SNAG responses | G23: Medium | H23: =$K$5 -> 46342 | I23: =$K$6 -> 46367 | K23: Not Started | M23: =IF(L23="Compliant",1,IF(L23="Partially Compliant",0.5,IF(L23="Non-Compliant",0,"")))
A24: DIR-AP-10 | B24: Physical & access security | C24: NDPA s.39; GAID Art. 29 | D24: Physical records and system access are restricted on a need-to-know basis. | E24: Inspect records rooms/cabinets; review user access list for NUC portal, planning databases, spreadsheets and confirm leavers are removed. | F24: Access lists; site inspection photos | G24: High | H24: =$K$5 -> 46342 | I24: =$K$6 -> 46367 | K24: Not Started | M24: =IF(L24="Compliant",1,IF(L24="Partially Compliant",0.5,IF(L24="Non-Compliant",0,"")))
A25: DIR-AP-11 | B25: Technical security & devices | C25: GAID Art. 10(5), 29(2); NDPA s.39 | D25: Unit devices and online systems use authentication, encryption, updated software and are audited frequently. | E25: Sample 5 unit laptops/desktops: password, screen lock, encryption, antivirus, OS updates; check use of personal email/USB for personal data. | F25: Device checklist; screenshots | G25: High | H25: =$K$5 -> 46342 | I25: =$K$6 -> 46367 | K25: Not Started | M25: =IF(L25="Compliant",1,IF(L25="Partially Compliant",0.5,IF(L25="Non-Compliant",0,"")))
A26: DIR-AP-12 | B26: Third-party processors & DPAs | C26: GAID Art. 34; NDPA s.29 | D26: Vendors/partners processing personal data for Directorate of Academic Planning have Data Processing Agreements and were vetted. | E26: List third parties receiving data from Directorate of Academic Planning; inspect DPAs against Art. 34(2). | F26: Vendor list; DPAs | G26: High | H26: =$K$5 -> 46342 | I26: =$K$6 -> 46367 | K26: Not Started | M26: =IF(L26="Compliant",1,IF(L26="Partially Compliant",0.5,IF(L26="Non-Compliant",0,"")))
... A38: DIR-AP-24 | B38: Legal obligation reliance | C38: GAID Art. 22 | D38: Disclosures to regulators rest on a documented legal obligation limited to the minimum required. | E38: Review requests from NUC/JAMB/TETFund; confirm DPO opinion or legal basis on file. | F38: Request letters; DPO opinion | G38: Medium | H38: =$K$5 -> 46342 | I38: =$K$6 -> 46367 | K38: Not Started | M38: =IF(L38="Compliant",1,IF(L38="Partially Compliant",0.5,IF(L38="Non-Compliant",0,"")))
A40: Bold teal CAR Areas = controls specific to this unit. Base controls are listed on the 'CAR Framework' tab.

Sheet DIR-Quality Assurance
A1: Compliance Audit Work Plan — Directorate of Quality Assurance | N1: ← Back to Dashboard
A2: NDPA 2023 / GAID 2025 — Article 10 Compliance Audit Returns (CAR) | Audit year 2026 | CAR due 31 March 2027
A4: Unit | C4: Directorate of Quality Assurance | H4: Lead Auditor | K4: [Enter name]
A5: Unit type | C5: Directorate | H5: Planned Start | K5: 46342
A6: Reports to | C6: Vice-Chancellor | H6: Planned End | K6: 46367
A7: Head of Unit | C7: [Enter name] | H7: Controls in plan | K7: =COUNTA(A15:A38) -> 24
A8: Data subjects | C8: Students, lecturers | H8: Completed | K8: =COUNTIF(K15:K38,"Completed") -> 0
A9: Key personal data | C9: Course evaluation responses, staff appraisal inputs, accreditation files | H9: Compliant | K9: =COUNTIF(L15:L38,"Compliant") -> 0
A10: Key systems / records | C10: Survey tools (online forms), accreditation portal | H10: Partially Compliant | K10: =COUNTIF(L15:L38,"Partially Compliant") -> 0
A11: Inherent data risk | C11: Medium | H11: Non-Compliant | K11: =COUNTIF(L15:L38,"Non-Compliant") -> 0
H12: Not Applicable | K12: =COUNTIF(L15:L38,"Not Applicable") -> 0
H13: Compliance Score | K13: =_xlfn.IFERROR(AVERAGE(M15:M38),"")
A14: Ref | B14: CAR Area | C14: GAID / NDPA Reference | D14: Control Objective | E14: Audit Procedure | F14: Evidence to Obtain | G14: Risk | H14: Planned Start | I14: Planned End | J14: Auditor | K14: Status | L14: Compliance Rating | M14: Score | N14: Findings | O14: Recommendation | P14: Management Response / Owner | Q14: Target Date
A15: DIR-QA-01 | B15: ROPA | C15: GAID Art. 13(2)-(3), Art. 52; NDPA s.24(3) | D15: All processing activities of the unit are captured in the Record of Processing Activities (ROPA) submitted to the DPO. | E15: Walk through Directorate of Quality Assurance's key processing (student evaluation of teaching, accreditation preparation) and confirm each activity is captured in the ROPA with purpose, data categories, recipients and retention. | F15: Unit ROPA extract; process walkthrough notes | G15: High | H15: =$K$5 -> 46342 | I15: =$K$6 -> 46367 | K15: Not Started | M15: =IF(L15="Compliant",1,IF(L15="Partially Compliant",0.5,IF(L15="Non-Compliant",0,"")))
A16: DIR-QA-02 | B16: Data inventory & sensitive data | C16: NDPA s.30; GAID Art. 28(3)(d) | D16: Personal and sensitive personal data held by the unit is identified and classified. | E16: Inventory data held (Course evaluation responses, staff appraisal inputs, accreditation files); flag sensitive categories and confirm they are recorded as such. | F16: Data inventory; classification register | G16: High | H16: =$K$5 -> 46342 | I16: =$K$6 -> 46367 | K16: Not Started | M16: =IF(L16="Compliant",1,IF(L16="Partially Compliant",0.5,IF(L16="Non-Compliant",0,"")))
A17: DIR-QA-03 | B17: Lawful basis | C17: GAID Art. 16, 23; NDPA s.25 | D17: A documented lawful basis exists for each processing activity; legitimate interest supported by LIA. | E17: For each ROPA activity, confirm lawful basis is recorded and appropriate; where legitimate interest is used, inspect Schedule 8 LIA. | F17: Lawful basis register; LIAs | G17: High | H17: =$K$5 -> 46342 | I17: =$K$6 -> 46367 | K17: Not Started | M17: =IF(L17="Compliant",1,IF(L17="Partially Compliant",0.5,IF(L17="Non-Compliant",0,"")))
A18: DIR-QA-04 | B18: Consent (CAR disclosure) | C18: GAID Art. 17, 18(1)-(2); NDPA s.26 | D18: Consent is obtained and recorded where required (marketing, sensitive data, children, incompatible further processing, transfers, automated decisions) — CAR must state reliance. | E18: Identify Art. 18(1) activities in Directorate of Quality Assurance; test consent capture, records and ease of withdrawal for a sample of 5. | F18: Consent forms/records; withdrawal mechanism | G18: High | H18: =$K$5 -> 46342 | I18: =$K$6 -> 46367 | K18: Not Started | M18: =IF(L18="Compliant",1,IF(L18="Partially Compliant",0.5,IF(L18="Non-Compliant",0,"")))
A19: DIR-QA-05 | B19: Privacy notice at collection | C19: GAID Art. 27; Art. 7(j)-(m); NDPA s.27 | D19: Data subjects receive clear privacy information at every collection point (forms, portals, surveys). | E19: Collect all forms/portals used by Directorate of Quality Assurance; check each notice against Art. 27(3)(a)-(j). | F19: Forms; screenshots; notice checklist | G19: Medium | H19: =$K$5 -> 46342 | I19: =$K$6 -> 46367 | K19: Not Started | M19: =IF(L19="Compliant",1,IF(L19="Partially Compliant",0.5,IF(L19="Non-Compliant",0,"")))
A20: DIR-QA-06 | B20: Minimisation & purpose limitation | C20: GAID Art. 15 & Sch. 1; NDPA s.24(1)(b),(c) | D20: Only data necessary for the stated purpose is collected and used. | E20: Review fields on Directorate of Quality Assurance forms and systems (Survey tools (online forms), accreditation portal); identify excessive fields (e.g., religion, NIN, BVN) not justified by purpose. | F20: Form review worksheet | G20: Medium | H20: =$K$5 -> 46342 | I20: =$K$6 -> 46367 | K20: Not Started | M20: =IF(L20="Compliant",1,IF(L20="Partially Compliant",0.5,IF(L20="Non-Compliant",0,"")))
A21: DIR-QA-07 | B21: Retention & disposal | C21: GAID Art. 49(3)-(4); NDPA s.24(1)(d) | D21: Retention periods defined; data disposed of securely (default not later than 6 months after purpose ends unless justified). | E21: Obtain retention schedule; inspect archives/systems for data past retention; review disposal records (shredding/wiping). | F21: Retention schedule; disposal certificates | G21: Medium | H21: =$K$5 -> 46342 | I21: =$K$6 -> 46367 | K21: Not Started | M21: =IF(L21="Compliant",1,IF(L21="Partially Compliant",0.5,IF(L21="Non-Compliant",0,"")))
A22: DIR-QA-08 | B22: Accuracy & rectification | C22: GAID Art. 36; NDPA s.24(1)(e) | D22: Data subjects can verify and correct data; input errors by the unit corrected free of charge. | E22: Review rectification procedure (e.g., name/DOB corrections); sample 5 requests for timeliness and absence of fees for unit errors. | F22: Correction requests; procedure | G22: Medium | H22: =$K$5 -> 46342 | I22: =$K$6 -> 46367 | K22: Not Started | M22: =IF(L22="Compliant",1,IF(L22="Partially Compliant",0.5,IF(L22="Non-Compliant",0,"")))
A23: DIR-QA-09 | B23: Data subject rights | C23: GAID Art. 36-38, 40; NDPA s.34-38 | D23: Access, erasure, portability, objection requests and SNAGs are logged, escalated to the DPO and resolved on time. | E23: Enquire about requests received by Directorate of Quality Assurance; test log and escalation to DPO. | F23: Rights request log; SNAG responses | G23: Medium | H23: =$K$5 -> 46342 | I23: =$K$6 -> 46367 | K23: Not Started | M23: =IF(L23="Compliant",1,IF(L23="Partially Compliant",0.5,IF(L23="Non-Compliant",0,"")))
A24: DIR-QA-10 | B24: Physical & access security | C24: NDPA s.39; GAID Art. 29 | D24: Physical records and system access are restricted on a need-to-know basis. | E24: Inspect records rooms/cabinets; review user access list for Survey tools (online forms), accreditation portal and confirm leavers are removed. | F24: Access lists; site inspection photos | G24: High | H24: =$K$5 -> 46342 | I24: =$K$6 -> 46367 | K24: Not Started | M24: =IF(L24="Compliant",1,IF(L24="Partially Compliant",0.5,IF(L24="Non-Compliant",0,"")))
A25: DIR-QA-11 | B25: Technical security & devices | C25: GAID Art. 10(5), 29(2); NDPA s.39 | D25: Unit devices and online systems use authentication, encryption, updated software and are audited frequently. | E25: Sample 5 unit laptops/desktops: password, screen lock, encryption, antivirus, OS updates; check use of personal email/USB for personal data. | F25: Device checklist; screenshots | G25: High | H25: =$K$5 -> 46342 | I25: =$K$6 -> 46367 | K25: Not Started | M25: =IF(L25="Compliant",1,IF(L25="Partially Compliant",0.5,IF(L25="Non-Compliant",0,"")))
A26: DIR-QA-12 | B26: Third-party processors & DPAs | C26: GAID Art. 34; NDPA s.29 | D26: Vendors/partners processing personal data for Directorate of Quality Assurance have Data Processing Agreements and were vetted. | E26: List third parties receiving data from Directorate of Quality Assurance; inspect DPAs against Art. 34(2). | F26: Vendor list; DPAs | G26: High | H26: =$K$5 -> 46342 | I26: =$K$6 -> 46367 | K26: Not Started | M26: =IF(L26="Compliant",1,IF(L26="Partially Compliant",0.5,IF(L26="Non-Compliant",0,"")))
... A38: DIR-QA-24 | B38: Use of evaluations | C38: GAID Art. 41, 42(5) | D38: Evaluation results used against staff are fair, accurate and not solely automated. | E38: Review how evaluation scores feed appraisal/promotion; confirm human review. | F38: QA procedure; appraisal guidelines | G38: Medium | H38: =$K$5 -> 46342 | I38: =$K$6 -> 46367 | K38: Not Started | M38: =IF(L38="Compliant",1,IF(L38="Partially Compliant",0.5,IF(L38="Non-Compliant",0,"")))
A40: Bold teal CAR Areas = controls specific to this unit. Base controls are listed on the 'CAR Framework' tab.

Sheet DIR-Physical Planning
A1: Compliance Audit Work Plan — Directorate of Physical Planning & Works | N1: ← Back to Dashboard
A2: NDPA 2023 / GAID 2025 — Article 10 Compliance Audit Returns (CAR) | Audit year 2026 | CAR due 31 March 2027
A4: Unit | C4: Directorate of Physical Planning & Works | H4: Lead Auditor | K4: [Enter name]
A5: Unit type | C5: Directorate | H5: Planned Start | K5: 46342
A6: Reports to | C6: Vice-Chancellor | H6: Planned End | K6: 46367
A7: Head of Unit | C7: [Enter name] | H7: Controls in plan | K7: =COUNTA(A15:A37) -> 23
A8: Data subjects | C8: Contractors, artisans, staff housing occupants | H8: Completed | K8: =COUNTIF(K15:K37,"Completed") -> 0
A9: Key personal data | C9: Contractor IDs, staff quarters allocation, maintenance requests | H9: Compliant | K9: =COUNTIF(L15:L37,"Compliant") -> 0
A10: Key systems / records | C10: Works request system, access registers | H10: Partially Compliant | K10: =COUNTIF(L15:L37,"Partially Compliant") -> 0
A11: Inherent data risk | C11: Low | H11: Non-Compliant | K11: =COUNTIF(L15:L37,"Non-Compliant") -> 0
H12: Not Applicable | K12: =COUNTIF(L15:L37,"Not Applicable") -> 0
H13: Compliance Score | K13: =_xlfn.IFERROR(AVERAGE(M15:M37),"")
A14: Ref | B14: CAR Area | C14: GAID / NDPA Reference | D14: Control Objective | E14: Audit Procedure | F14: Evidence to Obtain | G14: Risk | H14: Planned Start | I14: Planned End | J14: Auditor | K14: Status | L14: Compliance Rating | M14: Score | N14: Findings | O14: Recommendation | P14: Management Response / Owner | Q14: Target Date
A15: DIR-PP-01 | B15: ROPA | C15: GAID Art. 13(2)-(3), Art. 52; NDPA s.24(3) | D15: All processing activities of the unit are captured in the Record of Processing Activities (ROPA) submitted to the DPO. | E15: Walk through Directorate of Physical Planning & Works's key processing (staff housing allocation, contractor management, maintenance requests) and confirm each activity is captured in the ROPA with purpose, data categories, recipients and retention. | F15: Unit ROPA extract; process walkthrough notes | G15: Medium | H15: =$K$5 -> 46342 | I15: =$K$6 -> 46367 | K15: Not Started | M15: =IF(L15="Compliant",1,IF(L15="Partially Compliant",0.5,IF(L15="Non-Compliant",0,"")))
A16: DIR-PP-02 | B16: Data inventory & sensitive data | C16: NDPA s.30; GAID Art. 28(3)(d) | D16: Personal and sensitive personal data held by the unit is identified and classified. | E16: Inventory data held (Contractor IDs, staff quarters allocation, maintenance requests); flag sensitive categories and confirm they are recorded as such. | F16: Data inventory; classification register | G16: Medium | H16: =$K$5 -> 46342 | I16: =$K$6 -> 46367 | K16: Not Started | M16: =IF(L16="Compliant",1,IF(L16="Partially Compliant",0.5,IF(L16="Non-Compliant",0,"")))
A17: DIR-PP-03 | B17: Lawful basis | C17: GAID Art. 16, 23; NDPA s.25 | D17: A documented lawful basis exists for each processing activity; legitimate interest supported by LIA. | E17: For each ROPA activity, confirm lawful basis is recorded and appropriate; where legitimate interest is used, inspect Schedule 8 LIA. | F17: Lawful basis register; LIAs | G17: Medium | H17: =$K$5 -> 46342 | I17: =$K$6 -> 46367 | K17: Not Started | M17: =IF(L17="Compliant",1,IF(L17="Partially Compliant",0.5,IF(L17="Non-Compliant",0,"")))
A18: DIR-PP-04 | B18: Consent (CAR disclosure) | C18: GAID Art. 17, 18(1)-(2); NDPA s.26 | D18: Consent is obtained and recorded where required (marketing, sensitive data, children, incompatible further processing, transfers, automated decisions) — CAR must state reliance. | E18: Identify Art. 18(1) activities in Directorate of Physical Planning & Works; test consent capture, records and ease of withdrawal for a sample of 5. | F18: Consent forms/records; withdrawal mechanism | G18: Medium | H18: =$K$5 -> 46342 | I18: =$K$6 -> 46367 | K18: Not Started | M18: =IF(L18="Compliant",1,IF(L18="Partially Compliant",0.5,IF(L18="Non-Compliant",0,"")))
A19: DIR-PP-05 | B19: Privacy notice at collection | C19: GAID Art. 27; Art. 7(j)-(m); NDPA s.27 | D19: Data subjects receive clear privacy information at every collection point (forms, portals, surveys). | E19: Collect all forms/portals used by Directorate of Physical Planning & Works; check each notice against Art. 27(3)(a)-(j). | F19: Forms; screenshots; notice checklist | G19: Medium | H19: =$K$5 -> 46342 | I19: =$K$6 -> 46367 | K19: Not Started | M19: =IF(L19="Compliant",1,IF(L19="Partially Compliant",0.5,IF(L19="Non-Compliant",0,"")))
A20: DIR-PP-06 | B20: Minimisation & purpose limitation | C20: GAID Art. 15 & Sch. 1; NDPA s.24(1)(b),(c) | D20: Only data necessary for the stated purpose is collected and used. | E20: Review fields on Directorate of Physical Planning & Works forms and systems (Works request system, access registers); identify excessive fields (e.g., religion, NIN, BVN) not justified by purpose. | F20: Form review worksheet | G20: Medium | H20: =$K$5 -> 46342 | I20: =$K$6 -> 46367 | K20: Not Started | M20: =IF(L20="Compliant",1,IF(L20="Partially Compliant",0.5,IF(L20="Non-Compliant",0,"")))
A21: DIR-PP-07 | B21: Retention & disposal | C21: GAID Art. 49(3)-(4); NDPA s.24(1)(d) | D21: Retention periods defined; data disposed of securely (default not later than 6 months after purpose ends unless justified). | E21: Obtain retention schedule; inspect archives/systems for data past retention; review disposal records (shredding/wiping). | F21: Retention schedule; disposal certificates | G21: Medium | H21: =$K$5 -> 46342 | I21: =$K$6 -> 46367 | K21: Not Started | M21: =IF(L21="Compliant",1,IF(L21="Partially Compliant",0.5,IF(L21="Non-Compliant",0,"")))
A22: DIR-PP-08 | B22: Accuracy & rectification | C22: GAID Art. 36; NDPA s.24(1)(e) | D22: Data subjects can verify and correct data; input errors by the unit corrected free of charge. | E22: Review rectification procedure (e.g., name/DOB corrections); sample 5 requests for timeliness and absence of fees for unit errors. | F22: Correction requests; procedure | G22: Medium | H22: =$K$5 -> 46342 | I22: =$K$6 -> 46367 | K22: Not Started | M22: =IF(L22="Compliant",1,IF(L22="Partially Compliant",0.5,IF(L22="Non-Compliant",0,"")))
A23: DIR-PP-09 | B23: Data subject rights | C23: GAID Art. 36-38, 40; NDPA s.34-38 | D23: Access, erasure, portability, objection requests and SNAGs are logged, escalated to the DPO and resolved on time. | E23: Enquire about requests received by Directorate of Physical Planning & Works; test log and escalation to DPO. | F23: Rights request log; SNAG responses | G23: Medium | H23: =$K$5 -> 46342 | I23: =$K$6 -> 46367 | K23: Not Started | M23: =IF(L23="Compliant",1,IF(L23="Partially Compliant",0.5,IF(L23="Non-Compliant",0,"")))
A24: DIR-PP-10 | B24: Physical & access security | C24: NDPA s.39; GAID Art. 29 | D24: Physical records and system access are restricted on a need-to-know basis. | E24: Inspect records rooms/cabinets; review user access list for Works request system, access registers and confirm leavers are removed. | F24: Access lists; site inspection photos | G24: Medium | H24: =$K$5 -> 46342 | I24: =$K$6 -> 46367 | K24: Not Started | M24: =IF(L24="Compliant",1,IF(L24="Partially Compliant",0.5,IF(L24="Non-Compliant",0,"")))
A25: DIR-PP-11 | B25: Technical security & devices | C25: GAID Art. 10(5), 29(2); NDPA s.39 | D25: Unit devices and online systems use authentication, encryption, updated software and are audited frequently. | E25: Sample 5 unit laptops/desktops: password, screen lock, encryption, antivirus, OS updates; check use of personal email/USB for personal data. | F25: Device checklist; screenshots | G25: High | H25: =$K$5 -> 46342 | I25: =$K$6 -> 46367 | K25: Not Started | M25: =IF(L25="Compliant",1,IF(L25="Partially Compliant",0.5,IF(L25="Non-Compliant",0,"")))
A26: DIR-PP-12 | B26: Third-party processors & DPAs | C26: GAID Art. 34; NDPA s.29 | D26: Vendors/partners processing personal data for Directorate of Physical Planning & Works have Data Processing Agreements and were vetted. | E26: List third parties receiving data from Directorate of Physical Planning & Works; inspect DPAs against Art. 34(2). | F26: Vendor list; DPAs | G26: Medium | H26: =$K$5 -> 46342 | I26: =$K$6 -> 46367 | K26: Not Started | M26: =IF(L26="Compliant",1,IF(L26="Partially Compliant",0.5,IF(L26="Non-Compliant",0,"")))
... A37: DIR-PP-23 | B37: Contractor data & site access | C37: GAID Art. 34(3),(4) | D37: Contractors/artisans handling university premises data are bound by confidentiality and trained where high risk. | E37: Sample contractor contracts for confidentiality clauses; review site access registers retention. | F37: Contracts; access registers | G37: Low | H37: =$K$5 -> 46342 | I37: =$K$6 -> 46367 | K37: Not Started | M37: =IF(L37="Compliant",1,IF(L37="Partially Compliant",0.5,IF(L37="Non-Compliant",0,"")))
A39: Bold teal CAR Areas = controls specific to this unit. Base controls are listed on the 'CAR Framework' tab.

Sheet DIR-Health Services
A1: Compliance Audit Work Plan — Directorate of Health Services (University Health Centre) | N1: ← Back to Dashboard
A2: NDPA 2023 / GAID 2025 — Article 10 Compliance Audit Returns (CAR) | Audit year 2026 | CAR due 31 March 2027
A4: Unit | C4: Directorate of Health Services (University Health Centre) | H4: Lead Auditor | K4: [Enter name]
A5: Unit type | C5: Directorate | H5: Planned Start | K5: 46342
A6: Reports to | C6: Vice-Chancellor | H6: Planned End | K6: 46367
A7: Head of Unit | C7: [Enter name] | H7: Controls in plan | K7: =COUNTA(A15:A40) -> 26
A8: Data subjects | C8: Students, staff, dependants, patients | H8: Completed | K8: =COUNTIF(K15:K40,"Completed") -> 0
A9: Key personal data | C9: Medical records, diagnoses, test results, health insurance (NHIA/TISHIP) data, counselling notes | H9: Compliant | K9: =COUNTIF(L15:L40,"Compliant") -> 0
A10: Key systems / records | C10: Electronic Medical Records, NHIA portal, lab system | H10: Partially Compliant | K10: =COUNTIF(L15:L40,"Partially Compliant") -> 0
A11: Inherent data risk | C11: High | H11: Non-Compliant | K11: =COUNTIF(L15:L40,"Non-Compliant") -> 0
H12: Not Applicable | K12: =COUNTIF(L15:L40,"Not Applicable") -> 0
H13: Compliance Score | K13: =_xlfn.IFERROR(AVERAGE(M15:M40),"")
A14: Ref | B14: CAR Area | C14: GAID / NDPA Reference | D14: Control Objective | E14: Audit Procedure | F14: Evidence to Obtain | G14: Risk | H14: Planned Start | I14: Planned End | J14: Auditor | K14: Status | L14: Compliance Rating | M14: Score | N14: Findings | O14: Recommendation | P14: Management Response / Owner | Q14: Target Date
A15: DIR-HS-01 | B15: ROPA | C15: GAID Art. 13(2)-(3), Art. 52; NDPA s.24(3) | D15: All processing activities of the unit are captured in the Record of Processing Activities (ROPA) submitted to the DPO. | E15: Walk through Directorate of Health Services (University Health Centre)'s key processing (patient registration, consultation, pharmacy, lab tests, health insurance claims, medical fitness certification) and confirm each activity is captured in the ROPA with purpose, data categories, recipients and retention. | F15: Unit ROPA extract; process walkthrough notes | G15: High | H15: =$K$5 -> 46342 | I15: =$K$6 -> 46367 | K15: Not Started | M15: =IF(L15="Compliant",1,IF(L15="Partially Compliant",0.5,IF(L15="Non-Compliant",0,"")))
A16: DIR-HS-02 | B16: Data inventory & sensitive data | C16: NDPA s.30; GAID Art. 28(3)(d) | D16: Personal and sensitive personal data held by the unit is identified and classified. | E16: Inventory data held (Medical records, diagnoses, test results, health insurance (NHIA/TISHIP) data, counselling notes); flag sensitive categories and confirm they are recorded as such. | F16: Data inventory; classification register | G16: High | H16: =$K$5 -> 46342 | I16: =$K$6 -> 46367 | K16: Not Started | M16: =IF(L16="Compliant",1,IF(L16="Partially Compliant",0.5,IF(L16="Non-Compliant",0,"")))
A17: DIR-HS-03 | B17: Lawful basis | C17: GAID Art. 16, 23; NDPA s.25 | D17: A documented lawful basis exists for each processing activity; legitimate interest supported by LIA. | E17: For each ROPA activity, confirm lawful basis is recorded and appropriate; where legitimate interest is used, inspect Schedule 8 LIA. | F17: Lawful basis register; LIAs | G17: High | H17: =$K$5 -> 46342 | I17: =$K$6 -> 46367 | K17: Not Started | M17: =IF(L17="Compliant",1,IF(L17="Partially Compliant",0.5,IF(L17="Non-Compliant",0,"")))
A18: DIR-HS-04 | B18: Consent (CAR disclosure) | C18: GAID Art. 17, 18(1)-(2); NDPA s.26 | D18: Consent is obtained and recorded where required (marketing, sensitive data, children, incompatible further processing, transfers, automated decisions) — CAR must state reliance. | E18: Identify Art. 18(1) activities in Directorate of Health Services (University Health Centre); test consent capture, records and ease of withdrawal for a sample of 5. | F18: Consent forms/records; withdrawal mechanism | G18: High | H18: =$K$5 -> 46342 | I18: =$K$6 -> 46367 | K18: Not Started | M18: =IF(L18="Compliant",1,IF(L18="Partially Compliant",0.5,IF(L18="Non-Compliant",0,"")))
A19: DIR-HS-05 | B19: Privacy notice at collection | C19: GAID Art. 27; Art. 7(j)-(m); NDPA s.27 | D19: Data subjects receive clear privacy information at every collection point (forms, portals, surveys). | E19: Collect all forms/portals used by Directorate of Health Services (University Health Centre); check each notice against Art. 27(3)(a)-(j). | F19: Forms; screenshots; notice checklist | G19: High | H19: =$K$5 -> 46342 | I19: =$K$6 -> 46367 | K19: Not Started | M19: =IF(L19="Compliant",1,IF(L19="Partially Compliant",0.5,IF(L19="Non-Compliant",0,"")))
A20: DIR-HS-06 | B20: Minimisation & purpose limitation | C20: GAID Art. 15 & Sch. 1; NDPA s.24(1)(b),(c) | D20: Only data necessary for the stated purpose is collected and used. | E20: Review fields on Directorate of Health Services (University Health Centre) forms and systems (Electronic Medical Records, NHIA portal, lab system); identify excessive fields (e.g., religion, NIN, BVN) not justified by purpose. | F20: Form review worksheet | G20: High | H20: =$K$5 -> 46342 | I20: =$K$6 -> 46367 | K20: Not Started | M20: =IF(L20="Compliant",1,IF(L20="Partially Compliant",0.5,IF(L20="Non-Compliant",0,"")))
A21: DIR-HS-07 | B21: Retention & disposal | C21: GAID Art. 49(3)-(4); NDPA s.24(1)(d) | D21: Retention periods defined; data disposed of securely (default not later than 6 months after purpose ends unless justified). | E21: Obtain retention schedule; inspect archives/systems for data past retention; review disposal records (shredding/wiping). | F21: Retention schedule; disposal certificates | G21: High | H21: =$K$5 -> 46342 | I21: =$K$6 -> 46367 | K21: Not Started | M21: =IF(L21="Compliant",1,IF(L21="Partially Compliant",0.5,IF(L21="Non-Compliant",0,"")))
A22: DIR-HS-08 | B22: Accuracy & rectification | C22: GAID Art. 36; NDPA s.24(1)(e) | D22: Data subjects can verify and correct data; input errors by the unit corrected free of charge. | E22: Review rectification procedure (e.g., name/DOB corrections); sample 5 requests for timeliness and absence of fees for unit errors. | F22: Correction requests; procedure | G22: High | H22: =$K$5 -> 46342 | I22: =$K$6 -> 46367 | K22: Not Started | M22: =IF(L22="Compliant",1,IF(L22="Partially Compliant",0.5,IF(L22="Non-Compliant",0,"")))
A23: DIR-HS-09 | B23: Data subject rights | C23: GAID Art. 36-38, 40; NDPA s.34-38 | D23: Access, erasure, portability, objection requests and SNAGs are logged, escalated to the DPO and resolved on time. | E23: Enquire about requests received by Directorate of Health Services (University Health Centre); test log and escalation to DPO. | F23: Rights request log; SNAG responses | G23: High | H23: =$K$5 -> 46342 | I23: =$K$6 -> 46367 | K23: Not Started | M23: =IF(L23="Compliant",1,IF(L23="Partially Compliant",0.5,IF(L23="Non-Compliant",0,"")))
A24: DIR-HS-10 | B24: Physical & access security | C24: NDPA s.39; GAID Art. 29 | D24: Physical records and system access are restricted on a need-to-know basis. | E24: Inspect records rooms/cabinets; review user access list for Electronic Medical Records, NHIA portal, lab system and confirm leavers are removed. | F24: Access lists; site inspection photos | G24: High | H24: =$K$5 -> 46342 | I24: =$K$6 -> 46367 | K24: Not Started | M24: =IF(L24="Compliant",1,IF(L24="Partially Compliant",0.5,IF(L24="Non-Compliant",0,"")))
A25: DIR-HS-11 | B25: Technical security & devices | C25: GAID Art. 10(5), 29(2); NDPA s.39 | D25: Unit devices and online systems use authentication, encryption, updated software and are audited frequently. | E25: Sample 5 unit laptops/desktops: password, screen lock, encryption, antivirus, OS updates; check use of personal email/USB for personal data. | F25: Device checklist; screenshots | G25: High | H25: =$K$5 -> 46342 | I25: =$K$6 -> 46367 | K25: Not Started | M25: =IF(L25="Compliant",1,IF(L25="Partially Compliant",0.5,IF(L25="Non-Compliant",0,"")))
A26: DIR-HS-12 | B26: Third-party processors & DPAs | C26: GAID Art. 34; NDPA s.29 | D26: Vendors/partners processing personal data for Directorate of Health Services (University Health Centre) have Data Processing Agreements and were vetted. | E26: List third parties receiving data from Directorate of Health Services (University Health Centre); inspect DPAs against Art. 34(2). | F26: Vendor list; DPAs | G26: High | H26: =$K$5 -> 46342 | I26: =$K$6 -> 46367 | K26: Not Started | M26: =IF(L26="Compliant",1,IF(L26="Partially Compliant",0.5,IF(L26="Non-Compliant",0,"")))
... A40: DIR-HS-26 | B40: Insurance processors | C40: GAID Art. 34 | D40: DPAs in place with HMOs/NHIA and lab partners. | E40: Inspect agreements with HMOs and external labs for Art. 34(2) clauses. | F40: HMO agreements | G40: High | H40: =$K$5 -> 46342 | I40: =$K$6 -> 46367 | K40: Not Started | M40: =IF(L40="Compliant",1,IF(L40="Partially Compliant",0.5,IF(L40="Non-Compliant",0,"")))
A42: Bold teal CAR Areas = controls specific to this unit. Base controls are listed on the 'CAR Framework' tab.

Sheet DIR-Security Services
A1: Compliance Audit Work Plan — Directorate of Security Services | N1: ← Back to Dashboard
A2: NDPA 2023 / GAID 2025 — Article 10 Compliance Audit Returns (CAR) | Audit year 2026 | CAR due 31 March 2027
A4: Unit | C4: Directorate of Security Services | H4: Lead Auditor | K4: [Enter name]
A5: Unit type | C5: Directorate | H5: Planned Start | K5: 46342
A6: Reports to | C6: Vice-Chancellor | H6: Planned End | K6: 46367
A7: Head of Unit | C7: [Enter name] | H7: Controls in plan | K7: =COUNTA(A15:A40) -> 26
A8: Data subjects | C8: Students, staff, visitors, suspects/complainants | H8: Completed | K8: =COUNTIF(K15:K40,"Completed") -> 0
A9: Key personal data | C9: CCTV footage, visitor logs, incident reports, ID cards, vehicle registration | H9: Compliant | K9: =COUNTIF(L15:L40,"Compliant") -> 0
A10: Key systems / records | C10: CCTV/NVR, visitor register, access control / biometric gates | H10: Partially Compliant | K10: =COUNTIF(L15:L40,"Partially Compliant") -> 0
A11: Inherent data risk | C11: High | H11: Non-Compliant | K11: =COUNTIF(L15:L40,"Non-Compliant") -> 0
H12: Not Applicable | K12: =COUNTIF(L15:L40,"Not Applicable") -> 0
H13: Compliance Score | K13: =_xlfn.IFERROR(AVERAGE(M15:M40),"")
A14: Ref | B14: CAR Area | C14: GAID / NDPA Reference | D14: Control Objective | E14: Audit Procedure | F14: Evidence to Obtain | G14: Risk | H14: Planned Start | I14: Planned End | J14: Auditor | K14: Status | L14: Compliance Rating | M14: Score | N14: Findings | O14: Recommendation | P14: Management Response / Owner | Q14: Target Date
A15: DIR-SS-01 | B15: ROPA | C15: GAID Art. 13(2)-(3), Art. 52; NDPA s.24(3) | D15: All processing activities of the unit are captured in the Record of Processing Activities (ROPA) submitted to the DPO. | E15: Walk through Directorate of Security Services's key processing (CCTV surveillance, visitor management, investigations, gate access control) and confirm each activity is captured in the ROPA with purpose, data categories, recipients and retention. | F15: Unit ROPA extract; process walkthrough notes | G15: High | H15: =$K$5 -> 46342 | I15: =$K$6 -> 46367 | K15: Not Started | M15: =IF(L15="Compliant",1,IF(L15="Partially Compliant",0.5,IF(L15="Non-Compliant",0,"")))
A16: DIR-SS-02 | B16: Data inventory & sensitive data | C16: NDPA s.30; GAID Art. 28(3)(d) | D16: Personal and sensitive personal data held by the unit is identified and classified. | E16: Inventory data held (CCTV footage, visitor logs, incident reports, ID cards, vehicle registration); flag sensitive categories and confirm they are recorded as such. | F16: Data inventory; classification register | G16: High | H16: =$K$5 -> 46342 | I16: =$K$6 -> 46367 | K16: Not Started | M16: =IF(L16="Compliant",1,IF(L16="Partially Compliant",0.5,IF(L16="Non-Compliant",0,"")))
A17: DIR-SS-03 | B17: Lawful basis | C17: GAID Art. 16, 23; NDPA s.25 | D17: A documented lawful basis exists for each processing activity; legitimate interest supported by LIA. | E17: For each ROPA activity, confirm lawful basis is recorded and appropriate; where legitimate interest is used, inspect Schedule 8 LIA. | F17: Lawful basis register; LIAs | G17: High | H17: =$K$5 -> 46342 | I17: =$K$6 -> 46367 | K17: Not Started | M17: =IF(L17="Compliant",1,IF(L17="Partially Compliant",0.5,IF(L17="Non-Compliant",0,"")))
A18: DIR-SS-04 | B18: Consent (CAR disclosure) | C18: GAID Art. 17, 18(1)-(2); NDPA s.26 | D18: Consent is obtained and recorded where required (marketing, sensitive data, children, incompatible further processing, transfers, automated decisions) — CAR must state reliance. | E18: Identify Art. 18(1) activities in Directorate of Security Services; test consent capture, records and ease of withdrawal for a sample of 5. | F18: Consent forms/records; withdrawal mechanism | G18: High | H18: =$K$5 -> 46342 | I18: =$K$6 -> 46367 | K18: Not Started | M18: =IF(L18="Compliant",1,IF(L18="Partially Compliant",0.5,IF(L18="Non-Compliant",0,"")))
A19: DIR-SS-05 | B19: Privacy notice at collection | C19: GAID Art. 27; Art. 7(j)-(m); NDPA s.27 | D19: Data subjects receive clear privacy information at every collection point (forms, portals, surveys). | E19: Collect all forms/portals used by Directorate of Security Services; check each notice against Art. 27(3)(a)-(j). | F19: Forms; screenshots; notice checklist | G19: High | H19: =$K$5 -> 46342 | I19: =$K$6 -> 46367 | K19: Not Started | M19: =IF(L19="Compliant",1,IF(L19="Partially Compliant",0.5,IF(L19="Non-Compliant",0,"")))
A20: DIR-SS-06 | B20: Minimisation & purpose limitation | C20: GAID Art. 15 & Sch. 1; NDPA s.24(1)(b),(c) | D20: Only data necessary for the stated purpose is collected and used. | E20: Review fields on Directorate of Security Services forms and systems (CCTV/NVR, visitor register, access control / biometric gates); identify excessive fields (e.g., religion, NIN, BVN) not justified by purpose. | F20: Form review worksheet | G20: High | H20: =$K$5 -> 46342 | I20: =$K$6 -> 46367 | K20: Not Started | M20: =IF(L20="Compliant",1,IF(L20="Partially Compliant",0.5,IF(L20="Non-Compliant",0,"")))
A21: DIR-SS-07 | B21: Retention & disposal | C21: GAID Art. 49(3)-(4); NDPA s.24(1)(d) | D21: Retention periods defined; data disposed of securely (default not later than 6 months after purpose ends unless justified). | E21: Obtain retention schedule; inspect archives/systems for data past retention; review disposal records (shredding/wiping). | F21: Retention schedule; disposal certificates | G21: High | H21: =$K$5 -> 46342 | I21: =$K$6 -> 46367 | K21: Not Started | M21: =IF(L21="Compliant",1,IF(L21="Partially Compliant",0.5,IF(L21="Non-Compliant",0,"")))
A22: DIR-SS-08 | B22: Accuracy & rectification | C22: GAID Art. 36; NDPA s.24(1)(e) | D22: Data subjects can verify and correct data; input errors by the unit corrected free of charge. | E22: Review rectification procedure (e.g., name/DOB corrections); sample 5 requests for timeliness and absence of fees for unit errors. | F22: Correction requests; procedure | G22: High | H22: =$K$5 -> 46342 | I22: =$K$6 -> 46367 | K22: Not Started | M22: =IF(L22="Compliant",1,IF(L22="Partially Compliant",0.5,IF(L22="Non-Compliant",0,"")))
A23: DIR-SS-09 | B23: Data subject rights | C23: GAID Art. 36-38, 40; NDPA s.34-38 | D23: Access, erasure, portability, objection requests and SNAGs are logged, escalated to the DPO and resolved on time. | E23: Enquire about requests received by Directorate of Security Services; test log and escalation to DPO. | F23: Rights request log; SNAG responses | G23: High | H23: =$K$5 -> 46342 | I23: =$K$6 -> 46367 | K23: Not Started | M23: =IF(L23="Compliant",1,IF(L23="Partially Compliant",0.5,IF(L23="Non-Compliant",0,"")))
A24: DIR-SS-10 | B24: Physical & access security | C24: NDPA s.39; GAID Art. 29 | D24: Physical records and system access are restricted on a need-to-know basis. | E24: Inspect records rooms/cabinets; review user access list for CCTV/NVR, visitor register, access control / biometric gates and confirm leavers are removed. | F24: Access lists; site inspection photos | G24: High | H24: =$K$5 -> 46342 | I24: =$K$6 -> 46367 | K24: Not Started | M24: =IF(L24="Compliant",1,IF(L24="Partially Compliant",0.5,IF(L24="Non-Compliant",0,"")))
A25: DIR-SS-11 | B25: Technical security & devices | C25: GAID Art. 10(5), 29(2); NDPA s.39 | D25: Unit devices and online systems use authentication, encryption, updated software and are audited frequently. | E25: Sample 5 unit laptops/desktops: password, screen lock, encryption, antivirus, OS updates; check use of personal email/USB for personal data. | F25: Device checklist; screenshots | G25: High | H25: =$K$5 -> 46342 | I25: =$K$6 -> 46367 | K25: Not Started | M25: =IF(L25="Compliant",1,IF(L25="Partially Compliant",0.5,IF(L25="Non-Compliant",0,"")))
A26: DIR-SS-12 | B26: Third-party processors & DPAs | C26: GAID Art. 34; NDPA s.29 | D26: Vendors/partners processing personal data for Directorate of Security Services have Data Processing Agreements and were vetted. | E26: List third parties receiving data from Directorate of Security Services; inspect DPAs against Art. 34(2). | F26: Vendor list; DPAs | G26: High | H26: =$K$5 -> 46342 | I26: =$K$6 -> 46367 | K26: Not Started | M26: =IF(L26="Compliant",1,IF(L26="Partially Compliant",0.5,IF(L26="Non-Compliant",0,"")))
... A40: DIR-SS-26 | B40: Biometric access | C40: GAID Art. 18(1)(b), 28(3)(d) | D40: Biometric gate/attendance data has lawful basis, DPIA and security controls. | E40: Confirm biometric systems in use, DPIA, vendor DPA and template storage protection. | F40: Biometric system DPIA; vendor DPA | G40: High | H40: =$K$5 -> 46342 | I40: =$K$6 -> 46367 | K40: Not Started | M40: =IF(L40="Compliant",1,IF(L40="Partially Compliant",0.5,IF(L40="Non-Compliant",0,"")))
A42: Bold teal CAR Areas = controls specific to this unit. Base controls are listed on the 'CAR Framework' tab.

Sheet DIR-Research & Dev
A1: Compliance Audit Work Plan — Directorate of Research, Innovation & Development | N1: ← Back to Dashboard
A2: NDPA 2023 / GAID 2025 — Article 10 Compliance Audit Returns (CAR) | Audit year 2026 | CAR due 31 March 2027
A4: Unit | C4: Directorate of Research, Innovation & Development | H4: Lead Auditor | K4: [Enter name]
A5: Unit type | C5: Directorate | H5: Planned Start | K5: 46342
A6: Reports to | C6: DVC (Research) | H6: Planned End | K6: 46367
A7: Head of Unit | C7: [Enter name] | H7: Controls in plan | K7: =COUNTA(A15:A38) -> 24
A8: Data subjects | C8: Researchers, research participants, grant applicants | H8: Completed | K8: =COUNTIF(K15:K38,"Completed") -> 0
A9: Key personal data | C9: Research proposals, participant data, grant applicant biodata | H9: Compliant | K9: =COUNTIF(L15:L38,"Compliant") -> 0
A10: Key systems / records | C10: Grant management system, ethics committee files | H10: Partially Compliant | K10: =COUNTIF(L15:L38,"Partially Compliant") -> 0
A11: Inherent data risk | C11: Medium | H11: Non-Compliant | K11: =COUNTIF(L15:L38,"Non-Compliant") -> 0
H12: Not Applicable | K12: =COUNTIF(L15:L38,"Not Applicable") -> 0
H13: Compliance Score | K13: =_xlfn.IFERROR(AVERAGE(M15:M38),"")
A14: Ref | B14: CAR Area | C14: GAID / NDPA Reference | D14: Control Objective | E14: Audit Procedure | F14: Evidence to Obtain | G14: Risk | H14: Planned Start | I14: Planned End | J14: Auditor | K14: Status | L14: Compliance Rating | M14: Score | N14: Findings | O14: Recommendation | P14: Management Response / Owner | Q14: Target Date
A15: DIR-RD-01 | B15: ROPA | C15: GAID Art. 13(2)-(3), Art. 52; NDPA s.24(3) | D15: All processing activities of the unit are captured in the Record of Processing Activities (ROPA) submitted to the DPO. | E15: Walk through Directorate of Research, Innovation & Development's key processing (TETFund/IBR grants, research ethics review, IP and innovation) and confirm each activity is captured in the ROPA with purpose, data categories, recipients and retention. | F15: Unit ROPA extract; process walkthrough notes | G15: High | H15: =$K$5 -> 46342 | I15: =$K$6 -> 46367 | K15: Not Started | M15: =IF(L15="Compliant",1,IF(L15="Partially Compliant",0.5,IF(L15="Non-Compliant",0,"")))
A16: DIR-RD-02 | B16: Data inventory & sensitive data | C16: NDPA s.30; GAID Art. 28(3)(d) | D16: Personal and sensitive personal data held by the unit is identified and classified. | E16: Inventory data held (Research proposals, participant data, grant applicant biodata); flag sensitive categories and confirm they are recorded as such. | F16: Data inventory; classification register | G16: High | H16: =$K$5 -> 46342 | I16: =$K$6 -> 46367 | K16: Not Started | M16: =IF(L16="Compliant",1,IF(L16="Partially Compliant",0.5,IF(L16="Non-Compliant",0,"")))
A17: DIR-RD-03 | B17: Lawful basis | C17: GAID Art. 16, 23; NDPA s.25 | D17: A documented lawful basis exists for each processing activity; legitimate interest supported by LIA. | E17: For each ROPA activity, confirm lawful basis is recorded and appropriate; where legitimate interest is used, inspect Schedule 8 LIA. | F17: Lawful basis register; LIAs | G17: High | H17: =$K$5 -> 46342 | I17: =$K$6 -> 46367 | K17: Not Started | M17: =IF(L17="Compliant",1,IF(L17="Partially Compliant",0.5,IF(L17="Non-Compliant",0,"")))
A18: DIR-RD-04 | B18: Consent (CAR disclosure) | C18: GAID Art. 17, 18(1)-(2); NDPA s.26 | D18: Consent is obtained and recorded where required (marketing, sensitive data, children, incompatible further processing, transfers, automated decisions) — CAR must state reliance. | E18: Identify Art. 18(1) activities in Directorate of Research, Innovation & Development; test consent capture, records and ease of withdrawal for a sample of 5. | F18: Consent forms/records; withdrawal mechanism | G18: High | H18: =$K$5 -> 46342 | I18: =$K$6 -> 46367 | K18: Not Started | M18: =IF(L18="Compliant",1,IF(L18="Partially Compliant",0.5,IF(L18="Non-Compliant",0,"")))
A19: DIR-RD-05 | B19: Privacy notice at collection | C19: GAID Art. 27; Art. 7(j)-(m); NDPA s.27 | D19: Data subjects receive clear privacy information at every collection point (forms, portals, surveys). | E19: Collect all forms/portals used by Directorate of Research, Innovation & Development; check each notice against Art. 27(3)(a)-(j). | F19: Forms; screenshots; notice checklist | G19: Medium | H19: =$K$5 -> 46342 | I19: =$K$6 -> 46367 | K19: Not Started | M19: =IF(L19="Compliant",1,IF(L19="Partially Compliant",0.5,IF(L19="Non-Compliant",0,"")))
A20: DIR-RD-06 | B20: Minimisation & purpose limitation | C20: GAID Art. 15 & Sch. 1; NDPA s.24(1)(b),(c) | D20: Only data necessary for the stated purpose is collected and used. | E20: Review fields on Directorate of Research, Innovation & Development forms and systems (Grant management system, ethics committee files); identify excessive fields (e.g., religion, NIN, BVN) not justified by purpose. | F20: Form review worksheet | G20: Medium | H20: =$K$5 -> 46342 | I20: =$K$6 -> 46367 | K20: Not Started | M20: =IF(L20="Compliant",1,IF(L20="Partially Compliant",0.5,IF(L20="Non-Compliant",0,"")))
A21: DIR-RD-07 | B21: Retention & disposal | C21: GAID Art. 49(3)-(4); NDPA s.24(1)(d) | D21: Retention periods defined; data disposed of securely (default not later than 6 months after purpose ends unless justified). | E21: Obtain retention schedule; inspect archives/systems for data past retention; review disposal records (shredding/wiping). | F21: Retention schedule; disposal certificates | G21: Medium | H21: =$K$5 -> 46342 | I21: =$K$6 -> 46367 | K21: Not Started | M21: =IF(L21="Compliant",1,IF(L21="Partially Compliant",0.5,IF(L21="Non-Compliant",0,"")))
A22: DIR-RD-08 | B22: Accuracy & rectification | C22: GAID Art. 36; NDPA s.24(1)(e) | D22: Data subjects can verify and correct data; input errors by the unit corrected free of charge. | E22: Review rectification procedure (e.g., name/DOB corrections); sample 5 requests for timeliness and absence of fees for unit errors. | F22: Correction requests; procedure | G22: Medium | H22: =$K$5 -> 46342 | I22: =$K$6 -> 46367 | K22: Not Started | M22: =IF(L22="Compliant",1,IF(L22="Partially Compliant",0.5,IF(L22="Non-Compliant",0,"")))
A23: DIR-RD-09 | B23: Data subject rights | C23: GAID Art. 36-38, 40; NDPA s.34-38 | D23: Access, erasure, portability, objection requests and SNAGs are logged, escalated to the DPO and resolved on time. | E23: Enquire about requests received by Directorate of Research, Innovation & Development; test log and escalation to DPO. | F23: Rights request log; SNAG responses | G23: Medium | H23: =$K$5 -> 46342 | I23: =$K$6 -> 46367 | K23: Not Started | M23: =IF(L23="Compliant",1,IF(L23="Partially Compliant",0.5,IF(L23="Non-Compliant",0,"")))
A24: DIR-RD-10 | B24: Physical & access security | C24: NDPA s.39; GAID Art. 29 | D24: Physical records and system access are restricted on a need-to-know basis. | E24: Inspect records rooms/cabinets; review user access list for Grant management system, ethics committee files and confirm leavers are removed. | F24: Access lists; site inspection photos | G24: High | H24: =$K$5 -> 46342 | I24: =$K$6 -> 46367 | K24: Not Started | M24: =IF(L24="Compliant",1,IF(L24="Partially Compliant",0.5,IF(L24="Non-Compliant",0,"")))
A25: DIR-RD-11 | B25: Technical security & devices | C25: GAID Art. 10(5), 29(2); NDPA s.39 | D25: Unit devices and online systems use authentication, encryption, updated software and are audited frequently. | E25: Sample 5 unit laptops/desktops: password, screen lock, encryption, antivirus, OS updates; check use of personal email/USB for personal data. | F25: Device checklist; screenshots | G25: High | H25: =$K$5 -> 46342 | I25: =$K$6 -> 46367 | K25: Not Started | M25: =IF(L25="Compliant",1,IF(L25="Partially Compliant",0.5,IF(L25="Non-Compliant",0,"")))
A26: DIR-RD-12 | B26: Third-party processors & DPAs | C26: GAID Art. 34; NDPA s.29 | D26: Vendors/partners processing personal data for Directorate of Research, Innovation & Development have Data Processing Agreements and were vetted. | E26: List third parties receiving data from Directorate of Research, Innovation & Development; inspect DPAs against Art. 34(2). | F26: Vendor list; DPAs | G26: High | H26: =$K$5 -> 46342 | I26: =$K$6 -> 46367 | K26: Not Started | M26: =IF(L26="Compliant",1,IF(L26="Partially Compliant",0.5,IF(L26="Non-Compliant",0,"")))
... A38: DIR-RD-24 | B38: Research exemption use | C38: GAID Art. 5; Art. 38(2)(c) | D38: Reliance on research exemptions still complies with principles, lawful basis, DPO and breach obligations. | E38: Confirm research data management plans address s.24, s.25, s.40 obligations. | F38: Data management plans | G38: Medium | H38: =$K$5 -> 46342 | I38: =$K$6 -> 46367 | K38: Not Started | M38: =IF(L38="Compliant",1,IF(L38="Partially Compliant",0.5,IF(L38="Non-Compliant",0,"")))
A40: Bold teal CAR Areas = controls specific to this unit. Base controls are listed on the 'CAR Framework' tab.

Sheet DIR-Linkages
A1: Compliance Audit Work Plan — Directorate of Linkages & International Collaborations | N1: ← Back to Dashboard
A2: NDPA 2023 / GAID 2025 — Article 10 Compliance Audit Returns (CAR) | Audit year 2026 | CAR due 31 March 2027
A4: Unit | C4: Directorate of Linkages & International Collaborations | H4: Lead Auditor | K4: [Enter name]
A5: Unit type | C5: Directorate | H5: Planned Start | K5: 46342
A6: Reports to | C6: Vice-Chancellor | H6: Planned End | K6: 46367
A7: Head of Unit | C7: [Enter name] | H7: Controls in plan | K7: =COUNTA(A15:A38) -> 24
A8: Data subjects | C8: Exchange students, visiting scholars, foreign partners | H8: Completed | K8: =COUNTIF(K15:K38,"Completed") -> 0
A9: Key personal data | C9: Passport details, visas, transcripts, travel records | H9: Compliant | K9: =COUNTIF(L15:L38,"Compliant") -> 0
A10: Key systems / records | C10: Partner portals, email | H10: Partially Compliant | K10: =COUNTIF(L15:L38,"Partially Compliant") -> 0
A11: Inherent data risk | C11: High | H11: Non-Compliant | K11: =COUNTIF(L15:L38,"Non-Compliant") -> 0
H12: Not Applicable | K12: =COUNTIF(L15:L38,"Not Applicable") -> 0
H13: Compliance Score | K13: =_xlfn.IFERROR(AVERAGE(M15:M38),"")
A14: Ref | B14: CAR Area | C14: GAID / NDPA Reference | D14: Control Objective | E14: Audit Procedure | F14: Evidence to Obtain | G14: Risk | H14: Planned Start | I14: Planned End | J14: Auditor | K14: Status | L14: Compliance Rating | M14: Score | N14: Findings | O14: Recommendation | P14: Management Response / Owner | Q14: Target Date
A15: DIR-LIN-01 | B15: ROPA | C15: GAID Art. 13(2)-(3), Art. 52; NDPA s.24(3) | D15: All processing activities of the unit are captured in the Record of Processing Activities (ROPA) submitted to the DPO. | E15: Walk through Directorate of Linkages & International Collaborations's key processing (student/staff exchange, MoU partnerships, international admissions) and confirm each activity is captured in the ROPA with purpose, data categories, recipients and retention. | F15: Unit ROPA extract; process walkthrough notes | G15: High | H15: =$K$5 -> 46342 | I15: =$K$6 -> 46367 | K15: Not Started | M15: =IF(L15="Compliant",1,IF(L15="Partially Compliant",0.5,IF(L15="Non-Compliant",0,"")))
A16: DIR-LIN-02 | B16: Data inventory & sensitive data | C16: NDPA s.30; GAID Art. 28(3)(d) | D16: Personal and sensitive personal data held by the unit is identified and classified. | E16: Inventory data held (Passport details, visas, transcripts, travel records); flag sensitive categories and confirm they are recorded as such. | F16: Data inventory; classification register | G16: High | H16: =$K$5 -> 46342 | I16: =$K$6 -> 46367 | K16: Not Started | M16: =IF(L16="Compliant",1,IF(L16="Partially Compliant",0.5,IF(L16="Non-Compliant",0,"")))
A17: DIR-LIN-03 | B17: Lawful basis | C17: GAID Art. 16, 23; NDPA s.25 | D17: A documented lawful basis exists for each processing activity; legitimate interest supported by LIA. | E17: For each ROPA activity, confirm lawful basis is recorded and appropriate; where legitimate interest is used, inspect Schedule 8 LIA. | F17: Lawful basis register; LIAs | G17: High | H17: =$K$5 -> 46342 | I17: =$K$6 -> 46367 | K17: Not Started | M17: =IF(L17="Compliant",1,IF(L17="Partially Compliant",0.5,IF(L17="Non-Compliant",0,"")))
A18: DIR-LIN-04 | B18: Consent (CAR disclosure) | C18: GAID Art. 17, 18(1)-(2); NDPA s.26 | D18: Consent is obtained and recorded where required (marketing, sensitive data, children, incompatible further processing, transfers, automated decisions) — CAR must state reliance. | E18: Identify Art. 18(1) activities in Directorate of Linkages & International Collaborations; test consent capture, records and ease of withdrawal for a sample of 5. | F18: Consent forms/records; withdrawal mechanism | G18: High | H18: =$K$5 -> 46342 | I18: =$K$6 -> 46367 | K18: Not Started | M18: =IF(L18="Compliant",1,IF(L18="Partially Compliant",0.5,IF(L18="Non-Compliant",0,"")))
A19: DIR-LIN-05 | B19: Privacy notice at collection | C19: GAID Art. 27; Art. 7(j)-(m); NDPA s.27 | D19: Data subjects receive clear privacy information at every collection point (forms, portals, surveys). | E19: Collect all forms/portals used by Directorate of Linkages & International Collaborations; check each notice against Art. 27(3)(a)-(j). | F19: Forms; screenshots; notice checklist | G19: High | H19: =$K$5 -> 46342 | I19: =$K$6 -> 46367 | K19: Not Started | M19: =IF(L19="Compliant",1,IF(L19="Partially Compliant",0.5,IF(L19="Non-Compliant",0,"")))
A20: DIR-LIN-06 | B20: Minimisation & purpose limitation | C20: GAID Art. 15 & Sch. 1; NDPA s.24(1)(b),(c) | D20: Only data necessary for the stated purpose is collected and used. | E20: Review fields on Directorate of Linkages & International Collaborations forms and systems (Partner portals, email); identify excessive fields (e.g., religion, NIN, BVN) not justified by purpose. | F20: Form review worksheet | G20: High | H20: =$K$5 -> 46342 | I20: =$K$6 -> 46367 | K20: Not Started | M20: =IF(L20="Compliant",1,IF(L20="Partially Compliant",0.5,IF(L20="Non-Compliant",0,"")))
A21: DIR-LIN-07 | B21: Retention & disposal | C21: GAID Art. 49(3)-(4); NDPA s.24(1)(d) | D21: Retention periods defined; data disposed of securely (default not later than 6 months after purpose ends unless justified). | E21: Obtain retention schedule; inspect archives/systems for data past retention; review disposal records (shredding/wiping). | F21: Retention schedule; disposal certificates | G21: High | H21: =$K$5 -> 46342 | I21: =$K$6 -> 46367 | K21: Not Started | M21: =IF(L21="Compliant",1,IF(L21="Partially Compliant",0.5,IF(L21="Non-Compliant",0,"")))
A22: DIR-LIN-08 | B22: Accuracy & rectification | C22: GAID Art. 36; NDPA s.24(1)(e) | D22: Data subjects can verify and correct data; input errors by the unit corrected free of charge. | E22: Review rectification procedure (e.g., name/DOB corrections); sample 5 requests for timeliness and absence of fees for unit errors. | F22: Correction requests; procedure | G22: High | H22: =$K$5 -> 46342 | I22: =$K$6 -> 46367 | K22: Not Started | M22: =IF(L22="Compliant",1,IF(L22="Partially Compliant",0.5,IF(L22="Non-Compliant",0,"")))
A23: DIR-LIN-09 | B23: Data subject rights | C23: GAID Art. 36-38, 40; NDPA s.34-38 | D23: Access, erasure, portability, objection requests and SNAGs are logged, escalated to the DPO and resolved on time. | E23: Enquire about requests received by Directorate of Linkages & International Collaborations; test log and escalation to DPO. | F23: Rights request log; SNAG responses | G23: High | H23: =$K$5 -> 46342 | I23: =$K$6 -> 46367 | K23: Not Started | M23: =IF(L23="Compliant",1,IF(L23="Partially Compliant",0.5,IF(L23="Non-Compliant",0,"")))
A24: DIR-LIN-10 | B24: Physical & access security | C24: NDPA s.39; GAID Art. 29 | D24: Physical records and system access are restricted on a need-to-know basis. | E24: Inspect records rooms/cabinets; review user access list for Partner portals, email and confirm leavers are removed. | F24: Access lists; site inspection photos | G24: High | H24: =$K$5 -> 46342 | I24: =$K$6 -> 46367 | K24: Not Started | M24: =IF(L24="Compliant",1,IF(L24="Partially Compliant",0.5,IF(L24="Non-Compliant",0,"")))
A25: DIR-LIN-11 | B25: Technical security & devices | C25: GAID Art. 10(5), 29(2); NDPA s.39 | D25: Unit devices and online systems use authentication, encryption, updated software and are audited frequently. | E25: Sample 5 unit laptops/desktops: password, screen lock, encryption, antivirus, OS updates; check use of personal email/USB for personal data. | F25: Device checklist; screenshots | G25: High | H25: =$K$5 -> 46342 | I25: =$K$6 -> 46367 | K25: Not Started | M25: =IF(L25="Compliant",1,IF(L25="Partially Compliant",0.5,IF(L25="Non-Compliant",0,"")))
A26: DIR-LIN-12 | B26: Third-party processors & DPAs | C26: GAID Art. 34; NDPA s.29 | D26: Vendors/partners processing personal data for Directorate of Linkages & International Collaborations have Data Processing Agreements and were vetted. | E26: List third parties receiving data from Directorate of Linkages & International Collaborations; inspect DPAs against Art. 34(2). | F26: Vendor list; DPAs | G26: High | H26: =$K$5 -> 46342 | I26: =$K$6 -> 46367 | K26: Not Started | M26: =IF(L26="Compliant",1,IF(L26="Partially Compliant",0.5,IF(L26="Non-Compliant",0,"")))
... A38: DIR-LIN-24 | B38: Consent for transfer | C38: GAID Art. 18(1)(e) | D38: Consent is obtained where transfer is to a country without an NDPC adequacy decision. | E38: Sample 5 exchange participants; confirm informed consent covering transfer risks. | F38: Consent forms | G38: High | H38: =$K$5 -> 46342 | I38: =$K$6 -> 46367 | K38: Not Started | M38: =IF(L38="Compliant",1,IF(L38="Partially Compliant",0.5,IF(L38="Non-Compliant",0,"")))
A40: Bold teal CAR Areas = controls specific to this unit. Base controls are listed on the 'CAR Framework' tab.

Sheet DIR-Student Affairs
A1: Compliance Audit Work Plan — Directorate of Student Affairs | N1: ← Back to Dashboard
A2: NDPA 2023 / GAID 2025 — Article 10 Compliance Audit Returns (CAR) | Audit year 2026 | CAR due 31 March 2027
A4: Unit | C4: Directorate of Student Affairs | H4: Lead Auditor | K4: [Enter name]
A5: Unit type | C5: Directorate | H5: Planned Start | K5: 46342
A6: Reports to | C6: DVC (Academic) | H6: Planned End | K6: 46367
A7: Head of Unit | C7: [Enter name] | H7: Controls in plan | K7: =COUNTA(A15:A39) -> 25
A8: Data subjects | C8: Students, parents/guardians, student union officials | H8: Completed | K8: =COUNTIF(K15:K39,"Completed") -> 0
A9: Key personal data | C9: Hostel allocation, counselling notes, disciplinary records, scholarships, disability records | H9: Compliant | K9: =COUNTIF(L15:L39,"Compliant") -> 0
A10: Key systems / records | C10: Hostel portal, counselling files, SUG records | H10: Partially Compliant | K10: =COUNTIF(L15:L39,"Partially Compliant") -> 0
A11: Inherent data risk | C11: High | H11: Non-Compliant | K11: =COUNTIF(L15:L39,"Non-Compliant") -> 0
H12: Not Applicable | K12: =COUNTIF(L15:L39,"Not Applicable") -> 0
H13: Compliance Score | K13: =_xlfn.IFERROR(AVERAGE(M15:M39),"")
A14: Ref | B14: CAR Area | C14: GAID / NDPA Reference | D14: Control Objective | E14: Audit Procedure | F14: Evidence to Obtain | G14: Risk | H14: Planned Start | I14: Planned End | J14: Auditor | K14: Status | L14: Compliance Rating | M14: Score | N14: Findings | O14: Recommendation | P14: Management Response / Owner | Q14: Target Date
A15: DIR-SA-01 | B15: ROPA | C15: GAID Art. 13(2)-(3), Art. 52; NDPA s.24(3) | D15: All processing activities of the unit are captured in the Record of Processing Activities (ROPA) submitted to the DPO. | E15: Walk through Directorate of Student Affairs's key processing (hostel allocation, counselling, student discipline, scholarships and bursaries) and confirm each activity is captured in the ROPA with purpose, data categories, recipients and retention. | F15: Unit ROPA extract; process walkthrough notes | G15: High | H15: =$K$5 -> 46342 | I15: =$K$6 -> 46367 | K15: Not Started | M15: =IF(L15="Compliant",1,IF(L15="Partially Compliant",0.5,IF(L15="Non-Compliant",0,"")))
A16: DIR-SA-02 | B16: Data inventory & sensitive data | C16: NDPA s.30; GAID Art. 28(3)(d) | D16: Personal and sensitive personal data held by the unit is identified and classified. | E16: Inventory data held (Hostel allocation, counselling notes, disciplinary records, scholarships, disability records); flag sensitive categories and confirm they are recorded as such. | F16: Data inventory; classification register | G16: High | H16: =$K$5 -> 46342 | I16: =$K$6 -> 46367 | K16: Not Started | M16: =IF(L16="Compliant",1,IF(L16="Partially Compliant",0.5,IF(L16="Non-Compliant",0,"")))
A17: DIR-SA-03 | B17: Lawful basis | C17: GAID Art. 16, 23; NDPA s.25 | D17: A documented lawful basis exists for each processing activity; legitimate interest supported by LIA. | E17: For each ROPA activity, confirm lawful basis is recorded and appropriate; where legitimate interest is used, inspect Schedule 8 LIA. | F17: Lawful basis register; LIAs | G17: High | H17: =$K$5 -> 46342 | I17: =$K$6 -> 46367 | K17: Not Started | M17: =IF(L17="Compliant",1,IF(L17="Partially Compliant",0.5,IF(L17="Non-Compliant",0,"")))
A18: DIR-SA-04 | B18: Consent (CAR disclosure) | C18: GAID Art. 17, 18(1)-(2); NDPA s.26 | D18: Consent is obtained and recorded where required (marketing, sensitive data, children, incompatible further processing, transfers, automated decisions) — CAR must state reliance. | E18: Identify Art. 18(1) activities in Directorate of Student Affairs; test consent capture, records and ease of withdrawal for a sample of 5. | F18: Consent forms/records; withdrawal mechanism | G18: High | H18: =$K$5 -> 46342 | I18: =$K$6 -> 46367 | K18: Not Started | M18: =IF(L18="Compliant",1,IF(L18="Partially Compliant",0.5,IF(L18="Non-Compliant",0,"")))
A19: DIR-SA-05 | B19: Privacy notice at collection | C19: GAID Art. 27; Art. 7(j)-(m); NDPA s.27 | D19: Data subjects receive clear privacy information at every collection point (forms, portals, surveys). | E19: Collect all forms/portals used by Directorate of Student Affairs; check each notice against Art. 27(3)(a)-(j). | F19: Forms; screenshots; notice checklist | G19: High | H19: =$K$5 -> 46342 | I19: =$K$6 -> 46367 | K19: Not Started | M19: =IF(L19="Compliant",1,IF(L19="Partially Compliant",0.5,IF(L19="Non-Compliant",0,"")))
A20: DIR-SA-06 | B20: Minimisation & purpose limitation | C20: GAID Art. 15 & Sch. 1; NDPA s.24(1)(b),(c) | D20: Only data necessary for the stated purpose is collected and used. | E20: Review fields on Directorate of Student Affairs forms and systems (Hostel portal, counselling files, SUG records); identify excessive fields (e.g., religion, NIN, BVN) not justified by purpose. | F20: Form review worksheet | G20: High | H20: =$K$5 -> 46342 | I20: =$K$6 -> 46367 | K20: Not Started | M20: =IF(L20="Compliant",1,IF(L20="Partially Compliant",0.5,IF(L20="Non-Compliant",0,"")))
A21: DIR-SA-07 | B21: Retention & disposal | C21: GAID Art. 49(3)-(4); NDPA s.24(1)(d) | D21: Retention periods defined; data disposed of securely (default not later than 6 months after purpose ends unless justified). | E21: Obtain retention schedule; inspect archives/systems for data past retention; review disposal records (shredding/wiping). | F21: Retention schedule; disposal certificates | G21: High | H21: =$K$5 -> 46342 | I21: =$K$6 -> 46367 | K21: Not Started | M21: =IF(L21="Compliant",1,IF(L21="Partially Compliant",0.5,IF(L21="Non-Compliant",0,"")))
A22: DIR-SA-08 | B22: Accuracy & rectification | C22: GAID Art. 36; NDPA s.24(1)(e) | D22: Data subjects can verify and correct data; input errors by the unit corrected free of charge. | E22: Review rectification procedure (e.g., name/DOB corrections); sample 5 requests for timeliness and absence of fees for unit errors. | F22: Correction requests; procedure | G22: High | H22: =$K$5 -> 46342 | I22: =$K$6 -> 46367 | K22: Not Started | M22: =IF(L22="Compliant",1,IF(L22="Partially Compliant",0.5,IF(L22="Non-Compliant",0,"")))
A23: DIR-SA-09 | B23: Data subject rights | C23: GAID Art. 36-38, 40; NDPA s.34-38 | D23: Access, erasure, portability, objection requests and SNAGs are logged, escalated to the DPO and resolved on time. | E23: Enquire about requests received by Directorate of Student Affairs; test log and escalation to DPO. | F23: Rights request log; SNAG responses | G23: High | H23: =$K$5 -> 46342 | I23: =$K$6 -> 46367 | K23: Not Started | M23: =IF(L23="Compliant",1,IF(L23="Partially Compliant",0.5,IF(L23="Non-Compliant",0,"")))
A24: DIR-SA-10 | B24: Physical & access security | C24: NDPA s.39; GAID Art. 29 | D24: Physical records and system access are restricted on a need-to-know basis. | E24: Inspect records rooms/cabinets; review user access list for Hostel portal, counselling files, SUG records and confirm leavers are removed. | F24: Access lists; site inspection photos | G24: High | H24: =$K$5 -> 46342 | I24: =$K$6 -> 46367 | K24: Not Started | M24: =IF(L24="Compliant",1,IF(L24="Partially Compliant",0.5,IF(L24="Non-Compliant",0,"")))
A25: DIR-SA-11 | B25: Technical security & devices | C25: GAID Art. 10(5), 29(2); NDPA s.39 | D25: Unit devices and online systems use authentication, encryption, updated software and are audited frequently. | E25: Sample 5 unit laptops/desktops: password, screen lock, encryption, antivirus, OS updates; check use of personal email/USB for personal data. | F25: Device checklist; screenshots | G25: High | H25: =$K$5 -> 46342 | I25: =$K$6 -> 46367 | K25: Not Started | M25: =IF(L25="Compliant",1,IF(L25="Partially Compliant",0.5,IF(L25="Non-Compliant",0,"")))
A26: DIR-SA-12 | B26: Third-party processors & DPAs | C26: GAID Art. 34; NDPA s.29 | D26: Vendors/partners processing personal data for Directorate of Student Affairs have Data Processing Agreements and were vetted. | E26: List third parties receiving data from Directorate of Student Affairs; inspect DPAs against Art. 34(2). | F26: Vendor list; DPAs | G26: High | H26: =$K$5 -> 46342 | I26: =$K$6 -> 46367 | K26: Not Started | M26: =IF(L26="Compliant",1,IF(L26="Partially Compliant",0.5,IF(L26="Non-Compliant",0,"")))
... A39: DIR-SA-25 | B39: Disciplinary publication | C39: GAID Art. 41, 42(3) | D39: Publication of expulsion/rustication lists limits personal data to what is necessary. | E39: Review notices published in the year for excessive personal data. | F39: Published notices | G39: Medium | H39: =$K$5 -> 46342 | I39: =$K$6 -> 46367 | K39: Not Started | M39: =IF(L39="Compliant",1,IF(L39="Partially Compliant",0.5,IF(L39="Non-Compliant",0,"")))
A41: Bold teal CAR Areas = controls specific to this unit. Base controls are listed on the 'CAR Framework' tab.

Sheet DIR-Advancement
A1: Compliance Audit Work Plan — Directorate of Advancement, Alumni & Endowment | N1: ← Back to Dashboard
A2: NDPA 2023 / GAID 2025 — Article 10 Compliance Audit Returns (CAR) | Audit year 2026 | CAR due 31 March 2027
A4: Unit | C4: Directorate of Advancement, Alumni & Endowment | H4: Lead Auditor | K4: [Enter name]
A5: Unit type | C5: Directorate | H5: Planned Start | K5: 46342
A6: Reports to | C6: Vice-Chancellor | H6: Planned End | K6: 46367
A7: Head of Unit | C7: [Enter name] | H7: Controls in plan | K7: =COUNTA(A15:A38) -> 24
A8: Data subjects | C8: Alumni, donors, prospective donors | H8: Completed | K8: =COUNTIF(K15:K38,"Completed") -> 0
A9: Key personal data | C9: Contact details, employment, donation history, bank details | H9: Compliant | K9: =COUNTIF(L15:L38,"Compliant") -> 0
A10: Key systems / records | C10: Alumni database, CRM, bulk email/SMS tools | H10: Partially Compliant | K10: =COUNTIF(L15:L38,"Partially Compliant") -> 0
A11: Inherent data risk | C11: Medium | H11: Non-Compliant | K11: =COUNTIF(L15:L38,"Non-Compliant") -> 0
H12: Not Applicable | K12: =COUNTIF(L15:L38,"Not Applicable") -> 0
H13: Compliance Score | K13: =_xlfn.IFERROR(AVERAGE(M15:M38),"")
A14: Ref | B14: CAR Area | C14: GAID / NDPA Reference | D14: Control Objective | E14: Audit Procedure | F14: Evidence to Obtain | G14: Risk | H14: Planned Start | I14: Planned End | J14: Auditor | K14: Status | L14: Compliance Rating | M14: Score | N14: Findings | O14: Recommendation | P14: Management Response / Owner | Q14: Target Date
A15: DIR-ADV-01 | B15: ROPA | C15: GAID Art. 13(2)-(3), Art. 52; NDPA s.24(3) | D15: All processing activities of the unit are captured in the Record of Processing Activities (ROPA) submitted to the DPO. | E15: Walk through Directorate of Advancement, Alumni & Endowment's key processing (alumni database, fundraising campaigns, newsletters) and confirm each activity is captured in the ROPA with purpose, data categories, recipients and retention. | F15: Unit ROPA extract; process walkthrough notes | G15: High | H15: =$K$5 -> 46342 | I15: =$K$6 -> 46367 | K15: Not Started | M15: =IF(L15="Compliant",1,IF(L15="Partially Compliant",0.5,IF(L15="Non-Compliant",0,"")))
A16: DIR-ADV-02 | B16: Data inventory & sensitive data | C16: NDPA s.30; GAID Art. 28(3)(d) | D16: Personal and sensitive personal data held by the unit is identified and classified. | E16: Inventory data held (Contact details, employment, donation history, bank details); flag sensitive categories and confirm they are recorded as such. | F16: Data inventory; classification register | G16: High | H16: =$K$5 -> 46342 | I16: =$K$6 -> 46367 | K16: Not Started | M16: =IF(L16="Compliant",1,IF(L16="Partially Compliant",0.5,IF(L16="Non-Compliant",0,"")))
A17: DIR-ADV-03 | B17: Lawful basis | C17: GAID Art. 16, 23; NDPA s.25 | D17: A documented lawful basis exists for each processing activity; legitimate interest supported by LIA. | E17: For each ROPA activity, confirm lawful basis is recorded and appropriate; where legitimate interest is used, inspect Schedule 8 LIA. | F17: Lawful basis register; LIAs | G17: High | H17: =$K$5 -> 46342 | I17: =$K$6 -> 46367 | K17: Not Started | M17: =IF(L17="Compliant",1,IF(L17="Partially Compliant",0.5,IF(L17="Non-Compliant",0,"")))
A18: DIR-ADV-04 | B18: Consent (CAR disclosure) | C18: GAID Art. 17, 18(1)-(2); NDPA s.26 | D18: Consent is obtained and recorded where required (marketing, sensitive data, children, incompatible further processing, transfers, automated decisions) — CAR must state reliance. | E18: Identify Art. 18(1) activities in Directorate of Advancement, Alumni & Endowment; test consent capture, records and ease of withdrawal for a sample of 5. | F18: Consent forms/records; withdrawal mechanism | G18: High | H18: =$K$5 -> 46342 | I18: =$K$6 -> 46367 | K18: Not Started | M18: =IF(L18="Compliant",1,IF(L18="Partially Compliant",0.5,IF(L18="Non-Compliant",0,"")))
A19: DIR-ADV-05 | B19: Privacy notice at collection | C19: GAID Art. 27; Art. 7(j)-(m); NDPA s.27 | D19: Data subjects receive clear privacy information at every collection point (forms, portals, surveys). | E19: Collect all forms/portals used by Directorate of Advancement, Alumni & Endowment; check each notice against Art. 27(3)(a)-(j). | F19: Forms; screenshots; notice checklist | G19: Medium | H19: =$K$5 -> 46342 | I19: =$K$6 -> 46367 | K19: Not Started | M19: =IF(L19="Compliant",1,IF(L19="Partially Compliant",0.5,IF(L19="Non-Compliant",0,"")))
A20: DIR-ADV-06 | B20: Minimisation & purpose limitation | C20: GAID Art. 15 & Sch. 1; NDPA s.24(1)(b),(c) | D20: Only data necessary for the stated purpose is collected and used. | E20: Review fields on Directorate of Advancement, Alumni & Endowment forms and systems (Alumni database, CRM, bulk email/SMS tools); identify excessive fields (e.g., religion, NIN, BVN) not justified by purpose. | F20: Form review worksheet | G20: Medium | H20: =$K$5 -> 46342 | I20: =$K$6 -> 46367 | K20: Not Started | M20: =IF(L20="Compliant",1,IF(L20="Partially Compliant",0.5,IF(L20="Non-Compliant",0,"")))
A21: DIR-ADV-07 | B21: Retention & disposal | C21: GAID Art. 49(3)-(4); NDPA s.24(1)(d) | D21: Retention periods defined; data disposed of securely (default not later than 6 months after purpose ends unless justified). | E21: Obtain retention schedule; inspect archives/systems for data past retention; review disposal records (shredding/wiping). | F21: Retention schedule; disposal certificates | G21: Medium | H21: =$K$5 -> 46342 | I21: =$K$6 -> 46367 | K21: Not Started | M21: =IF(L21="Compliant",1,IF(L21="Partially Compliant",0.5,IF(L21="Non-Compliant",0,"")))
A22: DIR-ADV-08 | B22: Accuracy & rectification | C22: GAID Art. 36; NDPA s.24(1)(e) | D22: Data subjects can verify and correct data; input errors by the unit corrected free of charge. | E22: Review rectification procedure (e.g., name/DOB corrections); sample 5 requests for timeliness and absence of fees for unit errors. | F22: Correction requests; procedure | G22: Medium | H22: =$K$5 -> 46342 | I22: =$K$6 -> 46367 | K22: Not Started | M22: =IF(L22="Compliant",1,IF(L22="Partially Compliant",0.5,IF(L22="Non-Compliant",0,"")))
A23: DIR-ADV-09 | B23: Data subject rights | C23: GAID Art. 36-38, 40; NDPA s.34-38 | D23: Access, erasure, portability, objection requests and SNAGs are logged, escalated to the DPO and resolved on time. | E23: Enquire about requests received by Directorate of Advancement, Alumni & Endowment; test log and escalation to DPO. | F23: Rights request log; SNAG responses | G23: Medium | H23: =$K$5 -> 46342 | I23: =$K$6 -> 46367 | K23: Not Started | M23: =IF(L23="Compliant",1,IF(L23="Partially Compliant",0.5,IF(L23="Non-Compliant",0,"")))
A24: DIR-ADV-10 | B24: Physical & access security | C24: NDPA s.39; GAID Art. 29 | D24: Physical records and system access are restricted on a need-to-know basis. | E24: Inspect records rooms/cabinets; review user access list for Alumni database, CRM, bulk email/SMS tools and confirm leavers are removed. | F24: Access lists; site inspection photos | G24: High | H24: =$K$5 -> 46342 | I24: =$K$6 -> 46367 | K24: Not Started | M24: =IF(L24="Compliant",1,IF(L24="Partially Compliant",0.5,IF(L24="Non-Compliant",0,"")))
A25: DIR-ADV-11 | B25: Technical security & devices | C25: GAID Art. 10(5), 29(2); NDPA s.39 | D25: Unit devices and online systems use authentication, encryption, updated software and are audited frequently. | E25: Sample 5 unit laptops/desktops: password, screen lock, encryption, antivirus, OS updates; check use of personal email/USB for personal data. | F25: Device checklist; screenshots | G25: High | H25: =$K$5 -> 46342 | I25: =$K$6 -> 46367 | K25: Not Started | M25: =IF(L25="Compliant",1,IF(L25="Partially Compliant",0.5,IF(L25="Non-Compliant",0,"")))
A26: DIR-ADV-12 | B26: Third-party processors & DPAs | C26: GAID Art. 34; NDPA s.29 | D26: Vendors/partners processing personal data for Directorate of Advancement, Alumni & Endowment have Data Processing Agreements and were vetted. | E26: List third parties receiving data from Directorate of Advancement, Alumni & Endowment; inspect DPAs against Art. 34(2). | F26: Vendor list; DPAs | G26: High | H26: =$K$5 -> 46342 | I26: =$K$6 -> 46367 | K26: Not Started | M26: =IF(L26="Compliant",1,IF(L26="Partially Compliant",0.5,IF(L26="Non-Compliant",0,"")))
... A38: DIR-ADV-24 | B38: Bulk messaging processors | C38: GAID Art. 34, 45 | D38: Bulk SMS/email/CRM vendors have DPAs and transfer safeguards. | E38: Inspect vendor DPAs and data location. | F38: Vendor DPAs | G38: Medium | H38: =$K$5 -> 46342 | I38: =$K$6 -> 46367 | K38: Not Started | M38: =IF(L38="Compliant",1,IF(L38="Partially Compliant",0.5,IF(L38="Non-Compliant",0,"")))
A40: Bold teal CAR Areas = controls specific to this unit. Base controls are listed on the 'CAR Framework' tab.

Sheet DEPT-HR Establishments
A1: Compliance Audit Work Plan — Registry – Establishments / Human Resources | N1: ← Back to Dashboard
A2: NDPA 2023 / GAID 2025 — Article 10 Compliance Audit Returns (CAR) | Audit year 2026 | CAR due 31 March 2027
A4: Unit | C4: Registry – Establishments / Human Resources | H4: Lead Auditor | K4: [Enter name]
A5: Unit type | C5: Department | H5: Planned Start | K5: 46391
A6: Reports to | C6: Registrar | H6: Planned End | K6: 46409
A7: Head of Unit | C7: [Enter name] | H7: Controls in plan | K7: =COUNTA(A15:A39) -> 25
A8: Data subjects | C8: Staff, job applicants, next of kin, pensioners | H8: Completed | K8: =COUNTIF(K15:K39,"Completed") -> 0
A9: Key personal data | C9: Staff files, NIN, BVN, next of kin, medical, promotion, disciplinary records | H9: Compliant | K9: =COUNTIF(L15:L39,"Compliant") -> 0
A10: Key systems / records | C10: IPPIS, HR records, recruitment portal, personnel files | H10: Partially Compliant | K10: =COUNTIF(L15:L39,"Partially Compliant") -> 0
A11: Inherent data risk | C11: High | H11: Non-Compliant | K11: =COUNTIF(L15:L39,"Non-Compliant") -> 0
H12: Not Applicable | K12: =COUNTIF(L15:L39,"Not Applicable") -> 0
H13: Compliance Score | K13: =_xlfn.IFERROR(AVERAGE(M15:M39),"")
A14: Ref | B14: CAR Area | C14: GAID / NDPA Reference | D14: Control Objective | E14: Audit Procedure | F14: Evidence to Obtain | G14: Risk | H14: Planned Start | I14: Planned End | J14: Auditor | K14: Status | L14: Compliance Rating | M14: Score | N14: Findings | O14: Recommendation | P14: Management Response / Owner | Q14: Target Date
A15: DEPT-HE-01 | B15: ROPA | C15: GAID Art. 13(2)-(3), Art. 52; NDPA s.24(3) | D15: All processing activities of the unit are captured in the Record of Processing Activities (ROPA) submitted to the DPO. | E15: Walk through Registry – Establishments / Human Resources's key processing (recruitment, staff records, promotion, discipline, pensions) and confirm each activity is captured in the ROPA with purpose, data categories, recipients and retention. | F15: Unit ROPA extract; process walkthrough notes | G15: High | H15: =$K$5 -> 46391 | I15: =$K$6 -> 46409 | K15: Not Started | M15: =IF(L15="Compliant",1,IF(L15="Partially Compliant",0.5,IF(L15="Non-Compliant",0,"")))
A16: DEPT-HE-02 | B16: Data inventory & sensitive data | C16: NDPA s.30; GAID Art. 28(3)(d) | D16: Personal and sensitive personal data held by the unit is identified and classified. | E16: Inventory data held (Staff files, NIN, BVN, next of kin, medical, promotion, disciplinary records); flag sensitive categories and confirm they are recorded as such. | F16: Data inventory; classification register | G16: High | H16: =$K$5 -> 46391 | I16: =$K$6 -> 46409 | K16: Not Started | M16: =IF(L16="Compliant",1,IF(L16="Partially Compliant",0.5,IF(L16="Non-Compliant",0,"")))
A17: DEPT-HE-03 | B17: Lawful basis | C17: GAID Art. 16, 23; NDPA s.25 | D17: A documented lawful basis exists for each processing activity; legitimate interest supported by LIA. | E17: For each ROPA activity, confirm lawful basis is recorded and appropriate; where legitimate interest is used, inspect Schedule 8 LIA. | F17: Lawful basis register; LIAs | G17: High | H17: =$K$5 -> 46391 | I17: =$K$6 -> 46409 | K17: Not Started | M17: =IF(L17="Compliant",1,IF(L17="Partially Compliant",0.5,IF(L17="Non-Compliant",0,"")))
A18: DEPT-HE-04 | B18: Consent (CAR disclosure) | C18: GAID Art. 17, 18(1)-(2); NDPA s.26 | D18: Consent is obtained and recorded where required (marketing, sensitive data, children, incompatible further processing, transfers, automated decisions) — CAR must state reliance. | E18: Identify Art. 18(1) activities in Registry – Establishments / Human Resources; test consent capture, records and ease of withdrawal for a sample of 5. | F18: Consent forms/records; withdrawal mechanism | G18: High | H18: =$K$5 -> 46391 | I18: =$K$6 -> 46409 | K18: Not Started | M18: =IF(L18="Compliant",1,IF(L18="Partially Compliant",0.5,IF(L18="Non-Compliant",0,"")))
A19: DEPT-HE-05 | B19: Privacy notice at collection | C19: GAID Art. 27; Art. 7(j)-(m); NDPA s.27 | D19: Data subjects receive clear privacy information at every collection point (forms, portals, surveys). | E19: Collect all forms/portals used by Registry – Establishments / Human Resources; check each notice against Art. 27(3)(a)-(j). | F19: Forms; screenshots; notice checklist | G19: High | H19: =$K$5 -> 46391 | I19: =$K$6 -> 46409 | K19: Not Started | M19: =IF(L19="Compliant",1,IF(L19="Partially Compliant",0.5,IF(L19="Non-Compliant",0,"")))
A20: DEPT-HE-06 | B20: Minimisation & purpose limitation | C20: GAID Art. 15 & Sch. 1; NDPA s.24(1)(b),(c) | D20: Only data necessary for the stated purpose is collected and used. | E20: Review fields on Registry – Establishments / Human Resources forms and systems (IPPIS, HR records, recruitment portal, personnel files); identify excessive fields (e.g., religion, NIN, BVN) not justified by purpose. | F20: Form review worksheet | G20: High | H20: =$K$5 -> 46391 | I20: =$K$6 -> 46409 | K20: Not Started | M20: =IF(L20="Compliant",1,IF(L20="Partially Compliant",0.5,IF(L20="Non-Compliant",0,"")))
A21: DEPT-HE-07 | B21: Retention & disposal | C21: GAID Art. 49(3)-(4); NDPA s.24(1)(d) | D21: Retention periods defined; data disposed of securely (default not later than 6 months after purpose ends unless justified). | E21: Obtain retention schedule; inspect archives/systems for data past retention; review disposal records (shredding/wiping). | F21: Retention schedule; disposal certificates | G21: High | H21: =$K$5 -> 46391 | I21: =$K$6 -> 46409 | K21: Not Started | M21: =IF(L21="Compliant",1,IF(L21="Partially Compliant",0.5,IF(L21="Non-Compliant",0,"")))
A22: DEPT-HE-08 | B22: Accuracy & rectification | C22: GAID Art. 36; NDPA s.24(1)(e) | D22: Data subjects can verify and correct data; input errors by the unit corrected free of charge. | E22: Review rectification procedure (e.g., name/DOB corrections); sample 5 requests for timeliness and absence of fees for unit errors. | F22: Correction requests; procedure | G22: High | H22: =$K$5 -> 46391 | I22: =$K$6 -> 46409 | K22: Not Started | M22: =IF(L22="Compliant",1,IF(L22="Partially Compliant",0.5,IF(L22="Non-Compliant",0,"")))
A23: DEPT-HE-09 | B23: Data subject rights | C23: GAID Art. 36-38, 40; NDPA s.34-38 | D23: Access, erasure, portability, objection requests and SNAGs are logged, escalated to the DPO and resolved on time. | E23: Enquire about requests received by Registry – Establishments / Human Resources; test log and escalation to DPO. | F23: Rights request log; SNAG responses | G23: High | H23: =$K$5 -> 46391 | I23: =$K$6 -> 46409 | K23: Not Started | M23: =IF(L23="Compliant",1,IF(L23="Partially Compliant",0.5,IF(L23="Non-Compliant",0,"")))
A24: DEPT-HE-10 | B24: Physical & access security | C24: NDPA s.39; GAID Art. 29 | D24: Physical records and system access are restricted on a need-to-know basis. | E24: Inspect records rooms/cabinets; review user access list for IPPIS, HR records, recruitment portal, personnel files and confirm leavers are removed. | F24: Access lists; site inspection photos | G24: High | H24: =$K$5 -> 46391 | I24: =$K$6 -> 46409 | K24: Not Started | M24: =IF(L24="Compliant",1,IF(L24="Partially Compliant",0.5,IF(L24="Non-Compliant",0,"")))
A25: DEPT-HE-11 | B25: Technical security & devices | C25: GAID Art. 10(5), 29(2); NDPA s.39 | D25: Unit devices and online systems use authentication, encryption, updated software and are audited frequently. | E25: Sample 5 unit laptops/desktops: password, screen lock, encryption, antivirus, OS updates; check use of personal email/USB for personal data. | F25: Device checklist; screenshots | G25: High | H25: =$K$5 -> 46391 | I25: =$K$6 -> 46409 | K25: Not Started | M25: =IF(L25="Compliant",1,IF(L25="Partially Compliant",0.5,IF(L25="Non-Compliant",0,"")))
A26: DEPT-HE-12 | B26: Third-party processors & DPAs | C26: GAID Art. 34; NDPA s.29 | D26: Vendors/partners processing personal data for Registry – Establishments / Human Resources have Data Processing Agreements and were vetted. | E26: List third parties receiving data from Registry – Establishments / Human Resources; inspect DPAs against Art. 34(2). | F26: Vendor list; DPAs | G26: High | H26: =$K$5 -> 46391 | I26: =$K$6 -> 46409 | K26: Not Started | M26: =IF(L26="Compliant",1,IF(L26="Partially Compliant",0.5,IF(L26="Non-Compliant",0,"")))
... A39: DEPT-HE-25 | B39: Personnel file security | C39: NDPA s.39; GAID Art. 29 | D39: Personnel files secured in locked registry with sign-out log. | E39: Physically inspect records room and test file movement register. | F39: File movement register | G39: High | H39: =$K$5 -> 46391 | I39: =$K$6 -> 46409 | K39: Not Started | M39: =IF(L39="Compliant",1,IF(L39="Partially Compliant",0.5,IF(L39="Non-Compliant",0,"")))
A41: Bold teal CAR Areas = controls specific to this unit. Base controls are listed on the 'CAR Framework' tab.

Sheet DEPT-Admissions
A1: Compliance Audit Work Plan — Registry – Admissions Office | N1: ← Back to Dashboard
A2: NDPA 2023 / GAID 2025 — Article 10 Compliance Audit Returns (CAR) | Audit year 2026 | CAR due 31 March 2027
A4: Unit | C4: Registry – Admissions Office | H4: Lead Auditor | K4: [Enter name]
A5: Unit type | C5: Department | H5: Planned Start | K5: 46391
A6: Reports to | C6: Registrar | H6: Planned End | K6: 46409
A7: Head of Unit | C7: [Enter name] | H7: Controls in plan | K7: =COUNTA(A15:A40) -> 26
A8: Data subjects | C8: UTME/DE applicants (incl. minors), parents | H8: Completed | K8: =COUNTIF(K15:K40,"Completed") -> 0
A9: Key personal data | C9: JAMB CAPS data, O'level results, post-UTME scores, photographs | H9: Compliant | K9: =COUNTIF(L15:L40,"Compliant") -> 0
A10: Key systems / records | C10: JAMB CAPS, admissions portal, screening CBT | H10: Partially Compliant | K10: =COUNTIF(L15:L40,"Partially Compliant") -> 0
A11: Inherent data risk | C11: High | H11: Non-Compliant | K11: =COUNTIF(L15:L40,"Non-Compliant") -> 0
H12: Not Applicable | K12: =COUNTIF(L15:L40,"Not Applicable") -> 0
H13: Compliance Score | K13: =_xlfn.IFERROR(AVERAGE(M15:M40),"")
A14: Ref | B14: CAR Area | C14: GAID / NDPA Reference | D14: Control Objective | E14: Audit Procedure | F14: Evidence to Obtain | G14: Risk | H14: Planned Start | I14: Planned End | J14: Auditor | K14: Status | L14: Compliance Rating | M14: Score | N14: Findings | O14: Recommendation | P14: Management Response / Owner | Q14: Target Date
A15: DEPT-ADM-01 | B15: ROPA | C15: GAID Art. 13(2)-(3), Art. 52; NDPA s.24(3) | D15: All processing activities of the unit are captured in the Record of Processing Activities (ROPA) submitted to the DPO. | E15: Walk through Registry – Admissions Office's key processing (post-UTME screening, CAPS admission processing, result verification with WAEC/NECO) and confirm each activity is captured in the ROPA with purpose, data categories, recipients and retention. | F15: Unit ROPA extract; process walkthrough notes | G15: High | H15: =$K$5 -> 46391 | I15: =$K$6 -> 46409 | K15: Not Started | M15: =IF(L15="Compliant",1,IF(L15="Partially Compliant",0.5,IF(L15="Non-Compliant",0,"")))
A16: DEPT-ADM-02 | B16: Data inventory & sensitive data | C16: NDPA s.30; GAID Art. 28(3)(d) | D16: Personal and sensitive personal data held by the unit is identified and classified. | E16: Inventory data held (JAMB CAPS data, O'level results, post-UTME scores, photographs); flag sensitive categories and confirm they are recorded as such. | F16: Data inventory; classification register | G16: High | H16: =$K$5 -> 46391 | I16: =$K$6 -> 46409 | K16: Not Started | M16: =IF(L16="Compliant",1,IF(L16="Partially Compliant",0.5,IF(L16="Non-Compliant",0,"")))
A17: DEPT-ADM-03 | B17: Lawful basis | C17: GAID Art. 16, 23; NDPA s.25 | D17: A documented lawful basis exists for each processing activity; legitimate interest supported by LIA. | E17: For each ROPA activity, confirm lawful basis is recorded and appropriate; where legitimate interest is used, inspect Schedule 8 LIA. | F17: Lawful basis register; LIAs | G17: High | H17: =$K$5 -> 46391 | I17: =$K$6 -> 46409 | K17: Not Started | M17: =IF(L17="Compliant",1,IF(L17="Partially Compliant",0.5,IF(L17="Non-Compliant",0,"")))
A18: DEPT-ADM-04 | B18: Consent (CAR disclosure) | C18: GAID Art. 17, 18(1)-(2); NDPA s.26 | D18: Consent is obtained and recorded where required (marketing, sensitive data, children, incompatible further processing, transfers, automated decisions) — CAR must state reliance. | E18: Identify Art. 18(1) activities in Registry – Admissions Office; test consent capture, records and ease of withdrawal for a sample of 5. | F18: Consent forms/records; withdrawal mechanism | G18: High | H18: =$K$5 -> 46391 | I18: =$K$6 -> 46409 | K18: Not Started | M18: =IF(L18="Compliant",1,IF(L18="Partially Compliant",0.5,IF(L18="Non-Compliant",0,"")))
A19: DEPT-ADM-05 | B19: Privacy notice at collection | C19: GAID Art. 27; Art. 7(j)-(m); NDPA s.27 | D19: Data subjects receive clear privacy information at every collection point (forms, portals, surveys). | E19: Collect all forms/portals used by Registry – Admissions Office; check each notice against Art. 27(3)(a)-(j). | F19: Forms; screenshots; notice checklist | G19: High | H19: =$K$5 -> 46391 | I19: =$K$6 -> 46409 | K19: Not Started | M19: =IF(L19="Compliant",1,IF(L19="Partially Compliant",0.5,IF(L19="Non-Compliant",0,"")))
A20: DEPT-ADM-06 | B20: Minimisation & purpose limitation | C20: GAID Art. 15 & Sch. 1; NDPA s.24(1)(b),(c) | D20: Only data necessary for the stated purpose is collected and used. | E20: Review fields on Registry – Admissions Office forms and systems (JAMB CAPS, admissions portal, screening CBT); identify excessive fields (e.g., religion, NIN, BVN) not justified by purpose. | F20: Form review worksheet | G20: High | H20: =$K$5 -> 46391 | I20: =$K$6 -> 46409 | K20: Not Started | M20: =IF(L20="Compliant",1,IF(L20="Partially Compliant",0.5,IF(L20="Non-Compliant",0,"")))
A21: DEPT-ADM-07 | B21: Retention & disposal | C21: GAID Art. 49(3)-(4); NDPA s.24(1)(d) | D21: Retention periods defined; data disposed of securely (default not later than 6 months after purpose ends unless justified). | E21: Obtain retention schedule; inspect archives/systems for data past retention; review disposal records (shredding/wiping). | F21: Retention schedule; disposal certificates | G21: High | H21: =$K$5 -> 46391 | I21: =$K$6 -> 46409 | K21: Not Started | M21: =IF(L21="Compliant",1,IF(L21="Partially Compliant",0.5,IF(L21="Non-Compliant",0,"")))
A22: DEPT-ADM-08 | B22: Accuracy & rectification | C22: GAID Art. 36; NDPA s.24(1)(e) | D22: Data subjects can verify and correct data; input errors by the unit corrected free of charge. | E22: Review rectification procedure (e.g., name/DOB corrections); sample 5 requests for timeliness and absence of fees for unit errors. | F22: Correction requests; procedure | G22: High | H22: =$K$5 -> 46391 | I22: =$K$6 -> 46409 | K22: Not Started | M22: =IF(L22="Compliant",1,IF(L22="Partially Compliant",0.5,IF(L22="Non-Compliant",0,"")))
A23: DEPT-ADM-09 | B23: Data subject rights | C23: GAID Art. 36-38, 40; NDPA s.34-38 | D23: Access, erasure, portability, objection requests and SNAGs are logged, escalated to the DPO and resolved on time. | E23: Enquire about requests received by Registry – Admissions Office; test log and escalation to DPO. | F23: Rights request log; SNAG responses | G23: High | H23: =$K$5 -> 46391 | I23: =$K$6 -> 46409 | K23: Not Started | M23: =IF(L23="Compliant",1,IF(L23="Partially Compliant",0.5,IF(L23="Non-Compliant",0,"")))
A24: DEPT-ADM-10 | B24: Physical & access security | C24: NDPA s.39; GAID Art. 29 | D24: Physical records and system access are restricted on a need-to-know basis. | E24: Inspect records rooms/cabinets; review user access list for JAMB CAPS, admissions portal, screening CBT and confirm leavers are removed. | F24: Access lists; site inspection photos | G24: High | H24: =$K$5 -> 46391 | I24: =$K$6 -> 46409 | K24: Not Started | M24: =IF(L24="Compliant",1,IF(L24="Partially Compliant",0.5,IF(L24="Non-Compliant",0,"")))
A25: DEPT-ADM-11 | B25: Technical security & devices | C25: GAID Art. 10(5), 29(2); NDPA s.39 | D25: Unit devices and online systems use authentication, encryption, updated software and are audited frequently. | E25: Sample 5 unit laptops/desktops: password, screen lock, encryption, antivirus, OS updates; check use of personal email/USB for personal data. | F25: Device checklist; screenshots | G25: High | H25: =$K$5 -> 46391 | I25: =$K$6 -> 46409 | K25: Not Started | M25: =IF(L25="Compliant",1,IF(L25="Partially Compliant",0.5,IF(L25="Non-Compliant",0,"")))
A26: DEPT-ADM-12 | B26: Third-party processors & DPAs | C26: GAID Art. 34; NDPA s.29 | D26: Vendors/partners processing personal data for Registry – Admissions Office have Data Processing Agreements and were vetted. | E26: List third parties receiving data from Registry – Admissions Office; inspect DPAs against Art. 34(2). | F26: Vendor list; DPAs | G26: High | H26: =$K$5 -> 46391 | I26: =$K$6 -> 46409 | K26: Not Started | M26: =IF(L26="Compliant",1,IF(L26="Partially Compliant",0.5,IF(L26="Non-Compliant",0,"")))
... A40: DEPT-ADM-26 | B40: Automated screening decisions | C40: GAID Art. 18(1)(f); NDPA s.37 | D40: Admission decisions are not solely automated, or consent/review mechanism exists. | E40: Walk through cut-off and ranking logic; confirm human review and appeal route. | F40: Screening procedure; appeal records | G40: Medium | H40: =$K$5 -> 46391 | I40: =$K$6 -> 46409 | K40: Not Started | M40: =IF(L40="Compliant",1,IF(L40="Partially Compliant",0.5,IF(L40="Non-Compliant",0,"")))
A42: Bold teal CAR Areas = controls specific to this unit. Base controls are listed on the 'CAR Framework' tab.

Sheet DEPT-Exams & Records
A1: Compliance Audit Work Plan — Registry – Examinations & Records | N1: ← Back to Dashboard
A2: NDPA 2023 / GAID 2025 — Article 10 Compliance Audit Returns (CAR) | Audit year 2026 | CAR due 31 March 2027
A4: Unit | C4: Registry – Examinations & Records | H4: Lead Auditor | K4: [Enter name]
A5: Unit type | C5: Department | H5: Planned Start | K5: 46391
A6: Reports to | C6: Registrar | H6: Planned End | K6: 46409
A7: Head of Unit | C7: [Enter name] | H7: Controls in plan | K7: =COUNTA(A15:A38) -> 24
A8: Data subjects | C8: Students, graduates, employers, verification agencies | H8: Completed | K8: =COUNTIF(K15:K38,"Completed") -> 0
A9: Key personal data | C9: Results, transcripts, certificates, verification requests | H9: Compliant | K9: =COUNTIF(L15:L38,"Compliant") -> 0
A10: Key systems / records | C10: Results processing system, transcript portal | H10: Partially Compliant | K10: =COUNTIF(L15:L38,"Partially Compliant") -> 0
A11: Inherent data risk | C11: High | H11: Non-Compliant | K11: =COUNTIF(L15:L38,"Non-Compliant") -> 0
H12: Not Applicable | K12: =COUNTIF(L15:L38,"Not Applicable") -> 0
H13: Compliance Score | K13: =_xlfn.IFERROR(AVERAGE(M15:M38),"")
A14: Ref | B14: CAR Area | C14: GAID / NDPA Reference | D14: Control Objective | E14: Audit Procedure | F14: Evidence to Obtain | G14: Risk | H14: Planned Start | I14: Planned End | J14: Auditor | K14: Status | L14: Compliance Rating | M14: Score | N14: Findings | O14: Recommendation | P14: Management Response / Owner | Q14: Target Date
A15: DEPT-ER-01 | B15: ROPA | C15: GAID Art. 13(2)-(3), Art. 52; NDPA s.24(3) | D15: All processing activities of the unit are captured in the Record of Processing Activities (ROPA) submitted to the DPO. | E15: Walk through Registry – Examinations & Records's key processing (result compilation, transcript issuance, certificate verification) and confirm each activity is captured in the ROPA with purpose, data categories, recipients and retention. | F15: Unit ROPA extract; process walkthrough notes | G15: High | H15: =$K$5 -> 46391 | I15: =$K$6 -> 46409 | K15: Not Started | M15: =IF(L15="Compliant",1,IF(L15="Partially Compliant",0.5,IF(L15="Non-Compliant",0,"")))
A16: DEPT-ER-02 | B16: Data inventory & sensitive data | C16: NDPA s.30; GAID Art. 28(3)(d) | D16: Personal and sensitive personal data held by the unit is identified and classified. | E16: Inventory data held (Results, transcripts, certificates, verification requests); flag sensitive categories and confirm they are recorded as such. | F16: Data inventory; classification register | G16: High | H16: =$K$5 -> 46391 | I16: =$K$6 -> 46409 | K16: Not Started | M16: =IF(L16="Compliant",1,IF(L16="Partially Compliant",0.5,IF(L16="Non-Compliant",0,"")))
A17: DEPT-ER-03 | B17: Lawful basis | C17: GAID Art. 16, 23; NDPA s.25 | D17: A documented lawful basis exists for each processing activity; legitimate interest supported by LIA. | E17: For each ROPA activity, confirm lawful basis is recorded and appropriate; where legitimate interest is used, inspect Schedule 8 LIA. | F17: Lawful basis register; LIAs | G17: High | H17: =$K$5 -> 46391 | I17: =$K$6 -> 46409 | K17: Not Started | M17: =IF(L17="Compliant",1,IF(L17="Partially Compliant",0.5,IF(L17="Non-Compliant",0,"")))
A18: DEPT-ER-04 | B18: Consent (CAR disclosure) | C18: GAID Art. 17, 18(1)-(2); NDPA s.26 | D18: Consent is obtained and recorded where required (marketing, sensitive data, children, incompatible further processing, transfers, automated decisions) — CAR must state reliance. | E18: Identify Art. 18(1) activities in Registry – Examinations & Records; test consent capture, records and ease of withdrawal for a sample of 5. | F18: Consent forms/records; withdrawal mechanism | G18: High | H18: =$K$5 -> 46391 | I18: =$K$6 -> 46409 | K18: Not Started | M18: =IF(L18="Compliant",1,IF(L18="Partially Compliant",0.5,IF(L18="Non-Compliant",0,"")))
A19: DEPT-ER-05 | B19: Privacy notice at collection | C19: GAID Art. 27; Art. 7(j)-(m); NDPA s.27 | D19: Data subjects receive clear privacy information at every collection point (forms, portals, surveys). | E19: Collect all forms/portals used by Registry – Examinations & Records; check each notice against Art. 27(3)(a)-(j). | F19: Forms; screenshots; notice checklist | G19: High | H19: =$K$5 -> 46391 | I19: =$K$6 -> 46409 | K19: Not Started | M19: =IF(L19="Compliant",1,IF(L19="Partially Compliant",0.5,IF(L19="Non-Compliant",0,"")))
A20: DEPT-ER-06 | B20: Minimisation & purpose limitation | C20: GAID Art. 15 & Sch. 1; NDPA s.24(1)(b),(c) | D20: Only data necessary for the stated purpose is collected and used. | E20: Review fields on Registry – Examinations & Records forms and systems (Results processing system, transcript portal); identify excessive fields (e.g., religion, NIN, BVN) not justified by purpose. | F20: Form review worksheet | G20: High | H20: =$K$5 -> 46391 | I20: =$K$6 -> 46409 | K20: Not Started | M20: =IF(L20="Compliant",1,IF(L20="Partially Compliant",0.5,IF(L20="Non-Compliant",0,"")))
A21: DEPT-ER-07 | B21: Retention & disposal | C21: GAID Art. 49(3)-(4); NDPA s.24(1)(d) | D21: Retention periods defined; data disposed of securely (default not later than 6 months after purpose ends unless justified). | E21: Obtain retention schedule; inspect archives/systems for data past retention; review disposal records (shredding/wiping). | F21: Retention schedule; disposal certificates | G21: High | H21: =$K$5 -> 46391 | I21: =$K$6 -> 46409 | K21: Not Started | M21: =IF(L21="Compliant",1,IF(L21="Partially Compliant",0.5,IF(L21="Non-Compliant",0,"")))
A22: DEPT-ER-08 | B22: Accuracy & rectification | C22: GAID Art. 36; NDPA s.24(1)(e) | D22: Data subjects can verify and correct data; input errors by the unit corrected free of charge. | E22: Review rectification procedure (e.g., name/DOB corrections); sample 5 requests for timeliness and absence of fees for unit errors. | F22: Correction requests; procedure | G22: High | H22: =$K$5 -> 46391 | I22: =$K$6 -> 46409 | K22: Not Started | M22: =IF(L22="Compliant",1,IF(L22="Partially Compliant",0.5,IF(L22="Non-Compliant",0,"")))
A23: DEPT-ER-09 | B23: Data subject rights | C23: GAID Art. 36-38, 40; NDPA s.34-38 | D23: Access, erasure, portability, objection requests and SNAGs are logged, escalated to the DPO and resolved on time. | E23: Enquire about requests received by Registry – Examinations & Records; test log and escalation to DPO. | F23: Rights request log; SNAG responses | G23: High | H23: =$K$5 -> 46391 | I23: =$K$6 -> 46409 | K23: Not Started | M23: =IF(L23="Compliant",1,IF(L23="Partially Compliant",0.5,IF(L23="Non-Compliant",0,"")))
A24: DEPT-ER-10 | B24: Physical & access security | C24: NDPA s.39; GAID Art. 29 | D24: Physical records and system access are restricted on a need-to-know basis. | E24: Inspect records rooms/cabinets; review user access list for Results processing system, transcript portal and confirm leavers are removed. | F24: Access lists; site inspection photos | G24: High | H24: =$K$5 -> 46391 | I24: =$K$6 -> 46409 | K24: Not Started | M24: =IF(L24="Compliant",1,IF(L24="Partially Compliant",0.5,IF(L24="Non-Compliant",0,"")))
A25: DEPT-ER-11 | B25: Technical security & devices | C25: GAID Art. 10(5), 29(2); NDPA s.39 | D25: Unit devices and online systems use authentication, encryption, updated software and are audited frequently. | E25: Sample 5 unit laptops/desktops: password, screen lock, encryption, antivirus, OS updates; check use of personal email/USB for personal data. | F25: Device checklist; screenshots | G25: High | H25: =$K$5 -> 46391 | I25: =$K$6 -> 46409 | K25: Not Started | M25: =IF(L25="Compliant",1,IF(L25="Partially Compliant",0.5,IF(L25="Non-Compliant",0,"")))
A26: DEPT-ER-12 | B26: Third-party processors & DPAs | C26: GAID Art. 34; NDPA s.29 | D26: Vendors/partners processing personal data for Registry – Examinations & Records have Data Processing Agreements and were vetted. | E26: List third parties receiving data from Registry – Examinations & Records; inspect DPAs against Art. 34(2). | F26: Vendor list; DPAs | G26: High | H26: =$K$5 -> 46391 | I26: =$K$6 -> 46409 | K26: Not Started | M26: =IF(L26="Compliant",1,IF(L26="Partially Compliant",0.5,IF(L26="Non-Compliant",0,"")))
... A38: DEPT-ER-24 | B38: Result integrity | C38: GAID Art. 36; NDPA s.24(1)(e) | D38: Result amendments are authorised, logged and traceable to source. | E38: Sample 10 result changes; trace to Senate approval and audit trail. | F38: Audit trail; Senate approvals | G38: High | H38: =$K$5 -> 46391 | I38: =$K$6 -> 46409 | K38: Not Started | M38: =IF(L38="Compliant",1,IF(L38="Partially Compliant",0.5,IF(L38="Non-Compliant",0,"")))
A40: Bold teal CAR Areas = controls specific to this unit. Base controls are listed on the 'CAR Framework' tab.

Sheet DEPT-Council & Senate
A1: Compliance Audit Work Plan — Registry – Council & Senate Affairs | N1: ← Back to Dashboard
A2: NDPA 2023 / GAID 2025 — Article 10 Compliance Audit Returns (CAR) | Audit year 2026 | CAR due 31 March 2027
A4: Unit | C4: Registry – Council & Senate Affairs | H4: Lead Auditor | K4: [Enter name]
A5: Unit type | C5: Department | H5: Planned Start | K5: 46391
A6: Reports to | C6: Registrar | H6: Planned End | K6: 46409
A7: Head of Unit | C7: [Enter name] | H7: Controls in plan | K7: =COUNTA(A15:A37) -> 23
A8: Data subjects | C8: Council/Senate members, students and staff discussed in minutes | H8: Completed | K8: =COUNTIF(K15:K37,"Completed") -> 0
A9: Key personal data | C9: Minutes containing disciplinary, appointment and appeal decisions | H9: Compliant | K9: =COUNTIF(L15:L37,"Compliant") -> 0
A10: Key systems / records | C10: Minutes archive, board papers | H10: Partially Compliant | K10: =COUNTIF(L15:L37,"Partially Compliant") -> 0
A11: Inherent data risk | C11: Medium | H11: Non-Compliant | K11: =COUNTIF(L15:L37,"Non-Compliant") -> 0
H12: Not Applicable | K12: =COUNTIF(L15:L37,"Not Applicable") -> 0
H13: Compliance Score | K13: =_xlfn.IFERROR(AVERAGE(M15:M37),"")
A14: Ref | B14: CAR Area | C14: GAID / NDPA Reference | D14: Control Objective | E14: Audit Procedure | F14: Evidence to Obtain | G14: Risk | H14: Planned Start | I14: Planned End | J14: Auditor | K14: Status | L14: Compliance Rating | M14: Score | N14: Findings | O14: Recommendation | P14: Management Response / Owner | Q14: Target Date
A15: DEPT-CS-01 | B15: ROPA | C15: GAID Art. 13(2)-(3), Art. 52; NDPA s.24(3) | D15: All processing activities of the unit are captured in the Record of Processing Activities (ROPA) submitted to the DPO. | E15: Walk through Registry – Council & Senate Affairs's key processing (preparing and circulating Council/Senate papers and minutes) and confirm each activity is captured in the ROPA with purpose, data categories, recipients and retention. | F15: Unit ROPA extract; process walkthrough notes | G15: High | H15: =$K$5 -> 46391 | I15: =$K$6 -> 46409 | K15: Not Started | M15: =IF(L15="Compliant",1,IF(L15="Partially Compliant",0.5,IF(L15="Non-Compliant",0,"")))
A16: DEPT-CS-02 | B16: Data inventory & sensitive data | C16: NDPA s.30; GAID Art. 28(3)(d) | D16: Personal and sensitive personal data held by the unit is identified and classified. | E16: Inventory data held (Minutes containing disciplinary, appointment and appeal decisions); flag sensitive categories and confirm they are recorded as such. | F16: Data inventory; classification register | G16: High | H16: =$K$5 -> 46391 | I16: =$K$6 -> 46409 | K16: Not Started | M16: =IF(L16="Compliant",1,IF(L16="Partially Compliant",0.5,IF(L16="Non-Compliant",0,"")))
A17: DEPT-CS-03 | B17: Lawful basis | C17: GAID Art. 16, 23; NDPA s.25 | D17: A documented lawful basis exists for each processing activity; legitimate interest supported by LIA. | E17: For each ROPA activity, confirm lawful basis is recorded and appropriate; where legitimate interest is used, inspect Schedule 8 LIA. | F17: Lawful basis register; LIAs | G17: High | H17: =$K$5 -> 46391 | I17: =$K$6 -> 46409 | K17: Not Started | M17: =IF(L17="Compliant",1,IF(L17="Partially Compliant",0.5,IF(L17="Non-Compliant",0,"")))
A18: DEPT-CS-04 | B18: Consent (CAR disclosure) | C18: GAID Art. 17, 18(1)-(2); NDPA s.26 | D18: Consent is obtained and recorded where required (marketing, sensitive data, children, incompatible further processing, transfers, automated decisions) — CAR must state reliance. | E18: Identify Art. 18(1) activities in Registry – Council & Senate Affairs; test consent capture, records and ease of withdrawal for a sample of 5. | F18: Consent forms/records; withdrawal mechanism | G18: High | H18: =$K$5 -> 46391 | I18: =$K$6 -> 46409 | K18: Not Started | M18: =IF(L18="Compliant",1,IF(L18="Partially Compliant",0.5,IF(L18="Non-Compliant",0,"")))
A19: DEPT-CS-05 | B19: Privacy notice at collection | C19: GAID Art. 27; Art. 7(j)-(m); NDPA s.27 | D19: Data subjects receive clear privacy information at every collection point (forms, portals, surveys). | E19: Collect all forms/portals used by Registry – Council & Senate Affairs; check each notice against Art. 27(3)(a)-(j). | F19: Forms; screenshots; notice checklist | G19: Medium | H19: =$K$5 -> 46391 | I19: =$K$6 -> 46409 | K19: Not Started | M19: =IF(L19="Compliant",1,IF(L19="Partially Compliant",0.5,IF(L19="Non-Compliant",0,"")))
A20: DEPT-CS-06 | B20: Minimisation & purpose limitation | C20: GAID Art. 15 & Sch. 1; NDPA s.24(1)(b),(c) | D20: Only data necessary for the stated purpose is collected and used. | E20: Review fields on Registry – Council & Senate Affairs forms and systems (Minutes archive, board papers); identify excessive fields (e.g., religion, NIN, BVN) not justified by purpose. | F20: Form review worksheet | G20: Medium | H20: =$K$5 -> 46391 | I20: =$K$6 -> 46409 | K20: Not Started | M20: =IF(L20="Compliant",1,IF(L20="Partially Compliant",0.5,IF(L20="Non-Compliant",0,"")))
A21: DEPT-CS-07 | B21: Retention & disposal | C21: GAID Art. 49(3)-(4); NDPA s.24(1)(d) | D21: Retention periods defined; data disposed of securely (default not later than 6 months after purpose ends unless justified). | E21: Obtain retention schedule; inspect archives/systems for data past retention; review disposal records (shredding/wiping). | F21: Retention schedule; disposal certificates | G21: Medium | H21: =$K$5 -> 46391 | I21: =$K$6 -> 46409 | K21: Not Started | M21: =IF(L21="Compliant",1,IF(L21="Partially Compliant",0.5,IF(L21="Non-Compliant",0,"")))
A22: DEPT-CS-08 | B22: Accuracy & rectification | C22: GAID Art. 36; NDPA s.24(1)(e) | D22: Data subjects can verify and correct data; input errors by the unit corrected free of charge. | E22: Review rectification procedure (e.g., name/DOB corrections); sample 5 requests for timeliness and absence of fees for unit errors. | F22: Correction requests; procedure | G22: Medium | H22: =$K$5 -> 46391 | I22: =$K$6 -> 46409 | K22: Not Started | M22: =IF(L22="Compliant",1,IF(L22="Partially Compliant",0.5,IF(L22="Non-Compliant",0,"")))
A23: DEPT-CS-09 | B23: Data subject rights | C23: GAID Art. 36-38, 40; NDPA s.34-38 | D23: Access, erasure, portability, objection requests and SNAGs are logged, escalated to the DPO and resolved on time. | E23: Enquire about requests received by Registry – Council & Senate Affairs; test log and escalation to DPO. | F23: Rights request log; SNAG responses | G23: Medium | H23: =$K$5 -> 46391 | I23: =$K$6 -> 46409 | K23: Not Started | M23: =IF(L23="Compliant",1,IF(L23="Partially Compliant",0.5,IF(L23="Non-Compliant",0,"")))
A24: DEPT-CS-10 | B24: Physical & access security | C24: NDPA s.39; GAID Art. 29 | D24: Physical records and system access are restricted on a need-to-know basis. | E24: Inspect records rooms/cabinets; review user access list for Minutes archive, board papers and confirm leavers are removed. | F24: Access lists; site inspection photos | G24: High | H24: =$K$5 -> 46391 | I24: =$K$6 -> 46409 | K24: Not Started | M24: =IF(L24="Compliant",1,IF(L24="Partially Compliant",0.5,IF(L24="Non-Compliant",0,"")))
A25: DEPT-CS-11 | B25: Technical security & devices | C25: GAID Art. 10(5), 29(2); NDPA s.39 | D25: Unit devices and online systems use authentication, encryption, updated software and are audited frequently. | E25: Sample 5 unit laptops/desktops: password, screen lock, encryption, antivirus, OS updates; check use of personal email/USB for personal data. | F25: Device checklist; screenshots | G25: High | H25: =$K$5 -> 46391 | I25: =$K$6 -> 46409 | K25: Not Started | M25: =IF(L25="Compliant",1,IF(L25="Partially Compliant",0.5,IF(L25="Non-Compliant",0,"")))
A26: DEPT-CS-12 | B26: Third-party processors & DPAs | C26: GAID Art. 34; NDPA s.29 | D26: Vendors/partners processing personal data for Registry – Council & Senate Affairs have Data Processing Agreements and were vetted. | E26: List third parties receiving data from Registry – Council & Senate Affairs; inspect DPAs against Art. 34(2). | F26: Vendor list; DPAs | G26: High | H26: =$K$5 -> 46391 | I26: =$K$6 -> 46409 | K26: Not Started | M26: =IF(L26="Compliant",1,IF(L26="Partially Compliant",0.5,IF(L26="Non-Compliant",0,"")))
... A37: DEPT-CS-23 | B37: Circulation of papers | C37: GAID Art. 15; NDPA s.39 | D37: Board papers containing personal data are circulated securely and retrieved/destroyed after use. | E37: Review distribution method (email/WhatsApp/hard copy) and retrieval practice. | F37: Distribution list; procedure | G37: Medium | H37: =$K$5 -> 46391 | I37: =$K$6 -> 46409 | K37: Not Started | M37: =IF(L37="Compliant",1,IF(L37="Partially Compliant",0.5,IF(L37="Non-Compliant",0,"")))
A39: Bold teal CAR Areas = controls specific to this unit. Base controls are listed on the 'CAR Framework' tab.

Sheet DEPT-Bursary
A1: Compliance Audit Work Plan — Bursary Department | N1: ← Back to Dashboard
A2: NDPA 2023 / GAID 2025 — Article 10 Compliance Audit Returns (CAR) | Audit year 2026 | CAR due 31 March 2027
A4: Unit | C4: Bursary Department | H4: Lead Auditor | K4: [Enter name]
A5: Unit type | C5: Department | H5: Planned Start | K5: 46391
A6: Reports to | C6: Vice-Chancellor | H6: Planned End | K6: 46409
A7: Head of Unit | C7: [Enter name] | H7: Controls in plan | K7: =COUNTA(A15:A38) -> 24
A8: Data subjects | C8: Students, staff, vendors, parents | H8: Completed | K8: =COUNTIF(K15:K38,"Completed") -> 0
A9: Key personal data | C9: Bank details, BVN, payroll, fee payments, tax IDs | H9: Compliant | K9: =COUNTIF(L15:L38,"Compliant") -> 0
A10: Key systems / records | C10: Remita/TSA, payment gateways, payroll, accounting system | H10: Partially Compliant | K10: =COUNTIF(L15:L38,"Partially Compliant") -> 0
A11: Inherent data risk | C11: High | H11: Non-Compliant | K11: =COUNTIF(L15:L38,"Non-Compliant") -> 0
H12: Not Applicable | K12: =COUNTIF(L15:L38,"Not Applicable") -> 0
H13: Compliance Score | K13: =_xlfn.IFERROR(AVERAGE(M15:M38),"")
A14: Ref | B14: CAR Area | C14: GAID / NDPA Reference | D14: Control Objective | E14: Audit Procedure | F14: Evidence to Obtain | G14: Risk | H14: Planned Start | I14: Planned End | J14: Auditor | K14: Status | L14: Compliance Rating | M14: Score | N14: Findings | O14: Recommendation | P14: Management Response / Owner | Q14: Target Date
A15: DEPT-BUR-01 | B15: ROPA | C15: GAID Art. 13(2)-(3), Art. 52; NDPA s.24(3) | D15: All processing activities of the unit are captured in the Record of Processing Activities (ROPA) submitted to the DPO. | E15: Walk through Bursary Department's key processing (fee collection, payroll, vendor payments, refunds) and confirm each activity is captured in the ROPA with purpose, data categories, recipients and retention. | F15: Unit ROPA extract; process walkthrough notes | G15: High | H15: =$K$5 -> 46391 | I15: =$K$6 -> 46409 | K15: Not Started | M15: =IF(L15="Compliant",1,IF(L15="Partially Compliant",0.5,IF(L15="Non-Compliant",0,"")))
A16: DEPT-BUR-02 | B16: Data inventory & sensitive data | C16: NDPA s.30; GAID Art. 28(3)(d) | D16: Personal and sensitive personal data held by the unit is identified and classified. | E16: Inventory data held (Bank details, BVN, payroll, fee payments, tax IDs); flag sensitive categories and confirm they are recorded as such. | F16: Data inventory; classification register | G16: High | H16: =$K$5 -> 46391 | I16: =$K$6 -> 46409 | K16: Not Started | M16: =IF(L16="Compliant",1,IF(L16="Partially Compliant",0.5,IF(L16="Non-Compliant",0,"")))
A17: DEPT-BUR-03 | B17: Lawful basis | C17: GAID Art. 16, 23; NDPA s.25 | D17: A documented lawful basis exists for each processing activity; legitimate interest supported by LIA. | E17: For each ROPA activity, confirm lawful basis is recorded and appropriate; where legitimate interest is used, inspect Schedule 8 LIA. | F17: Lawful basis register; LIAs | G17: High | H17: =$K$5 -> 46391 | I17: =$K$6 -> 46409 | K17: Not Started | M17: =IF(L17="Compliant",1,IF(L17="Partially Compliant",0.5,IF(L17="Non-Compliant",0,"")))
A18: DEPT-BUR-04 | B18: Consent (CAR disclosure) | C18: GAID Art. 17, 18(1)-(2); NDPA s.26 | D18: Consent is obtained and recorded where required (marketing, sensitive data, children, incompatible further processing, transfers, automated decisions) — CAR must state reliance. | E18: Identify Art. 18(1) activities in Bursary Department; test consent capture, records and ease of withdrawal for a sample of 5. | F18: Consent forms/records; withdrawal mechanism | G18: High | H18: =$K$5 -> 46391 | I18: =$K$6 -> 46409 | K18: Not Started | M18: =IF(L18="Compliant",1,IF(L18="Partially Compliant",0.5,IF(L18="Non-Compliant",0,"")))
A19: DEPT-BUR-05 | B19: Privacy notice at collection | C19: GAID Art. 27; Art. 7(j)-(m); NDPA s.27 | D19: Data subjects receive clear privacy information at every collection point (forms, portals, surveys). | E19: Collect all forms/portals used by Bursary Department; check each notice against Art. 27(3)(a)-(j). | F19: Forms; screenshots; notice checklist | G19: High | H19: =$K$5 -> 46391 | I19: =$K$6 -> 46409 | K19: Not Started | M19: =IF(L19="Compliant",1,IF(L19="Partially Compliant",0.5,IF(L19="Non-Compliant",0,"")))
A20: DEPT-BUR-06 | B20: Minimisation & purpose limitation | C20: GAID Art. 15 & Sch. 1; NDPA s.24(1)(b),(c) | D20: Only data necessary for the stated purpose is collected and used. | E20: Review fields on Bursary Department forms and systems (Remita/TSA, payment gateways, payroll, accounting system); identify excessive fields (e.g., religion, NIN, BVN) not justified by purpose. | F20: Form review worksheet | G20: High | H20: =$K$5 -> 46391 | I20: =$K$6 -> 46409 | K20: Not Started | M20: =IF(L20="Compliant",1,IF(L20="Partially Compliant",0.5,IF(L20="Non-Compliant",0,"")))
A21: DEPT-BUR-07 | B21: Retention & disposal | C21: GAID Art. 49(3)-(4); NDPA s.24(1)(d) | D21: Retention periods defined; data disposed of securely (default not later than 6 months after purpose ends unless justified). | E21: Obtain retention schedule; inspect archives/systems for data past retention; review disposal records (shredding/wiping). | F21: Retention schedule; disposal certificates | G21: High | H21: =$K$5 -> 46391 | I21: =$K$6 -> 46409 | K21: Not Started | M21: =IF(L21="Compliant",1,IF(L21="Partially Compliant",0.5,IF(L21="Non-Compliant",0,"")))
A22: DEPT-BUR-08 | B22: Accuracy & rectification | C22: GAID Art. 36; NDPA s.24(1)(e) | D22: Data subjects can verify and correct data; input errors by the unit corrected free of charge. | E22: Review rectification procedure (e.g., name/DOB corrections); sample 5 requests for timeliness and absence of fees for unit errors. | F22: Correction requests; procedure | G22: High | H22: =$K$5 -> 46391 | I22: =$K$6 -> 46409 | K22: Not Started | M22: =IF(L22="Compliant",1,IF(L22="Partially Compliant",0.5,IF(L22="Non-Compliant",0,"")))
A23: DEPT-BUR-09 | B23: Data subject rights | C23: GAID Art. 36-38, 40; NDPA s.34-38 | D23: Access, erasure, portability, objection requests and SNAGs are logged, escalated to the DPO and resolved on time. | E23: Enquire about requests received by Bursary Department; test log and escalation to DPO. | F23: Rights request log; SNAG responses | G23: High | H23: =$K$5 -> 46391 | I23: =$K$6 -> 46409 | K23: Not Started | M23: =IF(L23="Compliant",1,IF(L23="Partially Compliant",0.5,IF(L23="Non-Compliant",0,"")))
A24: DEPT-BUR-10 | B24: Physical & access security | C24: NDPA s.39; GAID Art. 29 | D24: Physical records and system access are restricted on a need-to-know basis. | E24: Inspect records rooms/cabinets; review user access list for Remita/TSA, payment gateways, payroll, accounting system and confirm leavers are removed. | F24: Access lists; site inspection photos | G24: High | H24: =$K$5 -> 46391 | I24: =$K$6 -> 46409 | K24: Not Started | M24: =IF(L24="Compliant",1,IF(L24="Partially Compliant",0.5,IF(L24="Non-Compliant",0,"")))
A25: DEPT-BUR-11 | B25: Technical security & devices | C25: GAID Art. 10(5), 29(2); NDPA s.39 | D25: Unit devices and online systems use authentication, encryption, updated software and are audited frequently. | E25: Sample 5 unit laptops/desktops: password, screen lock, encryption, antivirus, OS updates; check use of personal email/USB for personal data. | F25: Device checklist; screenshots | G25: High | H25: =$K$5 -> 46391 | I25: =$K$6 -> 46409 | K25: Not Started | M25: =IF(L25="Compliant",1,IF(L25="Partially Compliant",0.5,IF(L25="Non-Compliant",0,"")))
A26: DEPT-BUR-12 | B26: Third-party processors & DPAs | C26: GAID Art. 34; NDPA s.29 | D26: Vendors/partners processing personal data for Bursary Department have Data Processing Agreements and were vetted. | E26: List third parties receiving data from Bursary Department; inspect DPAs against Art. 34(2). | F26: Vendor list; DPAs | G26: High | H26: =$K$5 -> 46391 | I26: =$K$6 -> 46409 | K26: Not Started | M26: =IF(L26="Compliant",1,IF(L26="Partially Compliant",0.5,IF(L26="Non-Compliant",0,"")))
... A38: DEPT-BUR-24 | B38: Financial data security | C38: NDPA s.39; GAID Art. 29 | D38: Payroll and bank data restricted by role; exports encrypted. | E38: Test system access rights; review how payroll schedules are sent to banks. | F38: Access list; transmission method | G38: High | H38: =$K$5 -> 46391 | I38: =$K$6 -> 46409 | K38: Not Started | M38: =IF(L38="Compliant",1,IF(L38="Partially Compliant",0.5,IF(L38="Non-Compliant",0,"")))
A40: Bold teal CAR Areas = controls specific to this unit. Base controls are listed on the 'CAR Framework' tab.

Sheet DEPT-Library
A1: Compliance Audit Work Plan — University Library | N1: ← Back to Dashboard
A2: NDPA 2023 / GAID 2025 — Article 10 Compliance Audit Returns (CAR) | Audit year 2026 | CAR due 31 March 2027
A4: Unit | C4: University Library | H4: Lead Auditor | K4: [Enter name]
A5: Unit type | C5: Department | H5: Planned Start | K5: 46391
A6: Reports to | C6: Vice-Chancellor | H6: Planned End | K6: 46409
A7: Head of Unit | C7: [Enter name] | H7: Controls in plan | K7: =COUNTA(A15:A38) -> 24
A8: Data subjects | C8: Students, staff, external readers | H8: Completed | K8: =COUNTIF(K15:K38,"Completed") -> 0
A9: Key personal data | C9: Patron records, borrowing history, e-resource access logs | H9: Compliant | K9: =COUNTIF(L15:L38,"Compliant") -> 0
A10: Key systems / records | C10: Library management system, e-resource proxy, CCTV | H10: Partially Compliant | K10: =COUNTIF(L15:L38,"Partially Compliant") -> 0
A11: Inherent data risk | C11: Medium | H11: Non-Compliant | K11: =COUNTIF(L15:L38,"Non-Compliant") -> 0
H12: Not Applicable | K12: =COUNTIF(L15:L38,"Not Applicable") -> 0
H13: Compliance Score | K13: =_xlfn.IFERROR(AVERAGE(M15:M38),"")
A14: Ref | B14: CAR Area | C14: GAID / NDPA Reference | D14: Control Objective | E14: Audit Procedure | F14: Evidence to Obtain | G14: Risk | H14: Planned Start | I14: Planned End | J14: Auditor | K14: Status | L14: Compliance Rating | M14: Score | N14: Findings | O14: Recommendation | P14: Management Response / Owner | Q14: Target Date
A15: DEPT-LIB-01 | B15: ROPA | C15: GAID Art. 13(2)-(3), Art. 52; NDPA s.24(3) | D15: All processing activities of the unit are captured in the Record of Processing Activities (ROPA) submitted to the DPO. | E15: Walk through University Library's key processing (patron registration, circulation, e-resource authentication) and confirm each activity is captured in the ROPA with purpose, data categories, recipients and retention. | F15: Unit ROPA extract; process walkthrough notes | G15: High | H15: =$K$5 -> 46391 | I15: =$K$6 -> 46409 | K15: Not Started | M15: =IF(L15="Compliant",1,IF(L15="Partially Compliant",0.5,IF(L15="Non-Compliant",0,"")))
A16: DEPT-LIB-02 | B16: Data inventory & sensitive data | C16: NDPA s.30; GAID Art. 28(3)(d) | D16: Personal and sensitive personal data held by the unit is identified and classified. | E16: Inventory data held (Patron records, borrowing history, e-resource access logs); flag sensitive categories and confirm they are recorded as such. | F16: Data inventory; classification register | G16: High | H16: =$K$5 -> 46391 | I16: =$K$6 -> 46409 | K16: Not Started | M16: =IF(L16="Compliant",1,IF(L16="Partially Compliant",0.5,IF(L16="Non-Compliant",0,"")))
A17: DEPT-LIB-03 | B17: Lawful basis | C17: GAID Art. 16, 23; NDPA s.25 | D17: A documented lawful basis exists for each processing activity; legitimate interest supported by LIA. | E17: For each ROPA activity, confirm lawful basis is recorded and appropriate; where legitimate interest is used, inspect Schedule 8 LIA. | F17: Lawful basis register; LIAs | G17: High | H17: =$K$5 -> 46391 | I17: =$K$6 -> 46409 | K17: Not Started | M17: =IF(L17="Compliant",1,IF(L17="Partially Compliant",0.5,IF(L17="Non-Compliant",0,"")))
A18: DEPT-LIB-04 | B18: Consent (CAR disclosure) | C18: GAID Art. 17, 18(1)-(2); NDPA s.26 | D18: Consent is obtained and recorded where required (marketing, sensitive data, children, incompatible further processing, transfers, automated decisions) — CAR must state reliance. | E18: Identify Art. 18(1) activities in University Library; test consent capture, records and ease of withdrawal for a sample of 5. | F18: Consent forms/records; withdrawal mechanism | G18: High | H18: =$K$5 -> 46391 | I18: =$K$6 -> 46409 | K18: Not Started | M18: =IF(L18="Compliant",1,IF(L18="Partially Compliant",0.5,IF(L18="Non-Compliant",0,"")))
A19: DEPT-LIB-05 | B19: Privacy notice at collection | C19: GAID Art. 27; Art. 7(j)-(m); NDPA s.27 | D19: Data subjects receive clear privacy information at every collection point (forms, portals, surveys). | E19: Collect all forms/portals used by University Library; check each notice against Art. 27(3)(a)-(j). | F19: Forms; screenshots; notice checklist | G19: Medium | H19: =$K$5 -> 46391 | I19: =$K$6 -> 46409 | K19: Not Started | M19: =IF(L19="Compliant",1,IF(L19="Partially Compliant",0.5,IF(L19="Non-Compliant",0,"")))
A20: DEPT-LIB-06 | B20: Minimisation & purpose limitation | C20: GAID Art. 15 & Sch. 1; NDPA s.24(1)(b),(c) | D20: Only data necessary for the stated purpose is collected and used. | E20: Review fields on University Library forms and systems (Library management system, e-resource proxy, CCTV); identify excessive fields (e.g., religion, NIN, BVN) not justified by purpose. | F20: Form review worksheet | G20: Medium | H20: =$K$5 -> 46391 | I20: =$K$6 -> 46409 | K20: Not Started | M20: =IF(L20="Compliant",1,IF(L20="Partially Compliant",0.5,IF(L20="Non-Compliant",0,"")))
A21: DEPT-LIB-07 | B21: Retention & disposal | C21: GAID Art. 49(3)-(4); NDPA s.24(1)(d) | D21: Retention periods defined; data disposed of securely (default not later than 6 months after purpose ends unless justified). | E21: Obtain retention schedule; inspect archives/systems for data past retention; review disposal records (shredding/wiping). | F21: Retention schedule; disposal certificates | G21: Medium | H21: =$K$5 -> 46391 | I21: =$K$6 -> 46409 | K21: Not Started | M21: =IF(L21="Compliant",1,IF(L21="Partially Compliant",0.5,IF(L21="Non-Compliant",0,"")))
A22: DEPT-LIB-08 | B22: Accuracy & rectification | C22: GAID Art. 36; NDPA s.24(1)(e) | D22: Data subjects can verify and correct data; input errors by the unit corrected free of charge. | E22: Review rectification procedure (e.g., name/DOB corrections); sample 5 requests for timeliness and absence of fees for unit errors. | F22: Correction requests; procedure | G22: Medium | H22: =$K$5 -> 46391 | I22: =$K$6 -> 46409 | K22: Not Started | M22: =IF(L22="Compliant",1,IF(L22="Partially Compliant",0.5,IF(L22="Non-Compliant",0,"")))
A23: DEPT-LIB-09 | B23: Data subject rights | C23: GAID Art. 36-38, 40; NDPA s.34-38 | D23: Access, erasure, portability, objection requests and SNAGs are logged, escalated to the DPO and resolved on time. | E23: Enquire about requests received by University Library; test log and escalation to DPO. | F23: Rights request log; SNAG responses | G23: Medium | H23: =$K$5 -> 46391 | I23: =$K$6 -> 46409 | K23: Not Started | M23: =IF(L23="Compliant",1,IF(L23="Partially Compliant",0.5,IF(L23="Non-Compliant",0,"")))
A24: DEPT-LIB-10 | B24: Physical & access security | C24: NDPA s.39; GAID Art. 29 | D24: Physical records and system access are restricted on a need-to-know basis. | E24: Inspect records rooms/cabinets; review user access list for Library management system, e-resource proxy, CCTV and confirm leavers are removed. | F24: Access lists; site inspection photos | G24: High | H24: =$K$5 -> 46391 | I24: =$K$6 -> 46409 | K24: Not Started | M24: =IF(L24="Compliant",1,IF(L24="Partially Compliant",0.5,IF(L24="Non-Compliant",0,"")))
A25: DEPT-LIB-11 | B25: Technical security & devices | C25: GAID Art. 10(5), 29(2); NDPA s.39 | D25: Unit devices and online systems use authentication, encryption, updated software and are audited frequently. | E25: Sample 5 unit laptops/desktops: password, screen lock, encryption, antivirus, OS updates; check use of personal email/USB for personal data. | F25: Device checklist; screenshots | G25: High | H25: =$K$5 -> 46391 | I25: =$K$6 -> 46409 | K25: Not Started | M25: =IF(L25="Compliant",1,IF(L25="Partially Compliant",0.5,IF(L25="Non-Compliant",0,"")))
A26: DEPT-LIB-12 | B26: Third-party processors & DPAs | C26: GAID Art. 34; NDPA s.29 | D26: Vendors/partners processing personal data for University Library have Data Processing Agreements and were vetted. | E26: List third parties receiving data from University Library; inspect DPAs against Art. 34(2). | F26: Vendor list; DPAs | G26: High | H26: =$K$5 -> 46391 | I26: =$K$6 -> 46409 | K26: Not Started | M26: =IF(L26="Compliant",1,IF(L26="Partially Compliant",0.5,IF(L26="Non-Compliant",0,"")))
... A38: DEPT-LIB-24 | B38: E-resource vendors | C38: GAID Art. 34, 45 | D38: Foreign e-resource providers receiving user identifiers have transfer safeguards. | E38: List SSO/proxy integrations passing user data; inspect terms. | F38: Vendor terms | G38: Medium | H38: =$K$5 -> 46391 | I38: =$K$6 -> 46409 | K38: Not Started | M38: =IF(L38="Compliant",1,IF(L38="Partially Compliant",0.5,IF(L38="Non-Compliant",0,"")))
A40: Bold teal CAR Areas = controls specific to this unit. Base controls are listed on the 'CAR Framework' tab.

Sheet DEPT-Legal Unit
A1: Compliance Audit Work Plan — Legal Unit | N1: ← Back to Dashboard
A2: NDPA 2023 / GAID 2025 — Article 10 Compliance Audit Returns (CAR) | Audit year 2026 | CAR due 31 March 2027
A4: Unit | C4: Legal Unit | H4: Lead Auditor | K4: [Enter name]
A5: Unit type | C5: Department | H5: Planned Start | K5: 46391
A6: Reports to | C6: Registrar | H6: Planned End | K6: 46409
A7: Head of Unit | C7: [Enter name] | H7: Controls in plan | K7: =COUNTA(A15:A39) -> 25
A8: Data subjects | C8: Litigants, staff, students, contractors | H8: Completed | K8: =COUNTIF(K15:K39,"Completed") -> 0
A9: Key personal data | C9: Litigation files, contracts, legal opinions | H9: Compliant | K9: =COUNTIF(L15:L39,"Compliant") -> 0
A10: Key systems / records | C10: Legal files, contract register | H10: Partially Compliant | K10: =COUNTIF(L15:L39,"Partially Compliant") -> 0
A11: Inherent data risk | C11: Medium | H11: Non-Compliant | K11: =COUNTIF(L15:L39,"Non-Compliant") -> 0
H12: Not Applicable | K12: =COUNTIF(L15:L39,"Not Applicable") -> 0
H13: Compliance Score | K13: =_xlfn.IFERROR(AVERAGE(M15:M39),"")
A14: Ref | B14: CAR Area | C14: GAID / NDPA Reference | D14: Control Objective | E14: Audit Procedure | F14: Evidence to Obtain | G14: Risk | H14: Planned Start | I14: Planned End | J14: Auditor | K14: Status | L14: Compliance Rating | M14: Score | N14: Findings | O14: Recommendation | P14: Management Response / Owner | Q14: Target Date
A15: DEPT-LU-01 | B15: ROPA | C15: GAID Art. 13(2)-(3), Art. 52; NDPA s.24(3) | D15: All processing activities of the unit are captured in the Record of Processing Activities (ROPA) submitted to the DPO. | E15: Walk through Legal Unit's key processing (litigation, contract review, legal opinions) and confirm each activity is captured in the ROPA with purpose, data categories, recipients and retention. | F15: Unit ROPA extract; process walkthrough notes | G15: High | H15: =$K$5 -> 46391 | I15: =$K$6 -> 46409 | K15: Not Started | M15: =IF(L15="Compliant",1,IF(L15="Partially Compliant",0.5,IF(L15="Non-Compliant",0,"")))
A16: DEPT-LU-02 | B16: Data inventory & sensitive data | C16: NDPA s.30; GAID Art. 28(3)(d) | D16: Personal and sensitive personal data held by the unit is identified and classified. | E16: Inventory data held (Litigation files, contracts, legal opinions); flag sensitive categories and confirm they are recorded as such. | F16: Data inventory; classification register | G16: High | H16: =$K$5 -> 46391 | I16: =$K$6 -> 46409 | K16: Not Started | M16: =IF(L16="Compliant",1,IF(L16="Partially Compliant",0.5,IF(L16="Non-Compliant",0,"")))
A17: DEPT-LU-03 | B17: Lawful basis | C17: GAID Art. 16, 23; NDPA s.25 | D17: A documented lawful basis exists for each processing activity; legitimate interest supported by LIA. | E17: For each ROPA activity, confirm lawful basis is recorded and appropriate; where legitimate interest is used, inspect Schedule 8 LIA. | F17: Lawful basis register; LIAs | G17: High | H17: =$K$5 -> 46391 | I17: =$K$6 -> 46409 | K17: Not Started | M17: =IF(L17="Compliant",1,IF(L17="Partially Compliant",0.5,IF(L17="Non-Compliant",0,"")))
A18: DEPT-LU-04 | B18: Consent (CAR disclosure) | C18: GAID Art. 17, 18(1)-(2); NDPA s.26 | D18: Consent is obtained and recorded where required (marketing, sensitive data, children, incompatible further processing, transfers, automated decisions) — CAR must state reliance. | E18: Identify Art. 18(1) activities in Legal Unit; test consent capture, records and ease of withdrawal for a sample of 5. | F18: Consent forms/records; withdrawal mechanism | G18: High | H18: =$K$5 -> 46391 | I18: =$K$6 -> 46409 | K18: Not Started | M18: =IF(L18="Compliant",1,IF(L18="Partially Compliant",0.5,IF(L18="Non-Compliant",0,"")))
A19: DEPT-LU-05 | B19: Privacy notice at collection | C19: GAID Art. 27; Art. 7(j)-(m); NDPA s.27 | D19: Data subjects receive clear privacy information at every collection point (forms, portals, surveys). | E19: Collect all forms/portals used by Legal Unit; check each notice against Art. 27(3)(a)-(j). | F19: Forms; screenshots; notice checklist | G19: Medium | H19: =$K$5 -> 46391 | I19: =$K$6 -> 46409 | K19: Not Started | M19: =IF(L19="Compliant",1,IF(L19="Partially Compliant",0.5,IF(L19="Non-Compliant",0,"")))
A20: DEPT-LU-06 | B20: Minimisation & purpose limitation | C20: GAID Art. 15 & Sch. 1; NDPA s.24(1)(b),(c) | D20: Only data necessary for the stated purpose is collected and used. | E20: Review fields on Legal Unit forms and systems (Legal files, contract register); identify excessive fields (e.g., religion, NIN, BVN) not justified by purpose. | F20: Form review worksheet | G20: Medium | H20: =$K$5 -> 46391 | I20: =$K$6 -> 46409 | K20: Not Started | M20: =IF(L20="Compliant",1,IF(L20="Partially Compliant",0.5,IF(L20="Non-Compliant",0,"")))
A21: DEPT-LU-07 | B21: Retention & disposal | C21: GAID Art. 49(3)-(4); NDPA s.24(1)(d) | D21: Retention periods defined; data disposed of securely (default not later than 6 months after purpose ends unless justified). | E21: Obtain retention schedule; inspect archives/systems for data past retention; review disposal records (shredding/wiping). | F21: Retention schedule; disposal certificates | G21: Medium | H21: =$K$5 -> 46391 | I21: =$K$6 -> 46409 | K21: Not Started | M21: =IF(L21="Compliant",1,IF(L21="Partially Compliant",0.5,IF(L21="Non-Compliant",0,"")))
A22: DEPT-LU-08 | B22: Accuracy & rectification | C22: GAID Art. 36; NDPA s.24(1)(e) | D22: Data subjects can verify and correct data; input errors by the unit corrected free of charge. | E22: Review rectification procedure (e.g., name/DOB corrections); sample 5 requests for timeliness and absence of fees for unit errors. | F22: Correction requests; procedure | G22: Medium | H22: =$K$5 -> 46391 | I22: =$K$6 -> 46409 | K22: Not Started | M22: =IF(L22="Compliant",1,IF(L22="Partially Compliant",0.5,IF(L22="Non-Compliant",0,"")))
A23: DEPT-LU-09 | B23: Data subject rights | C23: GAID Art. 36-38, 40; NDPA s.34-38 | D23: Access, erasure, portability, objection requests and SNAGs are logged, escalated to the DPO and resolved on time. | E23: Enquire about requests received by Legal Unit; test log and escalation to DPO. | F23: Rights request log; SNAG responses | G23: Medium | H23: =$K$5 -> 46391 | I23: =$K$6 -> 46409 | K23: Not Started | M23: =IF(L23="Compliant",1,IF(L23="Partially Compliant",0.5,IF(L23="Non-Compliant",0,"")))
A24: DEPT-LU-10 | B24: Physical & access security | C24: NDPA s.39; GAID Art. 29 | D24: Physical records and system access are restricted on a need-to-know basis. | E24: Inspect records rooms/cabinets; review user access list for Legal files, contract register and confirm leavers are removed. | F24: Access lists; site inspection photos | G24: High | H24: =$K$5 -> 46391 | I24: =$K$6 -> 46409 | K24: Not Started | M24: =IF(L24="Compliant",1,IF(L24="Partially Compliant",0.5,IF(L24="Non-Compliant",0,"")))
A25: DEPT-LU-11 | B25: Technical security & devices | C25: GAID Art. 10(5), 29(2); NDPA s.39 | D25: Unit devices and online systems use authentication, encryption, updated software and are audited frequently. | E25: Sample 5 unit laptops/desktops: password, screen lock, encryption, antivirus, OS updates; check use of personal email/USB for personal data. | F25: Device checklist; screenshots | G25: High | H25: =$K$5 -> 46391 | I25: =$K$6 -> 46409 | K25: Not Started | M25: =IF(L25="Compliant",1,IF(L25="Partially Compliant",0.5,IF(L25="Non-Compliant",0,"")))
A26: DEPT-LU-12 | B26: Third-party processors & DPAs | C26: GAID Art. 34; NDPA s.29 | D26: Vendors/partners processing personal data for Legal Unit have Data Processing Agreements and were vetted. | E26: List third parties receiving data from Legal Unit; inspect DPAs against Art. 34(2). | F26: Vendor list; DPAs | G26: High | H26: =$K$5 -> 46391 | I26: =$K$6 -> 46409 | K26: Not Started | M26: =IF(L26="Compliant",1,IF(L26="Partially Compliant",0.5,IF(L26="Non-Compliant",0,"")))
... A39: DEPT-LU-25 | B39: Oust clauses | C39: GAID Art. 21(4) | D39: Contracts do not oust jurisdiction of Nigerian courts or NDPC on data processing. | E39: Review foreign vendor contracts for governing law/jurisdiction clauses. | F39: Vendor contracts | G39: Medium | H39: =$K$5 -> 46391 | I39: =$K$6 -> 46409 | K39: Not Started | M39: =IF(L39="Compliant",1,IF(L39="Partially Compliant",0.5,IF(L39="Non-Compliant",0,"")))
A41: Bold teal CAR Areas = controls specific to this unit. Base controls are listed on the 'CAR Framework' tab.

Sheet DEPT-Info & PR
A1: Compliance Audit Work Plan — Information, Public Relations & Protocol | N1: ← Back to Dashboard
A2: NDPA 2023 / GAID 2025 — Article 10 Compliance Audit Returns (CAR) | Audit year 2026 | CAR due 31 March 2027
A4: Unit | C4: Information, Public Relations & Protocol | H4: Lead Auditor | K4: [Enter name]
A5: Unit type | C5: Department | H5: Planned Start | K5: 46391
A6: Reports to | C6: Vice-Chancellor | H6: Planned End | K6: 46409
A7: Head of Unit | C7: [Enter name] | H7: Controls in plan | K7: =COUNTA(A15:A38) -> 24
A8: Data subjects | C8: Students, staff, event attendees, social media audience | H8: Completed | K8: =COUNTIF(K15:K38,"Completed") -> 0
A9: Key personal data | C9: Photos, videos, names in publications, website visitor data | H9: Compliant | K9: =COUNTIF(L15:L38,"Compliant") -> 0
A10: Key systems / records | C10: Website, social media pages, bulk SMS, CMS | H10: Partially Compliant | K10: =COUNTIF(L15:L38,"Partially Compliant") -> 0
A11: Inherent data risk | C11: Medium | H11: Non-Compliant | K11: =COUNTIF(L15:L38,"Non-Compliant") -> 0
H12: Not Applicable | K12: =COUNTIF(L15:L38,"Not Applicable") -> 0
H13: Compliance Score | K13: =_xlfn.IFERROR(AVERAGE(M15:M38),"")
A14: Ref | B14: CAR Area | C14: GAID / NDPA Reference | D14: Control Objective | E14: Audit Procedure | F14: Evidence to Obtain | G14: Risk | H14: Planned Start | I14: Planned End | J14: Auditor | K14: Status | L14: Compliance Rating | M14: Score | N14: Findings | O14: Recommendation | P14: Management Response / Owner | Q14: Target Date
A15: DEPT-IP-01 | B15: ROPA | C15: GAID Art. 13(2)-(3), Art. 52; NDPA s.24(3) | D15: All processing activities of the unit are captured in the Record of Processing Activities (ROPA) submitted to the DPO. | E15: Walk through Information, Public Relations & Protocol's key processing (event coverage, publications, social media, website management) and confirm each activity is captured in the ROPA with purpose, data categories, recipients and retention. | F15: Unit ROPA extract; process walkthrough notes | G15: High | H15: =$K$5 -> 46391 | I15: =$K$6 -> 46409 | K15: Not Started | M15: =IF(L15="Compliant",1,IF(L15="Partially Compliant",0.5,IF(L15="Non-Compliant",0,"")))
A16: DEPT-IP-02 | B16: Data inventory & sensitive data | C16: NDPA s.30; GAID Art. 28(3)(d) | D16: Personal and sensitive personal data held by the unit is identified and classified. | E16: Inventory data held (Photos, videos, names in publications, website visitor data); flag sensitive categories and confirm they are recorded as such. | F16: Data inventory; classification register | G16: High | H16: =$K$5 -> 46391 | I16: =$K$6 -> 46409 | K16: Not Started | M16: =IF(L16="Compliant",1,IF(L16="Partially Compliant",0.5,IF(L16="Non-Compliant",0,"")))
A17: DEPT-IP-03 | B17: Lawful basis | C17: GAID Art. 16, 23; NDPA s.25 | D17: A documented lawful basis exists for each processing activity; legitimate interest supported by LIA. | E17: For each ROPA activity, confirm lawful basis is recorded and appropriate; where legitimate interest is used, inspect Schedule 8 LIA. | F17: Lawful basis register; LIAs | G17: High | H17: =$K$5 -> 46391 | I17: =$K$6 -> 46409 | K17: Not Started | M17: =IF(L17="Compliant",1,IF(L17="Partially Compliant",0.5,IF(L17="Non-Compliant",0,"")))
A18: DEPT-IP-04 | B18: Consent (CAR disclosure) | C18: GAID Art. 17, 18(1)-(2); NDPA s.26 | D18: Consent is obtained and recorded where required (marketing, sensitive data, children, incompatible further processing, transfers, automated decisions) — CAR must state reliance. | E18: Identify Art. 18(1) activities in Information, Public Relations & Protocol; test consent capture, records and ease of withdrawal for a sample of 5. | F18: Consent forms/records; withdrawal mechanism | G18: High | H18: =$K$5 -> 46391 | I18: =$K$6 -> 46409 | K18: Not Started | M18: =IF(L18="Compliant",1,IF(L18="Partially Compliant",0.5,IF(L18="Non-Compliant",0,"")))
A19: DEPT-IP-05 | B19: Privacy notice at collection | C19: GAID Art. 27; Art. 7(j)-(m); NDPA s.27 | D19: Data subjects receive clear privacy information at every collection point (forms, portals, surveys). | E19: Collect all forms/portals used by Information, Public Relations & Protocol; check each notice against Art. 27(3)(a)-(j). | F19: Forms; screenshots; notice checklist | G19: Medium | H19: =$K$5 -> 46391 | I19: =$K$6 -> 46409 | K19: Not Started | M19: =IF(L19="Compliant",1,IF(L19="Partially Compliant",0.5,IF(L19="Non-Compliant",0,"")))
A20: DEPT-IP-06 | B20: Minimisation & purpose limitation | C20: GAID Art. 15 & Sch. 1; NDPA s.24(1)(b),(c) | D20: Only data necessary for the stated purpose is collected and used. | E20: Review fields on Information, Public Relations & Protocol forms and systems (Website, social media pages, bulk SMS, CMS); identify excessive fields (e.g., religion, NIN, BVN) not justified by purpose. | F20: Form review worksheet | G20: Medium | H20: =$K$5 -> 46391 | I20: =$K$6 -> 46409 | K20: Not Started | M20: =IF(L20="Compliant",1,IF(L20="Partially Compliant",0.5,IF(L20="Non-Compliant",0,"")))
A21: DEPT-IP-07 | B21: Retention & disposal | C21: GAID Art. 49(3)-(4); NDPA s.24(1)(d) | D21: Retention periods defined; data disposed of securely (default not later than 6 months after purpose ends unless justified). | E21: Obtain retention schedule; inspect archives/systems for data past retention; review disposal records (shredding/wiping). | F21: Retention schedule; disposal certificates | G21: Medium | H21: =$K$5 -> 46391 | I21: =$K$6 -> 46409 | K21: Not Started | M21: =IF(L21="Compliant",1,IF(L21="Partially Compliant",0.5,IF(L21="Non-Compliant",0,"")))
A22: DEPT-IP-08 | B22: Accuracy & rectification | C22: GAID Art. 36; NDPA s.24(1)(e) | D22: Data subjects can verify and correct data; input errors by the unit corrected free of charge. | E22: Review rectification procedure (e.g., name/DOB corrections); sample 5 requests for timeliness and absence of fees for unit errors. | F22: Correction requests; procedure | G22: Medium | H22: =$K$5 -> 46391 | I22: =$K$6 -> 46409 | K22: Not Started | M22: =IF(L22="Compliant",1,IF(L22="Partially Compliant",0.5,IF(L22="Non-Compliant",0,"")))
A23: DEPT-IP-09 | B23: Data subject rights | C23: GAID Art. 36-38, 40; NDPA s.34-38 | D23: Access, erasure, portability, objection requests and SNAGs are logged, escalated to the DPO and resolved on time. | E23: Enquire about requests received by Information, Public Relations & Protocol; test log and escalation to DPO. | F23: Rights request log; SNAG responses | G23: Medium | H23: =$K$5 -> 46391 | I23: =$K$6 -> 46409 | K23: Not Started | M23: =IF(L23="Compliant",1,IF(L23="Partially Compliant",0.5,IF(L23="Non-Compliant",0,"")))
A24: DEPT-IP-10 | B24: Physical & access security | C24: NDPA s.39; GAID Art. 29 | D24: Physical records and system access are restricted on a need-to-know basis. | E24: Inspect records rooms/cabinets; review user access list for Website, social media pages, bulk SMS, CMS and confirm leavers are removed. | F24: Access lists; site inspection photos | G24: High | H24: =$K$5 -> 46391 | I24: =$K$6 -> 46409 | K24: Not Started | M24: =IF(L24="Compliant",1,IF(L24="Partially Compliant",0.5,IF(L24="Non-Compliant",0,"")))
A25: DEPT-IP-11 | B25: Technical security & devices | C25: GAID Art. 10(5), 29(2); NDPA s.39 | D25: Unit devices and online systems use authentication, encryption, updated software and are audited frequently. | E25: Sample 5 unit laptops/desktops: password, screen lock, encryption, antivirus, OS updates; check use of personal email/USB for personal data. | F25: Device checklist; screenshots | G25: High | H25: =$K$5 -> 46391 | I25: =$K$6 -> 46409 | K25: Not Started | M25: =IF(L25="Compliant",1,IF(L25="Partially Compliant",0.5,IF(L25="Non-Compliant",0,"")))
A26: DEPT-IP-12 | B26: Third-party processors & DPAs | C26: GAID Art. 34; NDPA s.29 | D26: Vendors/partners processing personal data for Information, Public Relations & Protocol have Data Processing Agreements and were vetted. | E26: List third parties receiving data from Information, Public Relations & Protocol; inspect DPAs against Art. 34(2). | F26: Vendor list; DPAs | G26: High | H26: =$K$5 -> 46391 | I26: =$K$6 -> 46409 | K26: Not Started | M26: =IF(L26="Compliant",1,IF(L26="Partially Compliant",0.5,IF(L26="Non-Compliant",0,"")))
... A38: DEPT-IP-24 | B38: Website cookies | C38: GAID Art. 19; Art. 7(l) | D38: Website cookie banner is conspicuous, not at page bottom, with accept/reject choices. | E38: Inspect website on desktop and mobile; review analytics/tracking tools used. | F38: Screenshots; tag inventory | G38: High | H38: =$K$5 -> 46391 | I38: =$K$6 -> 46409 | K38: Not Started | M38: =IF(L38="Compliant",1,IF(L38="Partially Compliant",0.5,IF(L38="Non-Compliant",0,"")))
A40: Bold teal CAR Areas = controls specific to this unit. Base controls are listed on the 'CAR Framework' tab.

Sheet DEPT-Procurement
A1: Compliance Audit Work Plan — Procurement Department | N1: ← Back to Dashboard
A2: NDPA 2023 / GAID 2025 — Article 10 Compliance Audit Returns (CAR) | Audit year 2026 | CAR due 31 March 2027
A4: Unit | C4: Procurement Department | H4: Lead Auditor | K4: [Enter name]
A5: Unit type | C5: Department | H5: Planned Start | K5: 46391
A6: Reports to | C6: Vice-Chancellor | H6: Planned End | K6: 46409
A7: Head of Unit | C7: [Enter name] | H7: Controls in plan | K7: =COUNTA(A15:A37) -> 23
A8: Data subjects | C8: Bidders, vendors, contractors | H8: Completed | K8: =COUNTIF(K15:K37,"Completed") -> 0
A9: Key personal data | C9: Bidder directors' IDs, tax & bank details, CVs of key personnel | H9: Compliant | K9: =COUNTIF(L15:L37,"Compliant") -> 0
A10: Key systems / records | C10: Vendor register, tender files | H10: Partially Compliant | K10: =COUNTIF(L15:L37,"Partially Compliant") -> 0
A11: Inherent data risk | C11: Medium | H11: Non-Compliant | K11: =COUNTIF(L15:L37,"Non-Compliant") -> 0
H12: Not Applicable | K12: =COUNTIF(L15:L37,"Not Applicable") -> 0
H13: Compliance Score | K13: =_xlfn.IFERROR(AVERAGE(M15:M37),"")
A14: Ref | B14: CAR Area | C14: GAID / NDPA Reference | D14: Control Objective | E14: Audit Procedure | F14: Evidence to Obtain | G14: Risk | H14: Planned Start | I14: Planned End | J14: Auditor | K14: Status | L14: Compliance Rating | M14: Score | N14: Findings | O14: Recommendation | P14: Management Response / Owner | Q14: Target Date
A15: DEPT-PRO-01 | B15: ROPA | C15: GAID Art. 13(2)-(3), Art. 52; NDPA s.24(3) | D15: All processing activities of the unit are captured in the Record of Processing Activities (ROPA) submitted to the DPO. | E15: Walk through Procurement Department's key processing (tendering, vendor registration, contract award publication) and confirm each activity is captured in the ROPA with purpose, data categories, recipients and retention. | F15: Unit ROPA extract; process walkthrough notes | G15: High | H15: =$K$5 -> 46391 | I15: =$K$6 -> 46409 | K15: Not Started | M15: =IF(L15="Compliant",1,IF(L15="Partially Compliant",0.5,IF(L15="Non-Compliant",0,"")))
